Workbook

Sheet README
A1: MPG Cost Estimating Relationship (CER): the math behind the deck, live
A3: Purpose: every statistic quoted in the MPG Prediction Deck is recomputed here as an Excel formula over the actual data, so the
A4: coefficients, R-squared, F, t, p, nested F-tests, elasticities, and the 50-year normalization can be inspected and recalculated on demand.
A6: Sheets
A7: Data: the 1,285 Model Year 2024 model types in the final CER (775 gasoline/diesel, 250 hybrid, 260 battery-electric) with log and dummy columns.
A8: Data_Combustion: the 1,025 combustion-only rows used by the original (combustion-only) CER, alternative A.
A9: CER: the final equation ln(MPG) = b0 + b1 ln(weight) + b2 ln(HP) + b3 hybrid + b4 electric, fit with LINEST; t, p, VIF, elasticities, prediction band, outliers.
A10: Alternatives: specifications A through E, each fit with LINEST, and the nested F-tests that decided between them.
A11: Normalization: the 50-year fleet series re-expressed at 2024 weight and horsepower using the CER's own elasticities, trend fit, and 2045 projection.
A12: Class Productivity: figs 43, 45, 46: class series 1975 to 2024, in-class BEV share, live BEV backing-out, both normalizations, LINEST trends, R-squared, 2045 projections.
A13: EV Productivity: fig 44: the Tesla fleet series (also the BEV proxy), normalized to constant weight, trend and R-squared.
A14: Diffusion: the technology S-curves behind slide 7: share data for five technologies, the logistic parameters, live fitted curves, R-squared, 10-to-90% years, projections, and an Excel cross-check of k and t0.
... A26: DATA_SOURCES.md, github.com/SCherwonik/OS3180.

Sheet Data
A1: carline | B1: manufacturer | C1: powertrain | D1: MPG or MPGe (unadjusted 2-cycle) | E1: weight_lbs | F1: horsepower | G1: footprint_sqft | H1: hp_source | I1: ln_mpg | J1: ln_weight | K1: ln_hp | L1: hybrid | M1: bev | N1: footprint (spec B block) | O1: electrified | P1: ordinal_0_1_2 | Q1: C: ln_weight | R1: C: ln_hp | S1: C: footprint | T1: C: electrified | U1: D: ln_weight | V1: D: ln_hp | W1: D: footprint | X1: D: ordinal | Y1: E: ln_weight | Z1: E: ln_hp | AA1: E: footprint | AB1: E: hybrid | AC1: E: bev | AD1: E: bev x ln_weight | AE1: E: bev x ln_hp | AF1: E: bev x footprint | AG1: VIF ln_hp: ln_weight | AH1: VIF ln_hp: hybrid | AI1: VIF ln_hp: bev | AJ1: VIF hybrid: ln_weight | AK1: VIF hybrid: ln_hp | AL1: VIF hybrid: bev | AM1: pred ln_mpg (CER) | AN1: pred MPG (CER) | AO1: residual (CER) | AP1: pred ln_mpg (spec C) | AQ1: residual (spec C)
A2: DB12 V8 | B2: Aston Martin Lagonda | C2: gas_diesel | D2: 22.4729 | E2: 4500 | F2: 680 | G2: 50 | H2: FE file ENG_RATED_HP | I2: =LN(D2) -> 3.1123101 | J2: =LN(E2) -> 8.4118327 | K2: =LN(F2) -> 6.5220928 | L2: 0 | M2: 0 | N2: =G2 -> 50 | O2: =L2+M2 -> 0 | P2: =L2+2*M2 -> 0 | Q2: =J2 -> 8.4118327 | R2: =K2 -> 6.5220928 | S2: =G2 -> 50 | T2: =O2 -> 0 | U2: =J2 -> 8.4118327 | V2: =K2 -> 6.5220928 | W2: =G2 -> 50 | X2: =P2 -> 0 | Y2: =J2 -> 8.4118327 | Z2: =K2 -> 6.5220928 | AA2: =G2 -> 50 | AB2: =L2 -> 0 | AC2: =M2 -> 0 | AD2: =M2*J2 -> 0 | AE2: =M2*K2 -> 0 | AF2: =M2*G2 -> 0 | AG2: =J2 -> 8.4118327 | AH2: =L2 -> 0 | AI2: =M2 -> 0 | AJ2: =J2 -> 8.4118327 | AK2: =K2 -> 6.5220928 | AL2: =M2 -> 0 | AM2: =CER!$C$7+CER!$C$8*J2+CER!$C$9*K2+CER!$C$10*L2+CER!$C$11*M2 -> 3.0433906 | AN2: =EXP(AM2) -> 20.976245 | AO2: =I2-AM2 -> 0.068919534 | AP2: =Alternatives!$F$25+Alternatives!$F$26*J2+Alternatives!$F$27*K2+Alternatives!$F$28*G2+Alternatives!$F$29*O2 -> 3.1715446 | AQ2: =I2-AP2 -> -0.059234477
A3: Valour | B3: Aston Martin Lagonda | C3: gas_diesel | D3: 18.3624 | E3: 4000 | F3: 715 | G3: 48.2 | H3: FE file ENG_RATED_HP | I3: =LN(D3) -> 2.9103051 | J3: =LN(E3) -> 8.2940496 | K3: =LN(F3) -> 6.5722825 | L3: 0 | M3: 0 | N3: =G3 -> 48.2 | O3: =L3+M3 -> 0 | P3: =L3+2*M3 -> 0 | Q3: =J3 -> 8.2940496 | R3: =K3 -> 6.5722825 | S3: =G3 -> 48.2 | T3: =O3 -> 0 | U3: =J3 -> 8.2940496 | V3: =K3 -> 6.5722825 | W3: =G3 -> 48.2 | X3: =P3 -> 0 | Y3: =J3 -> 8.2940496 | Z3: =K3 -> 6.5722825 | AA3: =G3 -> 48.2 | AB3: =L3 -> 0 | AC3: =M3 -> 0 | AD3: =M3*J3 -> 0 | AE3: =M3*K3 -> 0 | AF3: =M3*G3 -> 0 | AG3: =J3 -> 8.2940496 | AH3: =L3 -> 0 | AI3: =M3 -> 0 | AJ3: =J3 -> 8.2940496 | AK3: =K3 -> 6.5722825 | AL3: =M3 -> 0 | AM3: =CER!$C$7+CER!$C$8*J3+CER!$C$9*K3+CER!$C$10*L3+CER!$C$11*M3 -> 3.0781949 | AN3: =EXP(AM3) -> 21.719161 | AO3: =I3-AM3 -> -0.16788977 | AP3: =Alternatives!$F$25+Alternatives!$F$26*J3+Alternatives!$F$27*K3+Alternatives!$F$28*G3+Alternatives!$F$29*O3 -> 3.1380119 | AQ3: =I3-AP3 -> -0.22770684
A4: DBX V8 | B4: Aston Martin Lagonda | C4: gas_diesel | D4: 20.6665 | E4: 5500 | F4: 550 | G4: 55.4 | H4: FE file ENG_RATED_HP | I4: =LN(D4) -> 3.028514 | J4: =LN(E4) -> 8.6125034 | K4: =LN(F4) -> 6.3099183 | L4: 0 | M4: 0 | N4: =G4 -> 55.4 | O4: =L4+M4 -> 0 | P4: =L4+2*M4 -> 0 | Q4: =J4 -> 8.6125034 | R4: =K4 -> 6.3099183 | S4: =G4 -> 55.4 | T4: =O4 -> 0 | U4: =J4 -> 8.6125034 | V4: =K4 -> 6.3099183 | W4: =G4 -> 55.4 | X4: =P4 -> 0 | Y4: =J4 -> 8.6125034 | Z4: =K4 -> 6.3099183 | AA4: =G4 -> 55.4 | AB4: =L4 -> 0 | AC4: =M4 -> 0 | AD4: =M4*J4 -> 0 | AE4: =M4*K4 -> 0 | AF4: =M4*G4 -> 0 | AG4: =J4 -> 8.6125034 | AH4: =L4 -> 0 | AI4: =M4 -> 0 | AJ4: =J4 -> 8.6125034 | AK4: =K4 -> 6.3099183 | AL4: =M4 -> 0 | AM4: =CER!$C$7+CER!$C$8*J4+CER!$C$9*K4+CER!$C$10*L4+CER!$C$11*M4 -> 3.0308256 | AN4: =EXP(AM4) -> 20.714327 | AO4: =I4-AM4 -> -0.0023115748 | AP4: =Alternatives!$F$25+Alternatives!$F$26*J4+Alternatives!$F$27*K4+Alternatives!$F$28*G4+Alternatives!$F$29*O4 -> 3.2320323 | AQ4: =I4-AP4 -> -0.20351825
A5: DBX 707 | B5: Aston Martin Lagonda | C5: gas_diesel | D5: 21.5837 | E5: 5500 | F5: 707 | G5: 55.4 | H5: FE file ENG_RATED_HP | I5: =LN(D5) -> 3.0719384 | J5: =LN(E5) -> 8.6125034 | K5: =LN(F5) -> 6.5610307 | L5: 0 | M5: 0 | N5: =G5 -> 55.4 | O5: =L5+M5 -> 0 | P5: =L5+2*M5 -> 0 | Q5: =J5 -> 8.6125034 | R5: =K5 -> 6.5610307 | S5: =G5 -> 55.4 | T5: =O5 -> 0 | U5: =J5 -> 8.6125034 | V5: =K5 -> 6.5610307 | W5: =G5 -> 55.4 | X5: =P5 -> 0 | Y5: =J5 -> 8.6125034 | Z5: =K5 -> 6.5610307 | AA5: =G5 -> 55.4 | AB5: =L5 -> 0 | AC5: =M5 -> 0 | AD5: =M5*J5 -> 0 | AE5: =M5*K5 -> 0 | AF5: =M5*G5 -> 0 | AG5: =J5 -> 8.6125034 | AH5: =L5 -> 0 | AI5: =M5 -> 0 | AJ5: =J5 -> 8.6125034 | AK5: =K5 -> 6.5610307 | AL5: =M5 -> 0 | AM5: =CER!$C$7+CER!$C$8*J5+CER!$C$9*K5+CER!$C$10*L5+CER!$C$11*M5 -> 2.9381793 | AN5: =EXP(AM5) -> 18.881437 | AO5: =I5-AM5 -> 0.13375913 | AP5: =Alternatives!$F$25+Alternatives!$F$26*J5+Alternatives!$F$27*K5+Alternatives!$F$28*G5+Alternatives!$F$29*O5 -> 3.1652088 | AQ5: =I5-AP5 -> -0.093270373
A6: X3 xDrive30i | B6: BMW | C6: gas_diesel | D6: 31.5873 | E6: 4500 | F6: 248 | G6: 49.6 | H6: FE file ENG_RATED_HP | I6: =LN(D6) -> 3.4527551 | J6: =LN(E6) -> 8.4118327 | K6: =LN(F6) -> 5.5134287 | L6: 0 | M6: 0 | N6: =G6 -> 49.6 | O6: =L6+M6 -> 0 | P6: =L6+2*M6 -> 0 | Q6: =J6 -> 8.4118327 | R6: =K6 -> 5.5134287 | S6: =G6 -> 49.6 | T6: =O6 -> 0 | U6: =J6 -> 8.4118327 | V6: =K6 -> 5.5134287 | W6: =G6 -> 49.6 | X6: =P6 -> 0 | Y6: =J6 -> 8.4118327 | Z6: =K6 -> 5.5134287 | AA6: =G6 -> 49.6 | AB6: =L6 -> 0 | AC6: =M6 -> 0 | AD6: =M6*J6 -> 0 | AE6: =M6*K6 -> 0 | AF6: =M6*G6 -> 0 | AG6: =J6 -> 8.4118327 | AH6: =L6 -> 0 | AI6: =M6 -> 0 | AJ6: =J6 -> 8.4118327 | AK6: =K6 -> 5.5134287 | AL6: =M6 -> 0 | AM6: =CER!$C$7+CER!$C$8*J6+CER!$C$9*K6+CER!$C$10*L6+CER!$C$11*M6 -> 3.4155309 | AN6: =EXP(AM6) -> 30.433101 | AO6: =I6-AM6 -> 0.037224275 | AP6: =Alternatives!$F$25+Alternatives!$F$26*J6+Alternatives!$F$27*K6+Alternatives!$F$28*G6+Alternatives!$F$29*O6 -> 3.4451631 | AQ6: =I6-AP6 -> 0.0075920412
A7: X4 xDrive30i | B7: BMW | C7: gas_diesel | D7: 31.5873 | E7: 4500 | F7: 248 | G7: 50.7 | H7: FE file ENG_RATED_HP | I7: =LN(D7) -> 3.4527551 | J7: =LN(E7) -> 8.4118327 | K7: =LN(F7) -> 5.5134287 | L7: 0 | M7: 0 | N7: =G7 -> 50.7 | O7: =L7+M7 -> 0 | P7: =L7+2*M7 -> 0 | Q7: =J7 -> 8.4118327 | R7: =K7 -> 5.5134287 | S7: =G7 -> 50.7 | T7: =O7 -> 0 | U7: =J7 -> 8.4118327 | V7: =K7 -> 5.5134287 | W7: =G7 -> 50.7 | X7: =P7 -> 0 | Y7: =J7 -> 8.4118327 | Z7: =K7 -> 5.5134287 | AA7: =G7 -> 50.7 | AB7: =L7 -> 0 | AC7: =M7 -> 0 | AD7: =M7*J7 -> 0 | AE7: =M7*K7 -> 0 | AF7: =M7*G7 -> 0 | AG7: =J7 -> 8.4118327 | AH7: =L7 -> 0 | AI7: =M7 -> 0 | AJ7: =J7 -> 8.4118327 | AK7: =K7 -> 5.5134287 | AL7: =M7 -> 0 | AM7: =CER!$C$7+CER!$C$8*J7+CER!$C$9*K7+CER!$C$10*L7+CER!$C$11*M7 -> 3.4155309 | AN7: =EXP(AM7) -> 30.433101 | AO7: =I7-AM7 -> 0.037224275 | AP7: =Alternatives!$F$25+Alternatives!$F$26*J7+Alternatives!$F$27*K7+Alternatives!$F$28*G7+Alternatives!$F$29*O7 -> 3.4308551 | AQ7: =I7-AP7 -> 0.021900087
A8: X3 sDrive30i | B8: BMW | C8: gas_diesel | D8: 33.2063 | E8: 4500 | F8: 248 | G8: 50.2 | H8: FE file ENG_RATED_HP | I8: =LN(D8) -> 3.5027396 | J8: =LN(E8) -> 8.4118327 | K8: =LN(F8) -> 5.5134287 | L8: 0 | M8: 0 | N8: =G8 -> 50.2 | O8: =L8+M8 -> 0 | P8: =L8+2*M8 -> 0 | Q8: =J8 -> 8.4118327 | R8: =K8 -> 5.5134287 | S8: =G8 -> 50.2 | T8: =O8 -> 0 | U8: =J8 -> 8.4118327 | V8: =K8 -> 5.5134287 | W8: =G8 -> 50.2 | X8: =P8 -> 0 | Y8: =J8 -> 8.4118327 | Z8: =K8 -> 5.5134287 | AA8: =G8 -> 50.2 | AB8: =L8 -> 0 | AC8: =M8 -> 0 | AD8: =M8*J8 -> 0 | AE8: =M8*K8 -> 0 | AF8: =M8*G8 -> 0 | AG8: =J8 -> 8.4118327 | AH8: =L8 -> 0 | AI8: =M8 -> 0 | AJ8: =J8 -> 8.4118327 | AK8: =K8 -> 5.5134287 | AL8: =M8 -> 0 | AM8: =CER!$C$7+CER!$C$8*J8+CER!$C$9*K8+CER!$C$10*L8+CER!$C$11*M8 -> 3.4155309 | AN8: =EXP(AM8) -> 30.433101 | AO8: =I8-AM8 -> 0.08720875 | AP8: =Alternatives!$F$25+Alternatives!$F$26*J8+Alternatives!$F$27*K8+Alternatives!$F$28*G8+Alternatives!$F$29*O8 -> 3.4373587 | AQ8: =I8-AP8 -> 0.065380906
A9: M850i xDrive Coupe | B9: BMW | C9: gas_diesel | D9: 25.0424 | E9: 4500 | F9: 523 | G9: 49.7 | H9: FE file ENG_RATED_HP | I9: =LN(D9) -> 3.2205704 | J9: =LN(E9) -> 8.4118327 | K9: =LN(F9) -> 6.2595815 | L9: 0 | M9: 0 | N9: =G9 -> 49.7 | O9: =L9+M9 -> 0 | P9: =L9+2*M9 -> 0 | Q9: =J9 -> 8.4118327 | R9: =K9 -> 6.2595815 | S9: =G9 -> 49.7 | T9: =O9 -> 0 | U9: =J9 -> 8.4118327 | V9: =K9 -> 6.2595815 | W9: =G9 -> 49.7 | X9: =P9 -> 0 | Y9: =J9 -> 8.4118327 | Z9: =K9 -> 6.2595815 | AA9: =G9 -> 49.7 | AB9: =L9 -> 0 | AC9: =M9 -> 0 | AD9: =M9*J9 -> 0 | AE9: =M9*K9 -> 0 | AF9: =M9*G9 -> 0 | AG9: =J9 -> 8.4118327 | AH9: =L9 -> 0 | AI9: =M9 -> 0 | AJ9: =J9 -> 8.4118327 | AK9: =K9 -> 6.2595815 | AL9: =M9 -> 0 | AM9: =CER!$C$7+CER!$C$8*J9+CER!$C$9*K9+CER!$C$10*L9+CER!$C$11*M9 -> 3.1402425 | AN9: =EXP(AM9) -> 23.10947 | AO9: =I9-AM9 -> 0.080327877 | AP9: =Alternatives!$F$25+Alternatives!$F$26*J9+Alternatives!$F$27*K9+Alternatives!$F$28*G9+Alternatives!$F$29*O9 -> 3.2453037 | AQ9: =I9-AP9 -> -0.024733304
A10: M850i xDrive Convertible | B10: BMW | C10: gas_diesel | D10: 24.9997 | E10: 5000 | F10: 523 | G10: 49.7 | H10: FE file ENG_RATED_HP | I10: =LN(D10) -> 3.2188638 | J10: =LN(E10) -> 8.5171932 | K10: =LN(F10) -> 6.2595815 | L10: 0 | M10: 0 | N10: =G10 -> 49.7 | O10: =L10+M10 -> 0 | P10: =L10+2*M10 -> 0 | Q10: =J10 -> 8.5171932 | R10: =K10 -> 6.2595815 | S10: =G10 -> 49.7 | T10: =O10 -> 0 | U10: =J10 -> 8.5171932 | V10: =K10 -> 6.2595815 | W10: =G10 -> 49.7 | X10: =P10 -> 0 | Y10: =J10 -> 8.5171932 | Z10: =K10 -> 6.2595815 | AA10: =G10 -> 49.7 | AB10: =L10 -> 0 | AC10: =M10 -> 0 | AD10: =M10*J10 -> 0 | AE10: =M10*K10 -> 0 | AF10: =M10*G10 -> 0 | AG10: =J10 -> 8.5171932 | AH10: =L10 -> 0 | AI10: =M10 -> 0 | AJ10: =J10 -> 8.5171932 | AK10: =K10 -> 6.2595815 | AL10: =M10 -> 0 | AM10: =CER!$C$7+CER!$C$8*J10+CER!$C$9*K10+CER!$C$10*L10+CER!$C$11*M10 -> 3.0925448 | AN10: =EXP(AM10) -> 22.033077 | AO10: =I10-AM10 -> 0.12631898 | AP10: =Alternatives!$F$25+Alternatives!$F$26*J10+Alternatives!$F$27*K10+Alternatives!$F$28*G10+Alternatives!$F$29*O10 -> 3.2842961 | AQ10: =I10-AP10 -> -0.065432317
A11: Z4 sDrive30i | B11: BMW | C11: gas_diesel | D11: 37.762 | E11: 3500 | F11: 255 | G11: 42.9 | H11: FE file ENG_RATED_HP | I11: =LN(D11) -> 3.6313033 | J11: =LN(E11) -> 8.1605182 | K11: =LN(F11) -> 5.5412635 | L11: 0 | M11: 0 | N11: =G11 -> 42.9 | O11: =L11+M11 -> 0 | P11: =L11+2*M11 -> 0 | Q11: =J11 -> 8.1605182 | R11: =K11 -> 5.5412635 | S11: =G11 -> 42.9 | T11: =O11 -> 0 | U11: =J11 -> 8.1605182 | V11: =K11 -> 5.5412635 | W11: =G11 -> 42.9 | X11: =P11 -> 0 | Y11: =J11 -> 8.1605182 | Z11: =K11 -> 5.5412635 | AA11: =G11 -> 42.9 | AB11: =L11 -> 0 | AC11: =M11 -> 0 | AD11: =M11*J11 -> 0 | AE11: =M11*K11 -> 0 | AF11: =M11*G11 -> 0 | AG11: =J11 -> 8.1605182 | AH11: =L11 -> 0 | AI11: =M11 -> 0 | AJ11: =J11 -> 8.1605182 | AK11: =K11 -> 5.5412635 | AL11: =M11 -> 0 | AM11: =CER!$C$7+CER!$C$8*J11+CER!$C$9*K11+CER!$C$10*L11+CER!$C$11*M11 -> 3.5190337 | AN11: =EXP(AM11) -> 33.751799 | AO11: =I11-AM11 -> 0.11226958 | AP11: =Alternatives!$F$25+Alternatives!$F$26*J11+Alternatives!$F$27*K11+Alternatives!$F$28*G11+Alternatives!$F$29*O11 -> 3.431897 | AQ11: =I11-AP11 -> 0.19940626
A12: X3 M | B12: BMW | C12: gas_diesel | D12: 21.7837 | E12: 5000 | F12: 473 | G12: 49.7 | H12: FE file ENG_RATED_HP | I12: =LN(D12) -> 3.081162 | J12: =LN(E12) -> 8.5171932 | K12: =LN(F12) -> 6.1590954 | L12: 0 | M12: 0 | N12: =G12 -> 49.7 | O12: =L12+M12 -> 0 | P12: =L12+2*M12 -> 0 | Q12: =J12 -> 8.5171932 | R12: =K12 -> 6.1590954 | S12: =G12 -> 49.7 | T12: =O12 -> 0 | U12: =J12 -> 8.5171932 | V12: =K12 -> 6.1590954 | W12: =G12 -> 49.7 | X12: =P12 -> 0 | Y12: =J12 -> 8.5171932 | Z12: =K12 -> 6.1590954 | AA12: =G12 -> 49.7 | AB12: =L12 -> 0 | AC12: =M12 -> 0 | AD12: =M12*J12 -> 0 | AE12: =M12*K12 -> 0 | AF12: =M12*G12 -> 0 | AG12: =J12 -> 8.5171932 | AH12: =L12 -> 0 | AI12: =M12 -> 0 | AJ12: =J12 -> 8.5171932 | AK12: =K12 -> 6.1590954 | AL12: =M12 -> 0 | AM12: =CER!$C$7+CER!$C$8*J12+CER!$C$9*K12+CER!$C$10*L12+CER!$C$11*M12 -> 3.1296186 | AN12: =EXP(AM12) -> 22.865256 | AO12: =I12-AM12 -> -0.048456568 | AP12: =Alternatives!$F$25+Alternatives!$F$26*J12+Alternatives!$F$27*K12+Alternatives!$F$28*G12+Alternatives!$F$29*O12 -> 3.3110365 | AQ12: =I12-AP12 -> -0.2298745
A13: X3 M Competition | B13: BMW | C13: gas_diesel | D13: 21.7837 | E13: 5000 | F13: 503 | G13: 49.7 | H13: FE file ENG_RATED_HP | I13: =LN(D13) -> 3.081162 | J13: =LN(E13) -> 8.5171932 | K13: =LN(F13) -> 6.2205902 | L13: 0 | M13: 0 | N13: =G13 -> 49.7 | O13: =L13+M13 -> 0 | P13: =L13+2*M13 -> 0 | Q13: =J13 -> 8.5171932 | R13: =K13 -> 6.2205902 | S13: =G13 -> 49.7 | T13: =O13 -> 0 | U13: =J13 -> 8.5171932 | V13: =K13 -> 6.2205902 | W13: =G13 -> 49.7 | X13: =P13 -> 0 | Y13: =J13 -> 8.5171932 | Z13: =K13 -> 6.2205902 | AA13: =G13 -> 49.7 | AB13: =L13 -> 0 | AC13: =M13 -> 0 | AD13: =M13*J13 -> 0 | AE13: =M13*K13 -> 0 | AF13: =M13*G13 -> 0 | AG13: =J13 -> 8.5171932 | AH13: =L13 -> 0 | AI13: =M13 -> 0 | AJ13: =J13 -> 8.5171932 | AK13: =K13 -> 6.2205902 | AL13: =M13 -> 0 | AM13: =CER!$C$7+CER!$C$8*J13+CER!$C$9*K13+CER!$C$10*L13+CER!$C$11*M13 -> 3.1069304 | AN13: =EXP(AM13) -> 22.352327 | AO13: =I13-AM13 -> -0.025768454 | AP13: =Alternatives!$F$25+Alternatives!$F$26*J13+Alternatives!$F$27*K13+Alternatives!$F$28*G13+Alternatives!$F$29*O13 -> 3.2946721 | AQ13: =I13-AP13 -> -0.21351013
... A1286: Polestar 2 Single Motor (20 Inch Wheels) | B1286: Volvo Car USA, LLC | C1286: bev | D1286: 159.6008 | E1286: 4500 | F1286: 348.5 | G1286: 47 | H1286: Test Car List: tg | I1286: =LN(D1286) -> 5.0726757 | J1286: =LN(E1286) -> 8.4118327 | K1286: =LN(F1286) -> 5.8536382 | L1286: 0 | M1286: 1 | N1286: =G1286 -> 47 | O1286: =L1286+M1286 -> 1 | P1286: =L1286+2*M1286 -> 2 | Q1286: =J1286 -> 8.4118327 | R1286: =K1286 -> 5.8536382 | S1286: =G1286 -> 47 | T1286: =O1286 -> 1 | U1286: =J1286 -> 8.4118327 | V1286: =K1286 -> 5.8536382 | W1286: =G1286 -> 47 | X1286: =P1286 -> 2 | Y1286: =J1286 -> 8.4118327 | Z1286: =K1286 -> 5.8536382 | AA1286: =G1286 -> 47 | AB1286: =L1286 -> 0 | AC1286: =M1286 -> 1 | AD1286: =M1286*J1286 -> 8.4118327 | AE1286: =M1286*K1286 -> 5.8536382 | AF1286: =M1286*G1286 -> 47 | AG1286: =J1286 -> 8.4118327 | AH1286: =L1286 -> 0 | AI1286: =M1286 -> 1 | AJ1286: =J1286 -> 8.4118327 | AK1286: =K1286 -> 5.8536382 | AL1286: =M1286 -> 1 | AM1286: =CER!$C$7+CER!$C$8*J1286+CER!$C$9*K1286+CER!$C$10*L1286+CER!$C$11*M1286 -> 4.9979829 | AN1286: =EXP(AM1286) -> 148.11409 | AO1286: =I1286-AM1286 -> 0.074692844 | AP1286: =Alternatives!$F$25+Alternatives!$F$26*J1286+Alternatives!$F$27*K1286+Alternatives!$F$28*G1286+Alternatives!$F$29*O1286 -> 4.2331889 | AQ1286: =I1286-AP1286 -> 0.83948679

Sheet Data_Combustion
A1: carline | B1: powertrain | C1: MPG | D1: weight_lbs | E1: horsepower | F1: footprint_sqft | G1: hybrid | H1: ln_mpg | I1: ln_weight | J1: ln_hp | K1: footprint | L1: hybrid (block)
A2: DB12 V8 | B2: gas_diesel | C2: 22.4729 | D2: 4500 | E2: 680 | F2: 50 | G2: 0 | H2: =LN(C2) -> 3.1123101 | I2: =LN(D2) -> 8.4118327 | J2: =LN(E2) -> 6.5220928 | K2: =F2 -> 50 | L2: =G2 -> 0
A3: Valour | B3: gas_diesel | C3: 18.3624 | D3: 4000 | E3: 715 | F3: 48.2 | G3: 0 | H3: =LN(C3) -> 2.9103051 | I3: =LN(D3) -> 8.2940496 | J3: =LN(E3) -> 6.5722825 | K3: =F3 -> 48.2 | L3: =G3 -> 0
A4: DBX V8 | B4: gas_diesel | C4: 20.6665 | D4: 5500 | E4: 550 | F4: 55.4 | G4: 0 | H4: =LN(C4) -> 3.028514 | I4: =LN(D4) -> 8.6125034 | J4: =LN(E4) -> 6.3099183 | K4: =F4 -> 55.4 | L4: =G4 -> 0
A5: DBX 707 | B5: gas_diesel | C5: 21.5837 | D5: 5500 | E5: 707 | F5: 55.4 | G5: 0 | H5: =LN(C5) -> 3.0719384 | I5: =LN(D5) -> 8.6125034 | J5: =LN(E5) -> 6.5610307 | K5: =F5 -> 55.4 | L5: =G5 -> 0
A6: X3 xDrive30i | B6: gas_diesel | C6: 31.5873 | D6: 4500 | E6: 248 | F6: 49.6 | G6: 0 | H6: =LN(C6) -> 3.4527551 | I6: =LN(D6) -> 8.4118327 | J6: =LN(E6) -> 5.5134287 | K6: =F6 -> 49.6 | L6: =G6 -> 0
A7: X4 xDrive30i | B7: gas_diesel | C7: 31.5873 | D7: 4500 | E7: 248 | F7: 50.7 | G7: 0 | H7: =LN(C7) -> 3.4527551 | I7: =LN(D7) -> 8.4118327 | J7: =LN(E7) -> 5.5134287 | K7: =F7 -> 50.7 | L7: =G7 -> 0
A8: X3 sDrive30i | B8: gas_diesel | C8: 33.2063 | D8: 4500 | E8: 248 | F8: 50.2 | G8: 0 | H8: =LN(C8) -> 3.5027396 | I8: =LN(D8) -> 8.4118327 | J8: =LN(E8) -> 5.5134287 | K8: =F8 -> 50.2 | L8: =G8 -> 0
A9: M850i xDrive Coupe | B9: gas_diesel | C9: 25.0424 | D9: 4500 | E9: 523 | F9: 49.7 | G9: 0 | H9: =LN(C9) -> 3.2205704 | I9: =LN(D9) -> 8.4118327 | J9: =LN(E9) -> 6.2595815 | K9: =F9 -> 49.7 | L9: =G9 -> 0
A10: M850i xDrive Convertible | B10: gas_diesel | C10: 24.9997 | D10: 5000 | E10: 523 | F10: 49.7 | G10: 0 | H10: =LN(C10) -> 3.2188638 | I10: =LN(D10) -> 8.5171932 | J10: =LN(E10) -> 6.2595815 | K10: =F10 -> 49.7 | L10: =G10 -> 0
A11: Z4 sDrive30i | B11: gas_diesel | C11: 37.762 | D11: 3500 | E11: 255 | F11: 42.9 | G11: 0 | H11: =LN(C11) -> 3.6313033 | I11: =LN(D11) -> 8.1605182 | J11: =LN(E11) -> 5.5412635 | K11: =F11 -> 42.9 | L11: =G11 -> 0
A12: X3 M | B12: gas_diesel | C12: 21.7837 | D12: 5000 | E12: 473 | F12: 49.7 | G12: 0 | H12: =LN(C12) -> 3.081162 | I12: =LN(D12) -> 8.5171932 | J12: =LN(E12) -> 6.1590954 | K12: =F12 -> 49.7 | L12: =G12 -> 0
A13: X3 M Competition | B13: gas_diesel | C13: 21.7837 | D13: 5000 | E13: 503 | F13: 49.7 | G13: 0 | H13: =LN(C13) -> 3.081162 | I13: =LN(D13) -> 8.5171932 | J13: =LN(E13) -> 6.2205902 | K13: =F13 -> 49.7 | L13: =G13 -> 0
... A1026: XC90 B6 AWD | B1026: hybrid | C1026: 29.8831 | D1026: 5000 | E1026: 295 | F1026: 53.5 | G1026: 1 | H1026: =LN(C1026) -> 3.3972931 | I1026: =LN(D1026) -> 8.5171932 | J1026: =LN(E1026) -> 5.6869754 | K1026: =F1026 -> 53.5 | L1026: =G1026 -> 1

Sheet CER
A1: The final CER: ln(MPG) = b0 + b1 ln(weight) + b2 ln(horsepower) + b3 hybrid + b4 electric
A2: Fit by LINEST over Data rows 2 to 1286 (n below). Coefficients, R-squared, F, and SSE match the Python fit exactly; LINEST standard errors are classical OLS, the deck's are HC1 robust (column H).
A3: n (model types) | C3: =COUNT(Data!$I$2:$I$1286) -> 1285
A4: k (predictors) | C4: 4
A6: Term | B6: LINEST column | C6: Coefficient | D6: Std error (OLS, LINEST) | E6: t = coef / SE | F6: p (two-tailed) | G6: Verdict at alpha = 0.05 | H6: HC1 robust SE (deck) | I6: t with HC1 SE
A7: intercept | B7: 5 | C7: =INDEX(LINEST(Data!$I$2:$I$1286,Data!$J$2:$M$1286,TRUE,TRUE),1,5) -> 9.2577891 | D7: =INDEX(LINEST(Data!$I$2:$I$1286,Data!$J$2:$M$1286,TRUE,TRUE),2,5) -> 0.16906959 | E7: =C7/D7 -> 54.757271 | F7: =_xlfn.T.DIST.2T(ABS(E7),$C$17) -> 0 | G7: =IF(F7<0.05,"reject H0: coefficient differs from zero","fail to reject H0") -> reject H0: coefficient differs from zero | H7: 0.2014 | I7: =C7/H7 -> 45.967175
A8: ln(weight) | B8: 4 | C8: =INDEX(LINEST(Data!$I$2:$I$1286,Data!$J$2:$M$1286,TRUE,TRUE),1,4) -> -0.45270912 | D8: =INDEX(LINEST(Data!$I$2:$I$1286,Data!$J$2:$M$1286,TRUE,TRUE),2,4) -> 0.023394081 | E8: =C8/D8 -> -19.351439 | F8: =_xlfn.T.DIST.2T(ABS(E8),$C$17) -> 2.1929529e-73 | G8: =IF(F8<0.05,"reject H0: coefficient differs from zero","fail to reject H0") -> reject H0: coefficient differs from zero | H8: 0.0293 | I8: =C8/H8 -> -15.450823
A9: ln(horsepower) | B9: 3 | C9: =INDEX(LINEST(Data!$I$2:$I$1286,Data!$J$2:$M$1286,TRUE,TRUE),1,3) -> -0.36894371 | D9: =INDEX(LINEST(Data!$I$2:$I$1286,Data!$J$2:$M$1286,TRUE,TRUE),2,3) -> 0.010334543 | E9: =C9/D9 -> -35.700051 | F9: =_xlfn.T.DIST.2T(ABS(E9),$C$17) -> 2.7427466e-194 | G9: =IF(F9<0.05,"reject H0: coefficient differs from zero","fail to reject H0") -> reject H0: coefficient differs from zero | H9: 0.015 | I9: =C9/H9 -> -24.596248
A10: hybrid | B10: 2 | C10: =INDEX(LINEST(Data!$I$2:$I$1286,Data!$J$2:$M$1286,TRUE,TRUE),1,2) -> 0.22375357 | D10: =INDEX(LINEST(Data!$I$2:$I$1286,Data!$J$2:$M$1286,TRUE,TRUE),2,2) -> 0.010114394 | E10: =C10/D10 -> 22.122291 | F10: =_xlfn.T.DIST.2T(ABS(E10),$C$17) -> 4.2938087e-92 | G10: =IF(F10<0.05,"reject H0: coefficient differs from zero","fail to reject H0") -> reject H0: coefficient differs from zero | H10: 0.0107 | I10: =C10/H10 -> 20.911549
A11: battery-electric | B11: 1 | C11: =INDEX(LINEST(Data!$I$2:$I$1286,Data!$J$2:$M$1286,TRUE,TRUE),1,1) -> 1.7079701 | D11: =INDEX(LINEST(Data!$I$2:$I$1286,Data!$J$2:$M$1286,TRUE,TRUE),2,1) -> 0.010927903 | E11: =C11/D11 -> 156.29441 | F11: =_xlfn.T.DIST.2T(ABS(E11),$C$17) -> 0 | G11: =IF(F11<0.05,"reject H0: coefficient differs from zero","fail to reject H0") -> reject H0: coefficient differs from zero | H11: 0.0145 | I11: =C11/H11 -> 117.79104
A12: Note: LINEST lists coefficients in reverse order (last predictor first, intercept last); column B is the LINEST column each term is read from with INDEX.
A14: Whole-model fit
A15: R-squared | C15: =INDEX(LINEST(Data!$I$2:$I$1286,Data!$J$2:$M$1286,TRUE,TRUE),3,1) -> 0.954622
A16: Adjusted R-squared | C16: =1-(1-C15)*(C3-1)/(C3-C4-1) -> 0.95448019
A17: Residual degrees of freedom | C17: =INDEX(LINEST(Data!$I$2:$I$1286,Data!$J$2:$M$1286,TRUE,TRUE),4,2) -> 1280
A18: F statistic (whole model, H0: all four coefficients are zero) | C18: =INDEX(LINEST(Data!$I$2:$I$1286,Data!$J$2:$M$1286,TRUE,TRUE),4,1) -> 6731.8746
A19: F p-value | C19: =_xlfn.F.DIST.RT(C18,C4,C17) -> 0
A20: F recomputed from R-squared: (R2/k) / ((1-R2)/df) | C20: =(C15/C4)/((1-C15)/C17) -> 6731.8746
A21: Regression sum of squares | C21: =INDEX(LINEST(Data!$I$2:$I$1286,Data!$J$2:$M$1286,TRUE,TRUE),5,1) -> 493.78259
A22: Residual sum of squares (SSE) | C22: =INDEX(LINEST(Data!$I$2:$I$1286,Data!$J$2:$M$1286,TRUE,TRUE),5,2) -> 23.471981
A23: Residual standard error s (log units) | C23: =INDEX(LINEST(Data!$I$2:$I$1286,Data!$J$2:$M$1286,TRUE,TRUE),3,2) -> 0.13541597
A25: Reading the coefficients (elasticities and premiums)
A26: MPG change for 10% more weight, elasticity reading b1 x 10% (the deck's figure) | C26: =C8*0.1 -> -0.045270912
A27: MPG change for 10% more horsepower, elasticity reading b2 x 10% (the deck's figure) | C27: =C9*0.1 -> -0.036894371
A28: Hybrid premium at identical weight and power, exp(b3) - 1 | C28: =EXP(C10)-1 -> 0.25076276
A29: Battery-electric premium, exp(b4) - 1, in MPG-equivalent | C29: =EXP(C11)-1 -> 4.5177498
A30: Exact power-law reading for 10% more weight, 1.1^b1 - 1 (elasticity is the first-order approximation) | C30: =1.1^C8-1 -> -0.042230167
A31: Exact power-law reading for 10% more horsepower, 1.1^b2 - 1 | C31: =1.1^C9-1 -> -0.034553019
A33: Variance inflation factors: VIF_j = 1 / (1 - R2 of predictor j regressed on the other three)
A34: ln(weight) | C34: =1/(1-INDEX(LINEST(Data!$J$2:$J$1286,Data!$K$2:$M$1286,TRUE,TRUE),3,1)) -> 1.8961715
A35: ln(horsepower) | C35: =1/(1-INDEX(LINEST(Data!$K$2:$K$1286,Data!$AG$2:$AI$1286,TRUE,TRUE),3,1)) -> 1.628217
A36: hybrid | C36: =1/(1-INDEX(LINEST(Data!$L$2:$L$1286,Data!$AJ$2:$AL$1286,TRUE,TRUE),3,1)) -> 1.1233555
A37: battery-electric | C37: =1/(1-INDEX(LINEST(Data!$M$2:$M$1286,Data!$J$2:$L$1286,TRUE,TRUE),3,1)) -> 1.3506038
A39: Prediction band (in logs, leverage ignored)
A40: Typical miss, exp(s) - 1 | C40: =EXP(C23)-1 -> 0.14501298
A41: 95% band factor, exp(1.96 s): predicted times or divided by | C41: =EXP(1.96*C23) -> 1.3039724
A42: Share of model types inside the band | C42: =SUMPRODUCT(--(ABS(Data!$AO$2:$AO$1286)<=1.96*C23))/C3 -> 0.9385214
A45: Named outliers on the predicted-vs-actual slide (looked up live from Data)
A46: carline | B46: powertrain | C46: actual | D46: predicted | E46: actual / predicted | F46: residual / s
A47: VF 8 Plus | B47: =INDEX(Data!$C$2:$C$1286,MATCH(A47,Data!$A$2:$A$1286,0)) -> bev | C47: =INDEX(Data!$D$2:$D$1286,MATCH(A47,Data!$A$2:$A$1286,0)) -> 62.3061 | D47: =INDEX(Data!$AN$2:$AN$1286,MATCH(A47,Data!$A$2:$A$1286,0)) -> 123.35375 | E47: =C47/D47 -> 0.50510096 | F47: =INDEX(Data!$AO$2:$AO$1286,MATCH(A47,Data!$A$2:$A$1286,0))/$C$23 -> -5.0436957
A48: 500e | B48: =INDEX(Data!$C$2:$C$1286,MATCH(A48,Data!$A$2:$A$1286,0)) -> bev | C48: =INDEX(Data!$D$2:$D$1286,MATCH(A48,Data!$A$2:$A$1286,0)) -> 165.0059 | D48: =INDEX(Data!$AN$2:$AN$1286,MATCH(A48,Data!$A$2:$A$1286,0)) -> 296.94143 | E48: =C48/D48 -> 0.55568501 | F48: =INDEX(Data!$AO$2:$AO$1286,MATCH(A48,Data!$A$2:$A$1286,0))/$C$23 -> -4.3388803
A49: Air G Touring XR AWD w/19" wheels | B49: =INDEX(Data!$C$2:$C$1286,MATCH(A49,Data!$A$2:$A$1286,0)) -> bev | C49: =INDEX(Data!$D$2:$D$1286,MATCH(A49,Data!$A$2:$A$1286,0)) -> 174.7996 | D49: =INDEX(Data!$AN$2:$AN$1286,MATCH(A49,Data!$A$2:$A$1286,0)) -> 98.681251 | E49: =C49/D49 -> 1.7713557 | F49: =INDEX(Data!$AO$2:$AO$1286,MATCH(A49,Data!$A$2:$A$1286,0))/$C$23 -> 4.2221402
A50: Air Sapphire AWD | B50: =INDEX(Data!$C$2:$C$1286,MATCH(A50,Data!$A$2:$A$1286,0)) -> bev | C50: =INDEX(Data!$D$2:$D$1286,MATCH(A50,Data!$A$2:$A$1286,0)) -> 144.9629 | D50: =INDEX(Data!$AN$2:$AN$1286,MATCH(A50,Data!$A$2:$A$1286,0)) -> 84.830326 | E50: =C50/D50 -> 1.708857 | F50: =INDEX(Data!$AO$2:$AO$1286,MATCH(A50,Data!$A$2:$A$1286,0))/$C$23 -> 3.9568801
A51: 500e All Season | B51: =INDEX(Data!$C$2:$C$1286,MATCH(A51,Data!$A$2:$A$1286,0)) -> bev | C51: =INDEX(Data!$D$2:$D$1286,MATCH(A51,Data!$A$2:$A$1286,0)) -> 157.6998 | D51: =INDEX(Data!$AN$2:$AN$1286,MATCH(A51,Data!$A$2:$A$1286,0)) -> 266.1951 | E51: =C51/D51 -> 0.59242188 | F51: =INDEX(Data!$AO$2:$AO$1286,MATCH(A51,Data!$A$2:$A$1286,0))/$C$23 -> -3.8661339

Sheet Alternatives
A1: Alternative CERs, each fit with LINEST, and the nested F-tests between them
A2: Nested F = ((SSE_restricted - SSE_full) / q) / (SSE_full / df_full), where q is the number of restrictions; p from F.DIST.RT.
A4: Spec A: Combustion only (original CER): ln(weight), ln(HP), footprint, hybrid; n = 1,025
A5: n | C5: =COUNT(Data_Combustion!$H$2:$H$1026) -> 1025 | E5: Term | F5: Coefficient | G5: SE (OLS) | H5: t
A6: R-squared | C6: =INDEX(LINEST(Data_Combustion!$H$2:$H$1026,Data_Combustion!$I$2:$L$1026,TRUE,TRUE),3,1) -> 0.84603748 | E6: intercept | F6: =INDEX(LINEST(Data_Combustion!$H$2:$H$1026,Data_Combustion!$I$2:$L$1026,TRUE,TRUE),1,5) -> 8.7774826 | G6: =INDEX(LINEST(Data_Combustion!$H$2:$H$1026,Data_Combustion!$I$2:$L$1026,TRUE,TRUE),2,5) -> 0.22042489 | H6: =F6/G6 -> 39.820741
A7: Adjusted R-squared | C7: =1-(1-C6)*(C5-1)/(C5-4-1) -> 0.84543371 | E7: ln(weight) | F7: =INDEX(LINEST(Data_Combustion!$H$2:$H$1026,Data_Combustion!$I$2:$L$1026,TRUE,TRUE),1,4) -> -0.30375764 | G7: =INDEX(LINEST(Data_Combustion!$H$2:$H$1026,Data_Combustion!$I$2:$L$1026,TRUE,TRUE),2,4) -> 0.032739556 | H7: =F7/G7 -> -9.2780011
A8: F (whole model) | C8: =INDEX(LINEST(Data_Combustion!$H$2:$H$1026,Data_Combustion!$I$2:$L$1026,TRUE,TRUE),4,1) -> 1401.2473 | E8: ln(horsepower) | F8: =INDEX(LINEST(Data_Combustion!$H$2:$H$1026,Data_Combustion!$I$2:$L$1026,TRUE,TRUE),1,3) -> -0.48301416 | G8: =INDEX(LINEST(Data_Combustion!$H$2:$H$1026,Data_Combustion!$I$2:$L$1026,TRUE,TRUE),2,3) -> 0.010100109 | H8: =F8/G8 -> -47.82267
A9: Residual df | C9: =INDEX(LINEST(Data_Combustion!$H$2:$H$1026,Data_Combustion!$I$2:$L$1026,TRUE,TRUE),4,2) -> 1020 | E9: footprint | F9: =INDEX(LINEST(Data_Combustion!$H$2:$H$1026,Data_Combustion!$I$2:$L$1026,TRUE,TRUE),1,2) -> -0.0022273382 | G9: =INDEX(LINEST(Data_Combustion!$H$2:$H$1026,Data_Combustion!$I$2:$L$1026,TRUE,TRUE),2,2) -> 0.00077527425 | H9: =F9/G9 -> -2.8729681
A10: SSE | C10: =INDEX(LINEST(Data_Combustion!$H$2:$H$1026,Data_Combustion!$I$2:$L$1026,TRUE,TRUE),5,2) -> 13.153763 | E10: hybrid | F10: =INDEX(LINEST(Data_Combustion!$H$2:$H$1026,Data_Combustion!$I$2:$L$1026,TRUE,TRUE),1,1) -> 0.20740284 | G10: =INDEX(LINEST(Data_Combustion!$H$2:$H$1026,Data_Combustion!$I$2:$L$1026,TRUE,TRUE),2,1) -> 0.0087264189 | H10: =F10/G10 -> 23.767234
A13: Spec B: Pooled, powertrain factor plus footprint: ln(weight), ln(HP), hybrid, bev, footprint
A14: n | C14: =COUNT(Data!$I$2:$I$1286) -> 1285 | E14: Term | F14: Coefficient | G14: SE (OLS) | H14: t
A15: R-squared | C15: =INDEX(LINEST(Data!$I$2:$I$1286,Data!$J$2:$N$1286,TRUE,TRUE),3,1) -> 0.95462292 | E15: intercept | F15: =INDEX(LINEST(Data!$I$2:$I$1286,Data!$J$2:$N$1286,TRUE,TRUE),1,6) -> 9.2305493 | G15: =INDEX(LINEST(Data!$I$2:$I$1286,Data!$J$2:$N$1286,TRUE,TRUE),2,6) -> 0.2386676 | H15: =F15/G15 -> 38.675335
A16: Adjusted R-squared | C16: =1-(1-C15)*(C14-1)/(C14-5-1) -> 0.95444553 | E16: ln(weight) | F16: =INDEX(LINEST(Data!$I$2:$I$1286,Data!$J$2:$N$1286,TRUE,TRUE),1,5) -> -0.44837275 | G16: =INDEX(LINEST(Data!$I$2:$I$1286,Data!$J$2:$N$1286,TRUE,TRUE),2,5) -> 0.035585109 | H16: =F16/G16 -> -12.60001
A17: F (whole model) | C17: =INDEX(LINEST(Data!$I$2:$I$1286,Data!$J$2:$N$1286,TRUE,TRUE),4,1) -> 5381.4076 | E17: ln(horsepower) | F17: =INDEX(LINEST(Data!$I$2:$I$1286,Data!$J$2:$N$1286,TRUE,TRUE),1,4) -> -0.36926557 | G17: =INDEX(LINEST(Data!$I$2:$I$1286,Data!$J$2:$N$1286,TRUE,TRUE),2,4) -> 0.010528195 | H17: =F17/G17 -> -35.073969
A18: Residual df | C18: =INDEX(LINEST(Data!$I$2:$I$1286,Data!$J$2:$N$1286,TRUE,TRUE),4,2) -> 1279 | E18: hybrid | F18: =INDEX(LINEST(Data!$I$2:$I$1286,Data!$J$2:$N$1286,TRUE,TRUE),1,3) -> 0.22343156 | G18: =INDEX(LINEST(Data!$I$2:$I$1286,Data!$J$2:$N$1286,TRUE,TRUE),2,3) -> 0.010312194 | H18: =F18/G18 -> 21.666734
A19: SSE | C19: =INDEX(LINEST(Data!$I$2:$I$1286,Data!$J$2:$N$1286,TRUE,TRUE),5,2) -> 23.4715 | E19: battery-electric | F19: =INDEX(LINEST(Data!$I$2:$I$1286,Data!$J$2:$N$1286,TRUE,TRUE),1,2) -> 1.7073917 | G19: =INDEX(LINEST(Data!$I$2:$I$1286,Data!$J$2:$N$1286,TRUE,TRUE),2,2) -> 0.011502065 | H19: =F19/G19 -> 148.44219
E20: footprint | F20: =INDEX(LINEST(Data!$I$2:$I$1286,Data!$J$2:$N$1286,TRUE,TRUE),1,1) -> -0.00014119074 | G20: =INDEX(LINEST(Data!$I$2:$I$1286,Data!$J$2:$N$1286,TRUE,TRUE),2,1) -> 0.00087281771 | H20: =F20/G20 -> -0.1617643
A23: Spec C: Pooled, ONE merged electrified flag (hybrid or bev): ln(weight), ln(HP), footprint, electrified
A24: n | C24: =COUNT(Data!$I$2:$I$1286) -> 1285 | E24: Term | F24: Coefficient | G24: SE (OLS) | H24: t
A25: R-squared | C25: =INDEX(LINEST(Data!$I$2:$I$1286,Data!$Q$2:$T$1286,TRUE,TRUE),3,1) -> 0.46508851 | E25: intercept | F25: =INDEX(LINEST(Data!$I$2:$I$1286,Data!$Q$2:$T$1286,TRUE,TRUE),1,5) -> 2.4444029 | G25: =INDEX(LINEST(Data!$I$2:$I$1286,Data!$Q$2:$T$1286,TRUE,TRUE),2,5) -> 0.79475868 | H25: =F25/G25 -> 3.0756543
A26: Adjusted R-squared | C26: =1-(1-C25)*(C24-1)/(C24-4-1) -> 0.46341691 | E26: ln(weight) | F26: =INDEX(LINEST(Data!$I$2:$I$1286,Data!$Q$2:$T$1286,TRUE,TRUE),1,4) -> 0.37008598 | G26: =INDEX(LINEST(Data!$I$2:$I$1286,Data!$Q$2:$T$1286,TRUE,TRUE),2,4) -> 0.11976566 | H26: =F26/G26 -> 3.0900841
A27: F (whole model) | C27: =INDEX(LINEST(Data!$I$2:$I$1286,Data!$Q$2:$T$1286,TRUE,TRUE),4,1) -> 278.22981 | E27: ln(horsepower) | F27: =INDEX(LINEST(Data!$I$2:$I$1286,Data!$Q$2:$T$1286,TRUE,TRUE),1,3) -> -0.26610997 | G27: =INDEX(LINEST(Data!$I$2:$I$1286,Data!$Q$2:$T$1286,TRUE,TRUE),2,3) -> 0.036007319 | H27: =F27/G27 -> -7.3904409
A28: Residual df | C28: =INDEX(LINEST(Data!$I$2:$I$1286,Data!$Q$2:$T$1286,TRUE,TRUE),4,2) -> 1280 | E28: footprint | F28: =INDEX(LINEST(Data!$I$2:$I$1286,Data!$Q$2:$T$1286,TRUE,TRUE),1,2) -> -0.013007315 | G28: =INDEX(LINEST(Data!$I$2:$I$1286,Data!$Q$2:$T$1286,TRUE,TRUE),2,2) -> 0.0029718689 | H28: =F28/G28 -> -4.376813
A29: SSE | C29: =INDEX(LINEST(Data!$I$2:$I$1286,Data!$Q$2:$T$1286,TRUE,TRUE),5,2) -> 276.68542 | E29: electrified | F29: =INDEX(LINEST(Data!$I$2:$I$1286,Data!$Q$2:$T$1286,TRUE,TRUE),1,1) -> 0.84473993 | G29: =INDEX(LINEST(Data!$I$2:$I$1286,Data!$Q$2:$T$1286,TRUE,TRUE),2,1) -> 0.030381763 | H29: =F29/G29 -> 27.804178
A32: Spec D: Pooled, ordinal electrification 0/1/2: ln(weight), ln(HP), footprint, ordinal
A33: n | C33: =COUNT(Data!$I$2:$I$1286) -> 1285 | E33: Term | F33: Coefficient | G33: SE (OLS) | H33: t
A34: R-squared | C34: =INDEX(LINEST(Data!$I$2:$I$1286,Data!$U$2:$X$1286,TRUE,TRUE),3,1) -> 0.81354258 | E34: intercept | F34: =INDEX(LINEST(Data!$I$2:$I$1286,Data!$U$2:$X$1286,TRUE,TRUE),1,5) -> 9.0244752 | G34: =INDEX(LINEST(Data!$I$2:$I$1286,Data!$U$2:$X$1286,TRUE,TRUE),2,5) -> 0.48356473 | H34: =F34/G34 -> 18.662393
A35: Adjusted R-squared | C35: =1-(1-C34)*(C33-1)/(C33-4-1) -> 0.8129599 | E35: ln(weight) | F35: =INDEX(LINEST(Data!$I$2:$I$1286,Data!$U$2:$X$1286,TRUE,TRUE),1,4) -> -0.50715421 | G35: =INDEX(LINEST(Data!$I$2:$I$1286,Data!$U$2:$X$1286,TRUE,TRUE),2,4) -> 0.072081052 | H35: =F35/G35 -> -7.035888
A36: F (whole model) | C36: =INDEX(LINEST(Data!$I$2:$I$1286,Data!$U$2:$X$1286,TRUE,TRUE),4,1) -> 1396.2095 | E36: ln(horsepower) | F36: =INDEX(LINEST(Data!$I$2:$I$1286,Data!$U$2:$X$1286,TRUE,TRUE),1,3) -> -0.27031535 | G36: =INDEX(LINEST(Data!$I$2:$I$1286,Data!$U$2:$X$1286,TRUE,TRUE),2,3) -> 0.021094911 | H36: =F36/G36 -> -12.814245
A37: Residual df | C37: =INDEX(LINEST(Data!$I$2:$I$1286,Data!$U$2:$X$1286,TRUE,TRUE),4,2) -> 1280 | E37: footprint | F37: =INDEX(LINEST(Data!$I$2:$I$1286,Data!$U$2:$X$1286,TRUE,TRUE),1,2) -> 0.00097458916 | G37: =INDEX(LINEST(Data!$I$2:$I$1286,Data!$U$2:$X$1286,TRUE,TRUE),2,2) -> 0.0017682194 | H37: =F37/G37 -> 0.55116981
A38: SSE | C38: =INDEX(LINEST(Data!$I$2:$I$1286,Data!$U$2:$X$1286,TRUE,TRUE),5,2) -> 96.445953 | E38: ordinal 0/1/2 | F38: =INDEX(LINEST(Data!$I$2:$I$1286,Data!$U$2:$X$1286,TRUE,TRUE),1,1) -> 0.76969357 | G38: =INDEX(LINEST(Data!$I$2:$I$1286,Data!$U$2:$X$1286,TRUE,TRUE),2,1) -> 0.011336344 | H38: =F38/G38 -> 67.896103
A41: Spec E: B plus bev-specific slopes: adds bev x ln(weight), bev x ln(HP), bev x footprint
A42: n | C42: =COUNT(Data!$I$2:$I$1286) -> 1285 | E42: Term | F42: Coefficient | G42: SE (OLS) | H42: t
A43: R-squared | C43: =INDEX(LINEST(Data!$I$2:$I$1286,Data!$Y$2:$AF$1286,TRUE,TRUE),3,1) -> 0.96804523 | E43: intercept | F43: =INDEX(LINEST(Data!$I$2:$I$1286,Data!$Y$2:$AF$1286,TRUE,TRUE),1,9) -> 8.7774826 | G43: =INDEX(LINEST(Data!$I$2:$I$1286,Data!$Y$2:$AF$1286,TRUE,TRUE),2,9) -> 0.22091762 | H43: =F43/G43 -> 39.731925
A44: Adjusted R-squared | C44: =1-(1-C43)*(C42-1)/(C42-8-1) -> 0.96784489 | E44: ln(weight) | F44: =INDEX(LINEST(Data!$I$2:$I$1286,Data!$Y$2:$AF$1286,TRUE,TRUE),1,8) -> -0.30375764 | G44: =INDEX(LINEST(Data!$I$2:$I$1286,Data!$Y$2:$AF$1286,TRUE,TRUE),2,8) -> 0.032812741 | H44: =F44/G44 -> -9.2573077
A45: F (whole model) | C45: =INDEX(LINEST(Data!$I$2:$I$1286,Data!$Y$2:$AF$1286,TRUE,TRUE),4,1) -> 4831.9307 | E45: ln(horsepower) | F45: =INDEX(LINEST(Data!$I$2:$I$1286,Data!$Y$2:$AF$1286,TRUE,TRUE),1,7) -> -0.48301416 | G45: =INDEX(LINEST(Data!$I$2:$I$1286,Data!$Y$2:$AF$1286,TRUE,TRUE),2,7) -> 0.010122686 | H45: =F45/G45 -> -47.716007
A46: Residual df | C46: =INDEX(LINEST(Data!$I$2:$I$1286,Data!$Y$2:$AF$1286,TRUE,TRUE),4,2) -> 1276 | E46: footprint | F46: =INDEX(LINEST(Data!$I$2:$I$1286,Data!$Y$2:$AF$1286,TRUE,TRUE),1,6) -> -0.0022273382 | G46: =INDEX(LINEST(Data!$I$2:$I$1286,Data!$Y$2:$AF$1286,TRUE,TRUE),2,6) -> 0.00077700727 | H46: =F46/G46 -> -2.8665603
A47: SSE | C47: =INDEX(LINEST(Data!$I$2:$I$1286,Data!$Y$2:$AF$1286,TRUE,TRUE),5,2) -> 16.528749 | E47: hybrid | F47: =INDEX(LINEST(Data!$I$2:$I$1286,Data!$Y$2:$AF$1286,TRUE,TRUE),1,5) -> 0.20740284 | G47: =INDEX(LINEST(Data!$I$2:$I$1286,Data!$Y$2:$AF$1286,TRUE,TRUE),2,5) -> 0.0087459257 | H47: =F47/G47 -> 23.714224
E48: battery-electric | F48: =INDEX(LINEST(Data!$I$2:$I$1286,Data!$Y$2:$AF$1286,TRUE,TRUE),1,4) -> 4.8478824 | G48: =INDEX(LINEST(Data!$I$2:$I$1286,Data!$Y$2:$AF$1286,TRUE,TRUE),2,4) -> 0.55738184 | H48: =F48/G48 -> 8.6975966
E49: bev x ln(weight) | F49: =INDEX(LINEST(Data!$I$2:$I$1286,Data!$Y$2:$AF$1286,TRUE,TRUE),1,3) -> -0.7493466 | G49: =INDEX(LINEST(Data!$I$2:$I$1286,Data!$Y$2:$AF$1286,TRUE,TRUE),2,3) -> 0.082563013 | H49: =F49/G49 -> -9.0760569
E50: bev x ln(HP) | F50: =INDEX(LINEST(Data!$I$2:$I$1286,Data!$Y$2:$AF$1286,TRUE,TRUE),1,2) -> 0.47474939 | G50: =INDEX(LINEST(Data!$I$2:$I$1286,Data!$Y$2:$AF$1286,TRUE,TRUE),2,2) -> 0.021309926 | H50: =F50/G50 -> 22.278322
E51: bev x footprint | F51: =INDEX(LINEST(Data!$I$2:$I$1286,Data!$Y$2:$AF$1286,TRUE,TRUE),1,1) -> 0.0085667324 | G51: =INDEX(LINEST(Data!$I$2:$I$1286,Data!$Y$2:$AF$1286,TRUE,TRUE),2,1) -> 0.0024429633 | H51: =F51/G51 -> 3.5066971
A54: Mean residual by powertrain under spec C (why one merged flag fails), exponentiated to percent; spec C predictions are Data column AP
A55: gas_diesel | C55: =EXP(AVERAGEIF(Data!$C$2:$C$1286,"gas_diesel",Data!$AQ$2:$AQ$1286))-1 -> 2.6645353e-14
A56: hybrid | C56: =EXP(AVERAGEIF(Data!$C$2:$C$1286,"hybrid",Data!$AQ$2:$AQ$1286))-1 -> -0.49466598
A57: bev | C57: =EXP(AVERAGEIF(Data!$C$2:$C$1286,"bev",Data!$AQ$2:$AQ$1286))-1 -> 0.9276165
A59: Nested F-tests
A60: Test | B60: SSE restricted | C60: SSE full | D60: q | E60: df full | F60: F | G60: p
A61: Footprint earns its place? final CER (restricted) vs spec B (adds footprint) | B61: =CER!$C$22 -> 23.471981 | C61: =C19 -> 23.4715 | D61: 1 | E61: =C18 -> 1279 | F61: =((B61-C61)/D61)/(C61/E61) -> 0.026167688 | G61: =_xlfn.F.DIST.RT(F61,D61,E61) -> 0.87151702
A62: One merged flag vs two levels: spec C (restricted) vs spec B (full) | B62: =C29 -> 276.68542 | C62: =C19 -> 23.4715 | D62: 1 | E62: =C18 -> 1279 | F62: =((B62-C62)/D62)/(C62/E62) -> 13798.036 | G62: =_xlfn.F.DIST.RT(F62,D62,E62) -> 0
A63: Common slopes vs bev-specific slopes: spec B (restricted) vs spec E (full) | B63: =C19 -> 23.4715 | C63: =C47 -> 16.528749 | D63: 3 | E63: =C46 -> 1276 | F63: =((B63-C63)/D63)/(C63/E63) -> 178.65742 | G63: =_xlfn.F.DIST.RT(F63,D63,E63) -> 1.0555203e-96
A65: Battery-electric own elasticities under spec E (common slope plus interaction)
A66: weight elasticity for bev | C66: =F44+F49 -> -1.0531042
A67: horsepower elasticity for bev | C67: =F45+F50 -> -0.0082647715

Sheet Normalization
A1: Design-normalized fleet MPG: MPG_norm(t) = MPG(t) x (weight_t / weight_2024)^e_w x (HP_t / HP_2024)^e_h
A2: e_w and e_h are the CER's weight and horsepower elasticities (absolute values of CER!C8 and CER!C9). Fleet averages are production-weighted, EPA Automotive Trends, 1975 to 2024.
A3: e_w (weight elasticity) | C3: =ABS(CER!C8) -> 0.45270912
A4: e_h (horsepower elasticity) | C4: =ABS(CER!C9) -> 0.36894371
A5: 2024 fleet weight (lbs) | C5: =INDEX(C9:C58,MATCH(2024,A9:A58,0)) -> 4353.748
A6: 2024 fleet horsepower | C6: =INDEX(D9:D58,MATCH(2024,A9:A58,0)) -> 258.0114
A8: model year | B8: fleet MPG (raw) | C8: fleet weight (lbs) | D8: fleet HP | E8: weight factor | F8: HP factor | G8: MPG normalized to 2024 design | H8: ln(normalized) | J8: Trend fit: ln(normalized MPG) on model year
A9: 1975 | B9: 13.0597 | C9: 4060.399 | D9: 137.3346 | E9: =(C9/$C$5)^$C$3 -> 0.96891431 | F9: =(D9/$C$6)^$C$4 -> 0.79243102 | G9: =B9*E9*F9 -> 10.027208 | H9: =LN(G9) -> 2.3053022 | J9: Window | K9: 1975 to 2024 | L9: 2005 to 2024
A10: 1976 | B10: 14.22136 | C10: 4079.198 | D10: 135.0839 | E10: =(C10/$C$5)^$C$3 -> 0.97094256 | F10: =(D10/$C$6)^$C$4 -> 0.78761466 | G10: =B10*E10*F10 -> 10.875481 | H10: =LN(G10) -> 2.3865108 | J10: slope (per year, log units) | K10: =INDEX(LINEST(H9:H58,A9:A58,TRUE,TRUE),1,1) -> 0.017738874 | L10: =INDEX(LINEST(H39:H58,A39:A58,TRUE,TRUE),1,1) -> 0.021662592
A11: 1977 | B11: 15.06743 | C11: 3981.818 | D11: 135.9847 | E11: =(C11/$C$5)^$C$3 -> 0.96037996 | F11: =(D11/$C$6)^$C$4 -> 0.78954835 | G11: =B11*E11*F11 -> 11.425126 | H11: =LN(G11) -> 2.435815 | J11: intercept | K11: =INDEX(LINEST(H9:H58,A9:A58,TRUE,TRUE),1,2) -> -32.634981 | L11: =INDEX(LINEST(H39:H58,A39:A58,TRUE,TRUE),1,2) -> -40.538341
A12: 1978 | B12: 15.83777 | C12: 3715.238 | D12: 129.0248 | E12: =(C12/$C$5)^$C$3 -> 0.93071971 | F12: =(D12/$C$6)^$C$4 -> 0.77439153 | G12: =B12*E12*F12 -> 11.414938 | H12: =LN(G12) -> 2.4349228 | J12: R-squared of the trend line | K12: =INDEX(LINEST(H9:H58,A9:A58,TRUE,TRUE),3,1) -> 0.97954874 | L12: =INDEX(LINEST(H39:H58,A39:A58,TRUE,TRUE),3,1) -> 0.98473022
A13: 1979 | B13: 15.91271 | C13: 3655.465 | D13: 123.5922 | E13: =(C13/$C$5)^$C$3 -> 0.92391076 | F13: =(D13/$C$6)^$C$4 -> 0.76219824 | G13: =B13*E13*F13 -> 11.205781 | H13: =LN(G13) -> 2.4164298 | J13: growth per year, exp(slope) - 1 | K13: =EXP(K10)-1 -> 0.017897142 | L13: =EXP(L10)-1 -> 0.02189893
A14: 1980 | B14: 19.16493 | C14: 3227.876 | D14: 103.8276 | E14: =(C14/$C$5)^$C$3 -> 0.87331729 | F14: =(D14/$C$6)^$C$4 -> 0.71473809 | G14: =B14*E14*F14 -> 11.962618 | H14: =LN(G14) -> 2.4817866 | J14: projected 2035 | K14: =EXP(K11+K10*2035) -> 31.932604 | L14: =EXP(L11+L10*2035) -> 34.640887
A15: 1981 | B15: 20.52057 | C15: 3201.759 | D15: 102.1236 | E15: =(C15/$C$5)^$C$3 -> 0.8701113 | F15: =(D15/$C$6)^$C$4 -> 0.71038771 | G15: =B15*E15*F15 -> 12.6841 | H15: =LN(G15) -> 2.5403493 | J15: projected 2045 | K15: =EXP(K11+K10*2045) -> 38.130569 | L15: =EXP(L11+L10*2045) -> 43.019806
A16: 1982 | B16: 21.07205 | C16: 3201.843 | D16: 102.9528 | E16: =(C16/$C$5)^$C$3 -> 0.87012164 | F16: =(D16/$C$6)^$C$4 -> 0.71251037 | G16: =B16*E16*F16 -> 13.064053 | H16: =LN(G16) -> 2.5698644
A17: 1983 | B17: 20.95239 | C17: 3257.34 | D17: 106.9483 | E17: =(C17/$C$5)^$C$3 -> 0.87691715 | F17: =(D17/$C$6)^$C$4 -> 0.72258999 | G17: =B17*E17*F17 -> 13.276514 | H17: =LN(G17) -> 2.5859966 | J17: Normalized path (the trough vanishes) | K17: raw MPG | L17: normalized
A18: 1984 | B18: 21.00023 | C18: 3261.576 | D18: 108.5963 | E18: =(C18/$C$5)^$C$3 -> 0.87743323 | F18: =(D18/$C$6)^$C$4 -> 0.72667823 | G18: =B18*E18*F18 -> 13.389991 | H18: =LN(G18) -> 2.5945075 | J18: 1975 | K18: =INDEX(B9:B58,MATCH(J18,A9:A58,0)) -> 13.0597 | L18: =INDEX(G9:G58,MATCH(J18,A9:A58,0)) -> 10.027208
A19: 1985 | B19: 21.31942 | C19: 3271.127 | D19: 114.1306 | E19: =(C19/$C$5)^$C$3 -> 0.8785955 | F19: =(D19/$C$6)^$C$4 -> 0.74012753 | G19: =B19*E19*F19 -> 13.863437 | H19: =LN(G19) -> 2.629255 | J19: 1987 | K19: =INDEX(B9:B58,MATCH(J19,A9:A58,0)) -> 21.97197 | L19: =INDEX(G9:G58,MATCH(J19,A9:A58,0)) -> 14.346651
A20: 1986 | B20: 21.84433 | C20: 3237.974 | D20: 114.3758 | E20: =(C20/$C$5)^$C$3 -> 0.87455306 | F20: =(D20/$C$6)^$C$4 -> 0.7407138 | G20: =B20*E20*F20 -> 14.150615 | H20: =LN(G20) -> 2.6497581 | J20: 2004 | K20: =INDEX(B9:B58,MATCH(J20,A9:A58,0)) -> 19.2986 | L20: =INDEX(G9:G58,MATCH(J20,A9:A58,0)) -> 17.444399
A21: 1987 | B21: 21.97197 | C21: 3220.507 | D21: 117.6397 | E21: =(C21/$C$5)^$C$3 -> 0.87241415 | F21: =(D21/$C$6)^$C$4 -> 0.74844318 | G21: =B21*E21*F21 -> 14.346651 | H21: =LN(G21) -> 2.6635165 | J21: 2024 | K21: =INDEX(B9:B58,MATCH(J21,A9:A58,0)) -> 27.24521 | L21: =INDEX(G9:G58,MATCH(J21,A9:A58,0)) -> 27.24521
A22: 1988 | B22: 21.86353 | C22: 3283.465 | D22: 123.469 | E22: =(C22/$C$5)^$C$3 -> 0.88009417 | F22: =(D22/$C$6)^$C$4 -> 0.76191784 | G22: =B22*E22*F22 -> 14.660797 | H22: =LN(G22) -> 2.685177
A23: 1989 | B23: 21.42049 | C23: 3351.457 | D23: 128.748 | E23: =(C23/$C$5)^$C$3 -> 0.88829829 | F23: =(D23/$C$6)^$C$4 -> 0.77377819 | G23: =B23*E23*F23 -> 14.723285 | H23: =LN(G23) -> 2.6894302 | J23: Worked example, 1987 (the deck's normalization slide)
A24: 1990 | B24: 21.15752 | C24: 3426.038 | D24: 135.3422 | E24: =(C24/$C$5)^$C$3 -> 0.89719338 | F24: =(D24/$C$6)^$C$4 -> 0.78816997 | G24: =B24*E24*F24 -> 14.961347 | H24: =LN(G24) -> 2.70547 | J24: raw 1987 fleet MPG | K24: =B21 -> 21.97197
A25: 1991 | B25: 21.25642 | C25: 3409.555 | D25: 137.9169 | E25: =(C25/$C$5)^$C$3 -> 0.89523668 | F25: =(D25/$C$6)^$C$4 -> 0.79366899 | G25: =B25*E25*F25 -> 15.103145 | H25: =LN(G25) -> 2.714903 | J25: weight factor (3221/4354)^e_w | K25: =E21 -> 0.87241415
A26: 1992 | B26: 20.79365 | C26: 3512.305 | D26: 145.2572 | E26: =(C26/$C$5)^$C$3 -> 0.90735103 | F26: =(D26/$C$6)^$C$4 -> 0.8089992 | G26: =B26*E26*F26 -> 15.263501 | H26: =LN(G26) -> 2.7254644 | J26: HP factor (118/258)^e_h | K26: =F21 -> 0.74844318
A27: 1993 | B27: 20.8794 | C27: 3518.93 | D27: 146.8406 | E27: =(C27/$C$5)^$C$3 -> 0.90812543 | F27: =(D27/$C$6)^$C$4 -> 0.81224165 | G27: =B27*E27*F27 -> 15.401007 | H27: =LN(G27) -> 2.7344329 | J27: normalized 1987 MPG | K27: =G21 -> 14.346651
A28: 1994 | B28: 20.37752 | C28: 3603.432 | D28: 152.2823 | E28: =(C28/$C$5)^$C$3 -> 0.91793372 | F28: =(D28/$C$6)^$C$4 -> 0.82321974 | G28: =B28*E28*F28 -> 15.3985 | H28: =LN(G28) -> 2.7342701
A29: 1995 | B29: 20.48563 | C29: 3612.509 | D29: 158.1889 | E29: =(C29/$C$5)^$C$3 -> 0.91897978 | F29: =(D29/$C$6)^$C$4 -> 0.83485904 | G29: =B29*E29*F29 -> 15.716956 | H29: =LN(G29) -> 2.7547401
A30: 1996 | B30: 20.43168 | C30: 3658.786 | D30: 163.9606 | E30: =(C30/$C$5)^$C$3 -> 0.92429066 | F30: =(D30/$C$6)^$C$4 -> 0.84597047 | G30: =B30*E30*F30 -> 15.975993 | H30: =LN(G30) -> 2.7710871
A31: 1997 | B31: 20.15038 | C31: 3727.285 | D31: 169.2409 | E31: =(C31/$C$5)^$C$3 -> 0.93208476 | F31: =(D31/$C$6)^$C$4 -> 0.85592167 | G31: =B31*E31*F31 -> 16.075803 | H31: =LN(G31) -> 2.7773152
A32: 1998 | B32: 20.09648 | C32: 3744.005 | D32: 171.471 | E32: =(C32/$C$5)^$C$3 -> 0.9339753 | F32: =(D32/$C$6)^$C$4 -> 0.86006564 | G32: =B32*E32*F32 -> 16.143102 | H32: =LN(G32) -> 2.7814928
A33: 1999 | B33: 19.69506 | C33: 3835.375 | D33: 178.902 | E33: =(C33/$C$5)^$C$3 -> 0.94422587 | F33: =(D33/$C$6)^$C$4 -> 0.87363335 | G33: =B33*E33*F33 -> 16.246597 | H33: =LN(G33) -> 2.7878835
A34: 2000 | B34: 19.76896 | C34: 3821.286 | D34: 180.9861 | E34: =(C34/$C$5)^$C$3 -> 0.94265404 | F34: =(D34/$C$6)^$C$4 -> 0.87737449 | G34: =B34*E34*F34 -> 16.350128 | H34: =LN(G34) -> 2.7942357
A35: 2001 | B35: 19.62363 | C35: 3879.288 | D35: 186.9203 | E35: =(C35/$C$5)^$C$3 -> 0.94910481 | F35: =(D35/$C$6)^$C$4 -> 0.88788019 | G35: =B35*E35*F35 -> 16.536663 | H35: =LN(G35) -> 2.8055799
A36: 2002 | B36: 19.45354 | C36: 3950.932 | D36: 195.4821 | E36: =(C36/$C$5)^$C$3 -> 0.95700034 | F36: =(D36/$C$6)^$C$4 -> 0.90267313 | G36: =B36*E36*F36 -> 16.805106 | H36: =LN(G36) -> 2.8216828
A37: 2003 | B37: 19.58451 | C37: 3998.835 | D37: 198.5784 | E37: =(C37/$C$5)^$C$3 -> 0.96223587 | F37: =(D37/$C$6)^$C$4 -> 0.90792204 | G37: =B37*E37*F37 -> 17.109716 | H37: =LN(G37) -> 2.8396465
A38: 2004 | B38: 19.2986 | C38: 4111.072 | D38: 210.5212 | E38: =(C38/$C$5)^$C$3 -> 0.97436983 | F38: =(D38/$C$6)^$C$4 -> 0.9276975 | G38: =B38*E38*F38 -> 17.444399 | H38: =LN(G38) -> 2.8590186
A39: 2005 | B39: 19.88375 | C39: 4059.441 | D39: 209.0953 | E39: =(C39/$C$5)^$C$3 -> 0.96881081 | F39: =(D39/$C$6)^$C$4 -> 0.92537428 | G39: =B39*E39*F39 -> 17.826032 | H39: =LN(G39) -> 2.8806599
... A58: 2024 | B58: 27.24521 | C58: 4353.748 | D58: 258.0114 | E58: =(C58/$C$5)^$C$3 -> 1 | F58: =(D58/$C$6)^$C$4 -> 1 | G58: =B58*E58*F58 -> 27.24521 | H58: =LN(G58) -> 3.3048777

Sheet Diffusion
A1: Technology S-curves (deck slide 7): logistic diffusion, share(t) = L / (1 + exp(-k (t - t0)))
A2: Share data: EPA Automotive Trends technology-share series (production-weighted), through the preliminary 2025 point, as used in the fit. L, k, t0 are the nonlinear least-squares estimates from 10_stats.py (scipy curve_fit; 95% CIs from a 300-draw residual bootstrap); they are the only typed inputs on this sheet. Everything else is live: the fitted curve, residuals, R-squared, 10-to-90% years, projections, and an independent Excel cross-check that re-estimates k and t0 by a linearized fit (SLOPE and INTERCEPT of ln(share / (L - share)) on year, valid where 0 < share < L).
A4: Technology | B4: Ceiling L | C4: L status | D4: k (NLS) | E4: 95% CI k | F4: midpoint t0 (NLS) | G4: 95% CI t0 | H4: 10% to 90% years = LN(81)/k | I4: R-squared (live) | J4: k, Excel logit cross-check | K4: t0, Excel logit cross-check | L4: latest share (live) | M4: projected 2030 | N4: projected 2035 | O4: projected 2040
A5: Turbo | B5: 0.478 | C5: estimated | D5: 0.287 | E5: 0.243 to 0.324 | F5: 2017.3 | G5: 2016.5 to 2018.5 | H5: =LN(81)/D5 -> 15.31167 | I5: =1-SUMSQ(D16:D45)/DEVSQ(B16:B45) -> 0.98880164 | J5: =SLOPE(E16:E45,A16:A45) -> 0.24909092 | K5: =-INTERCEPT(E16:E45,A16:A45)/J5 -> 2017.2223 | L5: =B45 -> 0.448 | M5: =B5/(1+EXP(-D5*(2030-F5))) -> 0.46583063 | N5: =B5/(1+EXP(-D5*(2035-F5))) -> 0.47504497 | O5: =B5/(1+EXP(-D5*(2040-F5))) -> 0.47729303
A6: GDI | B6: 0.535 | C6: estimated | D6: 0.612 | E6: 0.547 to 0.692 | F6: 2012.6 | G6: 2012.4 to 2012.8 | H6: =LN(81)/D6 -> 7.1804725 | I6: =1-SUMSQ(J16:J33)/DEVSQ(H16:H33) -> 0.99270687 | J6: =SLOPE(K16:K33,G16:G33) -> 0.45437303 | K6: =-INTERCEPT(K16:K33,G16:G33)/J6 -> 2012.7471 | L6: =H33 -> 0.52 | M6: =B6/(1+EXP(-D6*(2030-F6))) -> 0.53498731 | N6: =B6/(1+EXP(-D6*(2035-F6))) -> 0.5349994 | O6: =B6/(1+EXP(-D6*(2040-F6))) -> 0.53499997
A7: CVT | B7: 0.216 | C7: estimated | D7: 0.437 | E7: 0.346 to 0.546 | F7: 2011.5 | G7: 2010.9 to 2012.1 | H7: =LN(81)/D7 -> 10.055948 | I7: =1-SUMSQ(P16:P50)/DEVSQ(N16:N50) -> 0.97299125 | J7: =SLOPE(Q16:Q50,M16:M50) -> 0.30699425 | K7: =-INTERCEPT(Q16:Q50,M16:M50)/J7 -> 2011.608 | L7: =N50 -> 0.192 | M7: =B7/(1+EXP(-D7*(2030-F7))) -> 0.21593343 | N7: =B7/(1+EXP(-D7*(2035-F7))) -> 0.21599251 | O7: =B7/(1+EXP(-D7*(2040-F7))) -> 0.21599916
A8: Hybrid (HEV) | B8: 1 | C8: assumed (takeoff) | D8: 0.184 | E8: 0.126 to 0.203 | F8: 2036.2 | G8: 2034.5 to 2042.4 | H8: =LN(81)/D8 -> 23.882876 | I8: =1-SUMSQ(V16:V40)/DEVSQ(T16:T40) -> 0.82205316 | J8: =SLOPE(W16:W40,S16:S40) -> 0.15749534 | K8: =-INTERCEPT(W16:W40,S16:S40)/J8 -> 2038.3201 | L8: =T40 -> 0.14 | M8: =B8/(1+EXP(-D8*(2030-F8))) -> 0.24217351 | N8: =B8/(1+EXP(-D8*(2035-F8))) -> 0.44502317 | O8: =B8/(1+EXP(-D8*(2040-F8))) -> 0.66801038
A9: BEV | B9: 1 | C9: assumed (takeoff) | D9: 0.291 | E9: 0.229 to 0.398 | F9: 2032.3 | G9: 2029.7 to 2034.5 | H9: =LN(81)/D9 -> 15.1012 | I9: =1-SUMSQ(AB16:AB30)/DEVSQ(Z16:Z30) -> 0.90219117 | J9: =SLOPE(AC16:AC30,Y16:Y30) -> 0.34784091 | K9: =-INTERCEPT(AC16:AC30,Y16:Y30)/J9 -> 2030.8594 | L9: =Z30 -> 0.098 | M9: =B9/(1+EXP(-D9*(2030-F9))) -> 0.3386536 | N9: =B9/(1+EXP(-D9*(2035-F9))) -> 0.68690729 | O9: =B9/(1+EXP(-D9*(2040-F9))) -> 0.90384531
A11: Reading: the three completed curves (turbo, GDI, CVT) have data on both sides of the midpoint, so L is estimated. Hybrid and BEV are still on the ramp: a free fit cannot identify L, so it is fixed at 1 (takeoff assumed) and only k and t0 are estimated; their midpoints lie beyond the data. The logit cross-check weights points differently from nonlinear least squares (it up-weights the tails), so it lands near, not on, the NLS values.
A14: Turbo | G14: GDI | M14: CVT | S14: Hybrid (HEV) | Y14: BEV
A15: year | B15: share | C15: fitted | D15: residual | E15: logit ln(s/(L-s)) | G15: year | H15: share | I15: fitted | J15: residual | K15: logit ln(s/(L-s)) | M15: year | N15: share | O15: fitted | P15: residual | Q15: logit ln(s/(L-s)) | S15: year | T15: share | U15: fitted | V15: residual | W15: logit ln(s/(L-s)) | Y15: year | Z15: share | AA15: fitted | AB15: residual | AC15: logit ln(s/(L-s))
A16: 1996 | B16: 0.001 | C16: =$B$5/(1+EXP(-$D$5*(A16-$F$5))) -> 0.0010558008 | D16: =B16-C16 -> -5.5800769e-05 | E16: =IF(AND(B16>0,B16<$B$5),LN(B16/($B$5-B16)),"") -> -6.1675165 | G16: 2008 | H16: 0.023 | I16: =$B$6/(1+EXP(-$D$6*(G16-$F$6))) -> 0.030231942 | J16: =H16-I16 -> -0.0072319416 | K16: =IF(AND(H16>0,H16<$B$6),LN(H16/($B$6-H16)),"") -> -3.1028304 | M16: 1989 | N16: 0.001 | O16: =$B$7/(1+EXP(-$D$7*(M16-$F$7))) -> 1.1593911e-05 | P16: =N16-O16 -> 0.00098840609 | Q16: =IF(AND(N16>0,N16<$B$7),LN(N16/($B$7-N16)),"") -> -5.370638 | S16: 2001 | T16: 0.001 | U16: =$B$8/(1+EXP(-$D$8*(S16-$F$8))) -> 0.0015363627 | V16: =T16-U16 -> -0.00053636269 | W16: =IF(AND(T16>0,T16<$B$8),LN(T16/($B$8-T16)),"") -> -6.9067548 | Y16: 2011 | Z16: 0.001 | AA16: =$B$9/(1+EXP(-$D$9*(Y16-$F$9))) -> 0.0020287594 | AB16: =Z16-AA16 -> -0.0010287594 | AC16: =IF(AND(Z16>0,Z16<$B$9),LN(Z16/($B$9-Z16)),"") -> -6.9067548
A17: 1997 | B17: 0.004 | C17: =$B$5/(1+EXP(-$D$5*(A17-$F$5))) -> 0.0014057423 | D17: =B17-C17 -> 0.0025942577 | E17: =IF(AND(B17>0,B17<$B$5),LN(B17/($B$5-B17)),"") -> -4.774913 | G17: 2009 | H17: 0.042 | I17: =$B$6/(1+EXP(-$D$6*(G17-$F$6))) -> 0.05321297 | J17: =H17-I17 -> -0.01121297 | K17: =IF(AND(H17>0,H17<$B$6),LN(H17/($B$6-H17)),"") -> -2.4628396 | M17: 1990 | N17: 0 | O17: =$B$7/(1+EXP(-$D$7*(M17-$F$7))) -> 1.7947496e-05 | P17: =N17-O17 -> -1.7947496e-05 | Q17: =IF(AND(N17>0,N17<$B$7),LN(N17/($B$7-N17)),"") | S17: 2002 | T17: 0.001 | U17: =$B$8/(1+EXP(-$D$8*(S17-$F$8))) -> 0.0018461593 | V17: =T17-U17 -> -0.00084615927 | W17: =IF(AND(T17>0,T17<$B$8),LN(T17/($B$8-T17)),"") -> -6.9067548 | Y17: 2012 | Z17: 0.001 | AA17: =$B$9/(1+EXP(-$D$9*(Y17-$F$9))) -> 0.002712144 | AB17: =Z17-AA17 -> -0.001712144 | AC17: =IF(AND(Z17>0,Z17<$B$9),LN(Z17/($B$9-Z17)),"") -> -6.9067548
A18: 1998 | B18: 0.007 | C18: =$B$5/(1+EXP(-$D$5*(A18-$F$5))) -> 0.0018712158 | D18: =B18-C18 -> 0.0051287842 | E18: =IF(AND(B18>0,B18<$B$5),LN(B18/($B$5-B18)),"") -> -4.2089479 | G18: 2010 | H18: 0.083 | I18: =$B$6/(1+EXP(-$D$6*(G18-$F$6))) -> 0.090530096 | J18: =H18-I18 -> -0.0075300958 | K18: =IF(AND(H18>0,H18<$B$6),LN(H18/($B$6-H18)),"") -> -1.6948416 | M18: 1991 | N18: 0 | O18: =$B$7/(1+EXP(-$D$7*(M18-$F$7))) -> 2.7782465e-05 | P18: =N18-O18 -> -2.7782465e-05 | Q18: =IF(AND(N18>0,N18<$B$7),LN(N18/($B$7-N18)),"") | S18: 2003 | T18: 0.001 | U18: =$B$8/(1+EXP(-$D$8*(S18-$F$8))) -> 0.0022182853 | V18: =T18-U18 -> -0.0012182853 | W18: =IF(AND(T18>0,T18<$B$8),LN(T18/($B$8-T18)),"") -> -6.9067548 | Y18: 2013 | Z18: 0.003 | AA18: =$B$9/(1+EXP(-$D$9*(Y18-$F$9))) -> 0.0036248895 | AB18: =Z18-AA18 -> -0.00062488949 | AC18: =IF(AND(Z18>0,Z18<$B$9),LN(Z18/($B$9-Z18)),"") -> -5.8061385
A19: 1999 | B19: 0.013 | C19: =$B$5/(1+EXP(-$D$5*(A19-$F$5))) -> 0.0024900129 | D19: =B19-C19 -> 0.010509987 | E19: =IF(AND(B19>0,B19<$B$5),LN(B19/($B$5-B19)),"") -> -3.577088 | G19: 2011 | H19: 0.154 | I19: =$B$6/(1+EXP(-$D$6*(G19-$F$6))) -> 0.14608204 | J19: =H19-I19 -> 0.0079179558 | K19: =IF(AND(H19>0,H19<$B$6),LN(H19/($B$6-H19)),"") -> -0.90584677 | M19: 1992 | N19: 0 | O19: =$B$7/(1+EXP(-$D$7*(M19-$F$7))) -> 4.3005782e-05 | P19: =N19-O19 -> -4.3005782e-05 | Q19: =IF(AND(N19>0,N19<$B$7),LN(N19/($B$7-N19)),"") | S19: 2004 | T19: 0.003 | U19: =$B$8/(1+EXP(-$D$8*(S19-$F$8))) -> 0.0026652197 | V19: =T19-U19 -> 0.00033478028 | W19: =IF(AND(T19>0,T19<$B$8),LN(T19/($B$8-T19)),"") -> -5.8061385 | Y19: 2014 | Z19: 0.003 | AA19: =$B$9/(1+EXP(-$D$9*(Y19-$F$9))) -> 0.0048433188 | AB19: =Z19-AA19 -> -0.0018433188 | AC19: =IF(AND(Z19>0,Z19<$B$9),LN(Z19/($B$9-Z19)),"") -> -5.8061385
A20: 2000 | B20: 0.012 | C20: =$B$5/(1+EXP(-$D$5*(A20-$F$5))) -> 0.0033120181 | D20: =B20-C20 -> 0.0086879819 | E20: =IF(AND(B20>0,B20<$B$5),LN(B20/($B$5-B20)),"") -> -3.659279 | G20: 2012 | H20: 0.225 | I20: =$B$6/(1+EXP(-$D$6*(G20-$F$6))) -> 0.21893151 | J20: =H20-I20 -> 0.0060684914 | K20: =IF(AND(H20>0,H20<$B$6),LN(H20/($B$6-H20)),"") -> -0.3204719 | M20: 1993 | N20: 0 | O20: =$B$7/(1+EXP(-$D$7*(M20-$F$7))) -> 6.6568098e-05 | P20: =N20-O20 -> -6.6568098e-05 | Q20: =IF(AND(N20>0,N20<$B$7),LN(N20/($B$7-N20)),"") | S20: 2005 | T20: 0.008 | U20: =$B$8/(1+EXP(-$D$8*(S20-$F$8))) -> 0.0032019123 | V20: =T20-U20 -> 0.0047980877 | W20: =IF(AND(T20>0,T20<$B$8),LN(T20/($B$8-T20)),"") -> -4.8202816 | Y20: 2015 | Z20: 0.005 | AA20: =$B$9/(1+EXP(-$D$9*(Y20-$F$9))) -> 0.0064686383 | AB20: =Z20-AA20 -> -0.0014686383 | AC20: =IF(AND(Z20>0,Z20<$B$9),LN(Z20/($B$9-Z20)),"") -> -5.2933048
A21: 2001 | B21: 0.018 | C21: =$B$5/(1+EXP(-$D$5*(A21-$F$5))) -> 0.0044028718 | D21: =B21-C21 -> 0.013597128 | E21: =IF(AND(B21>0,B21<$B$5),LN(B21/($B$5-B21)),"") -> -3.2408547 | G21: 2013 | H21: 0.305 | I21: =$B$6/(1+EXP(-$D$6*(G21-$F$6))) -> 0.30007946 | J21: =H21-I21 -> 0.004920537 | K21: =IF(AND(H21>0,H21<$B$6),LN(H21/($B$6-H21)),"") -> 0.28223247 | M21: 1996 | N21: 0 | O21: =$B$7/(1+EXP(-$D$7*(M21-$F$7))) -> 0.0002467537 | P21: =N21-O21 -> -0.0002467537 | Q21: =IF(AND(N21>0,N21<$B$7),LN(N21/($B$7-N21)),"") | S21: 2006 | T21: 0.012 | U21: =$B$8/(1+EXP(-$D$8*(S21-$F$8))) -> 0.0038462614 | V21: =T21-U21 -> 0.0081537386 | W21: =IF(AND(T21>0,T21<$B$8),LN(T21/($B$8-T21)),"") -> -4.410776 | Y21: 2016 | Z21: 0.005 | AA21: =$B$9/(1+EXP(-$D$9*(Y21-$F$9))) -> 0.0086346496 | AB21: =Z21-AA21 -> -0.0036346496 | AC21: =IF(AND(Z21>0,Z21<$B$9),LN(Z21/($B$9-Z21)),"") -> -5.2933048
A22: 2002 | B22: 0.02 | C22: =$B$5/(1+EXP(-$D$5*(A22-$F$5))) -> 0.0058485849 | D22: =B22-C22 -> 0.014151415 | E22: =IF(AND(B22>0,B22<$B$5),LN(B22/($B$5-B22)),"") -> -3.1311369 | G22: 2014 | H22: 0.374 | I22: =$B$6/(1+EXP(-$D$6*(G22-$F$6))) -> 0.37556553 | J22: =H22-I22 -> -0.0015655324 | K22: =IF(AND(H22>0,H22<$B$6),LN(H22/($B$6-H22)),"") -> 0.84285143 | M22: 1997 | N22: 0 | O22: =$B$7/(1+EXP(-$D$7*(M22-$F$7))) -> 0.00038174955 | P22: =N22-O22 -> -0.00038174955 | Q22: =IF(AND(N22>0,N22<$B$7),LN(N22/($B$7-N22)),"") | S22: 2007 | T22: 0.019 | U22: =$B$8/(1+EXP(-$D$8*(S22-$F$8))) -> 0.0046196775 | V22: =T22-U22 -> 0.014380322 | W22: =IF(AND(T22>0,T22<$B$8),LN(T22/($B$8-T22)),"") -> -3.9441335 | Y22: 2017 | Z22: 0.006 | AA22: =$B$9/(1+EXP(-$D$9*(Y22-$F$9))) -> 0.011517538 | AB22: =Z22-AA22 -> -0.0055175378 | AC22: =IF(AND(Z22>0,Z22<$B$9),LN(Z22/($B$9-Z22)),"") -> -5.1099777
A23: 2003 | B23: 0.01 | C23: =$B$5/(1+EXP(-$D$5*(A23-$F$5))) -> 0.0077612282 | D23: =B23-C23 -> 0.0022387718 | E23: =IF(AND(B23>0,B23<$B$5),LN(B23/($B$5-B23)),"") -> -3.8458832 | G23: 2015 | H23: 0.419 | I23: =$B$6/(1+EXP(-$D$6*(G23-$F$6))) -> 0.43488808 | J23: =H23-I23 -> -0.015888084 | K23: =IF(AND(H23>0,H23<$B$6),LN(H23/($B$6-H23)),"") -> 1.2842807 | M23: 1998 | N23: 0 | O23: =$B$7/(1+EXP(-$D$7*(M23-$F$7))) -> 0.00059039784 | P23: =N23-O23 -> -0.00059039784 | Q23: =IF(AND(N23>0,N23<$B$7),LN(N23/($B$7-N23)),"") | S23: 2008 | T23: 0.022 | U23: =$B$8/(1+EXP(-$D$8*(S23-$F$8))) -> 0.005547748 | V23: =T23-U23 -> 0.016452252 | W23: =IF(AND(T23>0,T23<$B$8),LN(T23/($B$8-T23)),"") -> -3.7944672 | Y23: 2018 | Z23: 0.014 | AA23: =$B$9/(1+EXP(-$D$9*(Y23-$F$9))) -> 0.015348047 | AB23: =Z23-AA23 -> -0.001348047 | AC23: =IF(AND(Z23>0,Z23<$B$9),LN(Z23/($B$9-Z23)),"") -> -4.254599
A24: 2004 | B24: 0.021 | C24: =$B$5/(1+EXP(-$D$5*(A24-$F$5))) -> 0.010285731 | D24: =B24-C24 -> 0.010714269 | E24: =IF(AND(B24>0,B24<$B$5),LN(B24/($B$5-B24)),"") -> -3.080161 | G24: 2016 | H24: 0.48 | I24: =$B$6/(1+EXP(-$D$6*(G24-$F$6))) -> 0.4756273 | J24: =H24-I24 -> 0.0043727021 | K24: =IF(AND(H24>0,H24<$B$6),LN(H24/($B$6-H24)),"") -> 2.1664529 | M24: 1999 | N24: 0 | O24: =$B$7/(1+EXP(-$D$7*(M24-$F$7))) -> 0.00091260188 | P24: =N24-O24 -> -0.00091260188 | Q24: =IF(AND(N24>0,N24<$B$7),LN(N24/($B$7-N24)),"") | S24: 2009 | T24: 0.02 | U24: =$B$8/(1+EXP(-$D$8*(S24-$F$8))) -> 0.0066610157 | V24: =T24-U24 -> 0.013338984 | W24: =IF(AND(T24>0,T24<$B$8),LN(T24/($B$8-T24)),"") -> -3.8918203 | Y24: 2019 | Z24: 0.012 | AA24: =$B$9/(1+EXP(-$D$9*(Y24-$F$9))) -> 0.020426184 | AB24: =Z24-AA24 -> -0.0084261838 | AC24: =IF(AND(Z24>0,Z24<$B$9),LN(Z24/($B$9-Z24)),"") -> -4.410776
A25: 2005 | B25: 0.014 | C25: =$B$5/(1+EXP(-$D$5*(A25-$F$5))) -> 0.013607619 | D25: =B25-C25 -> 0.00039238117 | E25: =IF(AND(B25>0,B25<$B$5),LN(B25/($B$5-B25)),"") -> -3.5008272 | G25: 2017 | H25: 0.497 | I25: =$B$6/(1+EXP(-$D$6*(G25-$F$6))) -> 0.50108124 | J25: =H25-I25 -> -0.0040812403 | K25: =IF(AND(H25>0,H25<$B$6),LN(H25/($B$6-H25)),"") -> 2.5710039 | M25: 2000 | N25: 0 | O25: =$B$7/(1+EXP(-$D$7*(M25-$F$7))) -> 0.0014094951 | P25: =N25-O25 -> -0.0014094951 | Q25: =IF(AND(N25>0,N25<$B$7),LN(N25/($B$7-N25)),"") | S25: 2010 | T25: 0.038 | U25: =$B$8/(1+EXP(-$D$8*(S25-$F$8))) -> 0.0079958868 | V25: =T25-U25 -> 0.030004113 | W25: =IF(AND(T25>0,T25<$B$8),LN(T25/($B$8-T25)),"") -> -3.2314283 | Y25: 2020 | Z25: 0.018 | AA25: =$B$9/(1+EXP(-$D$9*(Y25-$F$9))) -> 0.027138192 | AB25: =Z25-AA25 -> -0.0091381923 | AC25: =IF(AND(Z25>0,Z25<$B$9),LN(Z25/($B$9-Z25)),"") -> -3.9992196
A26: 2006 | B26: 0.018 | C26: =$B$5/(1+EXP(-$D$5*(A26-$F$5))) -> 0.017961147 | D26: =B26-C26 -> 3.8852585e-05 | E26: =IF(AND(B26>0,B26<$B$5),LN(B26/($B$5-B26)),"") -> -3.2408547 | G26: 2018 | H26: 0.502 | I26: =$B$6/(1+EXP(-$D$6*(G26-$F$6))) -> 0.51605732 | J26: =H26-I26 -> -0.014057315 | K26: =IF(AND(H26>0,H26<$B$6),LN(H26/($B$6-H26)),"") -> 2.7220926 | M26: 2001 | N26: 0 | O26: =$B$7/(1+EXP(-$D$7*(M26-$F$7))) -> 0.0021742019 | P26: =N26-O26 -> -0.0021742019 | Q26: =IF(AND(N26>0,N26<$B$7),LN(N26/($B$7-N26)),"") | S26: 2011 | T26: 0.022 | U26: =$B$8/(1+EXP(-$D$8*(S26-$F$8))) -> 0.0095956825 | V26: =T26-U26 -> 0.012404317 | W26: =IF(AND(T26>0,T26<$B$8),LN(T26/($B$8-T26)),"") -> -3.7944672 | Y26: 2021 | Z26: 0.032 | AA26: =$B$9/(1+EXP(-$D$9*(Y26-$F$9))) -> 0.035974756 | AB26: =Z26-AA26 -> -0.0039747564 | AC26: =IF(AND(Z26>0,Z26<$B$9),LN(Z26/($B$9-Z26)),"") -> -3.4094962
A27: 2007 | B27: 0.025 | C27: =$B$5/(1+EXP(-$D$5*(A27-$F$5))) -> 0.023636622 | D27: =B27-C27 -> 0.0013633784 | E27: =IF(AND(B27>0,B27<$B$5),LN(B27/($B$5-B27)),"") -> -2.8970163 | G27: 2019 | H27: 0.529 | I27: =$B$6/(1+EXP(-$D$6*(G27-$F$6))) -> 0.52455882 | J27: =H27-I27 -> 0.0044411796 | K27: =IF(AND(H27>0,H27<$B$6),LN(H27/($B$6-H27)),"") -> 4.479229 | M27: 2002 | N27: 0.001 | O27: =$B$7/(1+EXP(-$D$7*(M27-$F$7))) -> 0.0033473207 | P27: =N27-O27 -> -0.0023473207 | Q27: =IF(AND(N27>0,N27<$B$7),LN(N27/($B$7-N27)),"") -> -5.370638 | S27: 2012 | T27: 0.03 | U27: =$B$8/(1+EXP(-$D$8*(S27-$F$8))) -> 0.011511847 | V27: =T27-U27 -> 0.018488153 | W27: =IF(AND(T27>0,T27<$B$8),LN(T27/($B$8-T27)),"") -> -3.4760987 | Y27: 2022 | Z27: 0.052 | AA27: =$B$9/(1+EXP(-$D$9*(Y27-$F$9))) -> 0.047547999 | AB27: =Z27-AA27 -> 0.0044520007 | AC27: =IF(AND(Z27>0,Z27<$B$9),LN(Z27/($B$9-Z27)),"") -> -2.9031108
... A30: 2010 | B30: 0.026 | C30: =$B$5/(1+EXP(-$D$5*(A30-$F$5))) -> 0.052376366 | D30: =B30-C30 -> -0.026376366 | E30: =IF(AND(B30>0,B30<$B$5),LN(B30/($B$5-B30)),"") -> -2.8555856 | G30: 2022 | H30: 0.523 | I30: =$B$6/(1+EXP(-$D$6*(G30-$F$6))) -> 0.53330735 | J30: =H30-I30 -> -0.010307346 | K30: =IF(AND(H30>0,H30<$B$6),LN(H30/($B$6-H30)),"") -> 3.7746748 | M30: 2005 | N30: 0.013 | O30: =$B$7/(1+EXP(-$D$7*(M30-$F$7))) -> 0.011917685 | P30: =N30-O30 -> 0.0010823152 | Q30: =IF(AND(N30>0,N30<$B$7),LN(N30/($B$7-N30)),"") -> -2.7482566 | S30: 2015 | T30: 0.024 | U30: =$B$8/(1+EXP(-$D$8*(S30-$F$8))) -> 0.019824754 | V30: =T30-U30 -> 0.0041752456 | W30: =IF(AND(T30>0,T30<$B$8),LN(T30/($B$8-T30)),"") -> -3.7054088 | Y30: 2025 | Z30: 0.098 | AA30: =$B$9/(1+EXP(-$D$9*(Y30-$F$9))) -> 0.10675733 | AB30: =Z30-AA30 -> -0.0087573277 | AC30: =IF(AND(Z30>0,Z30<$B$9),LN(Z30/($B$9-Z30)),"") -> -2.219647
A31: 2011 | B31: 0.061 | C31: =$B$5/(1+EXP(-$D$5*(A31-$F$5))) -> 0.067334863 | D31: =B31-C31 -> -0.0063348632 | E31: =IF(AND(B31>0,B31<$B$5),LN(B31/($B$5-B31)),"") -> -1.9222124 | G31: 2023 | H31: 0.505 | I31: =$B$6/(1+EXP(-$D$6*(G31-$F$6))) -> 0.5340808 | J31: =H31-I31 -> -0.029080801 | K31: =IF(AND(H31>0,H31<$B$6),LN(H31/($B$6-H31)),"") -> 2.823361 | M31: 2006 | N31: 0.014 | O31: =$B$7/(1+EXP(-$D$7*(M31-$F$7))) -> 0.017907738 | P31: =N31-O31 -> -0.0039077377 | Q31: =IF(AND(N31>0,N31<$B$7),LN(N31/($B$7-N31)),"") -> -2.6692104 | S31: 2016 | T31: 0.018 | U31: =$B$8/(1+EXP(-$D$8*(S31-$F$8))) -> 0.023734613 | V31: =T31-U31 -> -0.0057346134 | W31: =IF(AND(T31>0,T31<$B$8),LN(T31/($B$8-T31)),"") -> -3.9992196
A32: 2012 | B32: 0.075 | C32: =$B$5/(1+EXP(-$D$5*(A32-$F$5))) -> 0.085705207 | D32: =B32-C32 -> -0.010705207 | E32: =IF(AND(B32>0,B32<$B$5),LN(B32/($B$5-B32)),"") -> -1.6814484 | G32: 2024 | H32: 0.562 | I32: =$B$6/(1+EXP(-$D$6*(G32-$F$6))) -> 0.53450116 | J32: =H32-I32 -> 0.027498842 | K32: =IF(AND(H32>0,H32<$B$6),LN(H32/($B$6-H32)),"") | M32: 2007 | N32: 0.051 | O32: =$B$7/(1+EXP(-$D$7*(M32-$F$7))) -> 0.026517309 | P32: =N32-O32 -> 0.024482691 | Q32: =IF(AND(N32>0,N32<$B$7),LN(N32/($B$7-N32)),"") -> -1.1741198 | S32: 2017 | T32: 0.023 | U32: =$B$8/(1+EXP(-$D$8*(S32-$F$8))) -> 0.028393242 | V32: =T32-U32 -> -0.0053932418 | W32: =IF(AND(T32>0,T32<$B$8),LN(T32/($B$8-T32)),"") -> -3.7489924
A33: 2013 | B33: 0.13 | C33: =$B$5/(1+EXP(-$D$5*(A33-$F$5))) -> 0.1077721 | D33: =B33-C33 -> 0.022227904 | E33: =IF(AND(B33>0,B33<$B$5),LN(B33/($B$5-B33)),"") -> -0.98466803 | G33: 2025 | H33: 0.52 | I33: =$B$6/(1+EXP(-$D$6*(G33-$F$6))) -> 0.53472938 | J33: =H33-I33 -> -0.01472938 | K33: =IF(AND(H33>0,H33<$B$6),LN(H33/($B$6-H33)),"") -> 3.5457786 | M33: 2008 | N33: 0.055 | O33: =$B$7/(1+EXP(-$D$7*(M33-$F$7))) -> 0.03846244 | P33: =N33-O33 -> 0.01653756 | Q33: =IF(AND(N33>0,N33<$B$7),LN(N33/($B$7-N33)),"") -> -1.0740712 | S33: 2018 | T33: 0.019 | U33: =$B$8/(1+EXP(-$D$8*(S33-$F$8))) -> 0.033934482 | V33: =T33-U33 -> -0.014934482 | W33: =IF(AND(T33>0,T33<$B$8),LN(T33/($B$8-T33)),"") -> -3.9441335
A34: 2014 | B34: 0.138 | C34: =$B$5/(1+EXP(-$D$5*(A34-$F$5))) -> 0.1335859 | D34: =B34-C34 -> 0.0044141004 | E34: =IF(AND(B34>0,B34<$B$5),LN(B34/($B$5-B34)),"") -> -0.90169193 | M34: 2009 | N34: 0.073 | O34: =$B$7/(1+EXP(-$D$7*(M34-$F$7))) -> 0.054247926 | P34: =N34-O34 -> 0.018752074 | Q34: =IF(AND(N34>0,N34<$B$7),LN(N34/($B$7-N34)),"") -> -0.67238519 | S34: 2019 | T34: 0.025 | U34: =$B$8/(1+EXP(-$D$8*(S34-$F$8))) -> 0.040512062 | V34: =T34-U34 -> -0.015512062 | W34: =IF(AND(T34>0,T34<$B$8),LN(T34/($B$8-T34)),"") -> -3.6635616
A35: 2015 | B35: 0.148 | C35: =$B$5/(1+EXP(-$D$5*(A35-$F$5))) -> 0.1628628 | D35: =B35-C35 -> -0.014862797 | E35: =IF(AND(B35>0,B35<$B$5),LN(B35/($B$5-B35)),"") -> -0.80188038 | M35: 2010 | N35: 0.072 | O35: =$B$7/(1+EXP(-$D$7*(M35-$F$7))) -> 0.073818259 | P35: =N35-O35 -> -0.0018182586 | Q35: =IF(AND(N35>0,N35<$B$7),LN(N35/($B$7-N35)),"") -> -0.69314718 | S35: 2020 | T35: 0.031 | U35: =$B$8/(1+EXP(-$D$8*(S35-$F$8))) -> 0.048300841 | V35: =T35-U35 -> -0.017300841 | W35: =IF(AND(T35>0,T35<$B$8),LN(T35/($B$8-T35)),"") -> -3.4422774
A36: 2016 | B36: 0.194 | C36: =$B$5/(1+EXP(-$D$5*(A36-$F$5))) -> 0.19492465 | D36: =B36-C36 -> -0.00092465496 | E36: =IF(AND(B36>0,B36<$B$5),LN(B36/($B$5-B36)),"") -> -0.38111608 | M36: 2011 | N36: 0.08 | O36: =$B$7/(1+EXP(-$D$7*(M36-$F$7))) -> 0.09624772 | P36: =N36-O36 -> -0.01624772 | Q36: =IF(AND(N36>0,N36<$B$7),LN(N36/($B$7-N36)),"") -> -0.53062825 | S36: 2021 | T36: 0.053 | U36: =$B$8/(1+EXP(-$D$8*(S36-$F$8))) -> 0.057497343 | V36: =T36-U36 -> -0.004497343 | W36: =IF(AND(T36>0,T36<$B$8),LN(T36/($B$8-T36)),"") -> -2.8830072
A37: 2017 | B37: 0.232 | C37: =$B$5/(1+EXP(-$D$5*(A37-$F$5))) -> 0.2287174 | D37: =B37-C37 -> 0.0032825985 | E37: =IF(AND(B37>0,B37<$B$5),LN(B37/($B$5-B37)),"") -> -0.058594164 | M37: 2012 | N37: 0.089 | O37: =$B$7/(1+EXP(-$D$7*(M37-$F$7))) -> 0.11975228 | P37: =N37-O37 -> -0.03075228 | Q37: =IF(AND(N37>0,N37<$B$7),LN(N37/($B$7-N37)),"") -> -0.35555072 | S37: 2022 | T37: 0.06 | U37: =$B$8/(1+EXP(-$D$8*(S37-$F$8))) -> 0.068319164 | V37: =T37-U37 -> -0.0083191635 | W37: =IF(AND(T37>0,T37<$B$8),LN(T37/($B$8-T37)),"") -> -2.7515353
A38: 2018 | B38: 0.296 | C38: =$B$5/(1+EXP(-$D$5*(A38-$F$5))) -> 0.26292713 | D38: =B38-C38 -> 0.033072872 | E38: =IF(AND(B38>0,B38<$B$5),LN(B38/($B$5-B38)),"") -> 0.48635277 | M38: 2013 | N38: 0.114 | O38: =$B$7/(1+EXP(-$D$7*(M38-$F$7))) -> 0.14218174 | P38: =N38-O38 -> -0.028181741 | Q38: =IF(AND(N38>0,N38<$B$7),LN(N38/($B$7-N38)),"") -> 0.11122564 | S38: 2023 | T38: 0.072 | U38: =$B$8/(1+EXP(-$D$8*(S38-$F$8))) -> 0.081002752 | V38: =T38-U38 -> -0.0090027519 | W38: =IF(AND(T38>0,T38<$B$8),LN(T38/($B$8-T38)),"") -> -2.5563656
A39: 2019 | B39: 0.298 | C39: =$B$5/(1+EXP(-$D$5*(A39-$F$5))) -> 0.29617435 | D39: =B39-C39 -> 0.0018256545 | E39: =IF(AND(B39>0,B39<$B$5),LN(B39/($B$5-B39)),"") -> 0.50413664 | M39: 2014 | N39: 0.163 | O39: =$B$7/(1+EXP(-$D$7*(M39-$F$7))) -> 0.16175207 | P39: =N39-O39 -> 0.0012479258 | Q39: =IF(AND(N39>0,N39<$B$7),LN(N39/($B$7-N39)),"") -> 1.1234583 | S39: 2024 | T39: 0.095 | U39: =$B$8/(1+EXP(-$D$8*(S39-$F$8))) -> 0.095798951 | V39: =T39-U39 -> -0.000798951 | W39: =IF(AND(T39>0,T39<$B$8),LN(T39/($B$8-T39)),"") -> -2.2540581
A40: 2020 | B40: 0.342 | C40: =$B$5/(1+EXP(-$D$5*(A40-$F$5))) -> 0.3272292 | D40: =B40-C40 -> 0.014770804 | E40: =IF(AND(B40>0,B40<$B$5),LN(B40/($B$5-B40)),"") -> 0.92215585 | M40: 2015 | N40: 0.213 | O40: =$B$7/(1+EXP(-$D$7*(M40-$F$7))) -> 0.17753756 | P40: =N40-O40 -> 0.03546244 | Q40: =IF(AND(N40>0,N40<$B$7),LN(N40/($B$7-N40)),"") -> 4.2626799 | S40: 2025 | T40: 0.14 | U40: =$B$8/(1+EXP(-$D$8*(S40-$F$8))) -> 0.11296564 | V40: =T40-U40 -> 0.027034358 | W40: =IF(AND(T40>0,T40<$B$8),LN(T40/($B$8-T40)),"") -> -1.81529
A41: 2021 | B41: 0.318 | C41: =$B$5/(1+EXP(-$D$5*(A41-$F$5))) -> 0.35517956 | D41: =B41-C41 -> -0.037179559 | E41: =IF(AND(B41>0,B41<$B$5),LN(B41/($B$5-B41)),"") -> 0.68687757 | M41: 2016 | N41: 0.21 | O41: =$B$7/(1+EXP(-$D$7*(M41-$F$7))) -> 0.18948269 | P41: =N41-O41 -> 0.020517309 | Q41: =IF(AND(N41>0,N41<$B$7),LN(N41/($B$7-N41)),"") -> 3.5553481
A42: 2022 | B42: 0.358 | C42: =$B$5/(1+EXP(-$D$5*(A42-$F$5))) -> 0.37950797 | D42: =B42-C42 -> -0.021507973 | E42: =IF(AND(B42>0,B42<$B$5),LN(B42/($B$5-B42)),"") -> 1.0930412 | M42: 2017 | N42: 0.212 | O42: =$B$7/(1+EXP(-$D$7*(M42-$F$7))) -> 0.19809226 | P42: =N42-O42 -> 0.013907738 | Q42: =IF(AND(N42>0,N42<$B$7),LN(N42/($B$7-N42)),"") -> 3.9702919
A43: 2023 | B43: 0.373 | C43: =$B$5/(1+EXP(-$D$5*(A43-$F$5))) -> 0.40007466 | D43: =B43-C43 -> -0.027074661 | E43: =IF(AND(B43>0,B43<$B$5),LN(B43/($B$5-B43)),"") -> 1.2676181 | M43: 2018 | N43: 0.201 | O43: =$B$7/(1+EXP(-$D$7*(M43-$F$7))) -> 0.20408232 | P43: =N43-O43 -> -0.0030823152 | Q43: =IF(AND(N43>0,N43<$B$7),LN(N43/($B$7-N43)),"") -> 2.5952547
A44: 2024 | B44: 0.444 | C44: =$B$5/(1+EXP(-$D$5*(A44-$F$5))) -> 0.41703658 | D44: =B44-C44 -> 0.026963416 | E44: =IF(AND(B44>0,B44<$B$5),LN(B44/($B$5-B44)),"") -> 2.569464 | M44: 2019 | N44: 0.217 | O44: =$B$7/(1+EXP(-$D$7*(M44-$F$7))) -> 0.20814814 | P44: =N44-O44 -> 0.0088518569 | Q44: =IF(AND(N44>0,N44<$B$7),LN(N44/($B$7-N44)),"")
A45: 2025 | B45: 0.448 | C45: =$B$5/(1+EXP(-$D$5*(A45-$F$5))) -> 0.43074254 | D45: =B45-C45 -> 0.017257461 | E45: =IF(AND(B45>0,B45<$B$5),LN(B45/($B$5-B45)),"") -> 2.7035959 | M45: 2020 | N45: 0.245 | O45: =$B$7/(1+EXP(-$D$7*(M45-$F$7))) -> 0.2108618 | P45: =N45-O45 -> 0.034138201 | Q45: =IF(AND(N45>0,N45<$B$7),LN(N45/($B$7-N45)),"")
M46: 2021 | N46: 0.212 | O46: =$B$7/(1+EXP(-$D$7*(M46-$F$7))) -> 0.21265268 | P46: =N46-O46 -> -0.00065267934 | Q46: =IF(AND(N46>0,N46<$B$7),LN(N46/($B$7-N46)),"") -> 3.9702919
M47: 2022 | N47: 0.201 | O47: =$B$7/(1+EXP(-$D$7*(M47-$F$7))) -> 0.2138258 | P47: =N47-O47 -> -0.012825798 | Q47: =IF(AND(N47>0,N47<$B$7),LN(N47/($B$7-N47)),"") -> 2.5952547
M48: 2023 | N48: 0.189 | O48: =$B$7/(1+EXP(-$D$7*(M48-$F$7))) -> 0.2145905 | P48: =N48-O48 -> -0.025590505 | Q48: =IF(AND(N48>0,N48<$B$7),LN(N48/($B$7-N48)),"") -> 1.9459101
M49: 2024 | N49: 0.208 | O49: =$B$7/(1+EXP(-$D$7*(M49-$F$7))) -> 0.2150874 | P49: =N49-O49 -> -0.0070873981 | Q49: =IF(AND(N49>0,N49<$B$7),LN(N49/($B$7-N49)),"") -> 3.2580965
M50: 2025 | N50: 0.192 | O50: =$B$7/(1+EXP(-$D$7*(M50-$F$7))) -> 0.2154096 | P50: =N50-O50 -> -0.023409602 | Q50: =IF(AND(N50>0,N50<$B$7),LN(N50/($B$7-N50)),"") -> 2.0794415

Sheet EV Productivity
A1: Chart: 'EVs ride the same productivity clock' (fig44). Tesla fleet MPGe normalized to constant 2024 weight
A2: Series: EPA Automotive Trends, manufacturer = Tesla, production-weighted, 2012 to 2024: the only EV series in the project with MPGe, weight, and HP on the same basis. It is also the BEV proxy used to back electrics out of the class series (Class Productivity sheet). Normalized MPGe = MPGe x (weight / weight_2024)^e_w.
A4: e_w used (BEV-only model, MPGe on weight, n = 153, R2 0.708; typed input) | E4: 0.975
A5: for comparison: BEV own weight elasticity from spec E (live) | E5: =ABS(Alternatives!C66) -> 1.0531042
A8: model year | B8: Tesla fleet MPGe (raw) | C8: weight (lbs) | D8: horsepower | E8: weight factor | F8: MPGe normalized to 2024 weight | G8: ln(normalized) | I8: Trend fit: ln(normalized MPGe) on year
A9: 2012 | B9: 89.14065 | C9: 4500 | D9: 349 | E9: =(C9/$C$21)^$E$4 -> 1.0199547 | F9: =B9*E9 -> 90.919425 | G9: =LN(F9) -> 4.5099737 | I9: slope (log units per year) | J9: =INDEX(LINEST(G9:G21,A9:A21,TRUE,TRUE),1,1) -> 0.023326899
A10: 2013 | B10: 90.655 | C10: 4500 | D10: 346.984 | E10: =(C10/$C$21)^$E$4 -> 1.0199547 | F10: =B10*E10 -> 92.463994 | G10: =LN(F10) -> 4.5268193 | I10: intercept | J10: =INDEX(LINEST(G9:G21,A9:A21,TRUE,TRUE),1,2) -> -42.36905
A11: 2014 | B11: 90.16863 | C11: 4562.222 | D11: 335.7883 | E11: =(C11/$C$21)^$E$4 -> 1.0337028 | F11: =B11*E11 -> 93.207565 | G11: =LN(F11) -> 4.5348289 | I11: R-squared | J11: =INDEX(LINEST(G9:G21,A9:A21,TRUE,TRUE),3,1) -> 0.71632056
A12: 2015 | B12: 97.13512 | C12: 4901.756 | D12: 396.1661 | E12: =(C12/$C$21)^$E$4 -> 1.1086426 | F12: =B12*E12 -> 107.68814 | G12: =LN(F12) -> 4.6792394 | I12: growth per year, exp(slope) - 1 | J12: =EXP(J9)-1 -> 0.023601099
A13: 2016 | B13: 96.81841 | C13: 5172.598 | D13: 384.3064 | E13: =(C13/$C$21)^$E$4 -> 1.1683278 | F13: =B13*E13 -> 113.11564 | G13: =LN(F13) -> 4.7284106 | I13: n (annual points) | J13: =COUNT(A9:A21) -> 13
A14: 2017 | B14: 98.21854 | C14: 5211.807 | D14: 499.9051 | E14: =(C14/$C$21)^$E$4 -> 1.1769616 | F14: =B14*E14 -> 115.59945 | G14: =LN(F14) -> 4.7501312 | I14: projected 2045 (MPGe-equivalent, illustrative) | J14: =EXP(J10+J9*2045) -> 207.36049
A15: 2018 | B15: 113.67319 | C15: 4522.574 | D15: 402.7222 | E15: =(C15/$C$21)^$E$4 -> 1.024943 | F15: =B15*E15 -> 116.50854 | G15: =LN(F15) -> 4.7579646
A16: 2019 | B16: 117.9998 | C16: 4436.414 | D16: 392.0165 | E16: =(C16/$C$21)^$E$4 -> 1.0059003 | F16: =B16*E16 -> 118.69604 | G16: =LN(F16) -> 4.7765659
A17: 2020 | B17: 119.08936 | C17: 4393.679 | D17: 443.699 | E17: =(C17/$C$21)^$E$4 -> 0.99645181 | F17: =B17*E17 -> 118.66681 | G17: =LN(F17) -> 4.7763196
A18: 2021 | B18: 123.91925 | C18: 4317.204 | D18: 375.8981 | E18: =(C18/$C$21)^$E$4 -> 0.97953778 | F18: =B18*E18 -> 121.38359 | G18: =LN(F18) -> 4.7989557
A19: 2022 | B19: 119.25117 | C19: 4364.185 | D19: 451.8285 | E19: =(C19/$C$21)^$E$4 -> 0.98992948 | F19: =B19*E19 -> 118.05025 | G19: =LN(F19) -> 4.7711104
A20: 2023 | B20: 120.57422 | C20: 4383.789 | D20: 406.8769 | E20: =(C20/$C$21)^$E$4 -> 0.99426485 | F20: =B20*E20 -> 119.88271 | G20: =LN(F20) -> 4.7865138
A21: 2024 | B21: 117.14232 | C21: 4409.726 | D21: 420.4574 | E21: =(C21/$C$21)^$E$4 -> 1 | F21: =B21*E21 -> 117.14232 | G21: =LN(F21) -> 4.7633896

Sheet Class Productivity
A1: Charts: 'Normalized by class, the productivity law is universal' (fig43), 'Combustion alone kept the clock' (fig45), 'Without BEVs the classes converge harder' (fig46)
A2: Raw series: EPA Automotive Trends, production-weighted, by vehicle type, 1975 to 2024 (typed inputs: MPG, weight, HP, in-class BEV share). Everything else is live. BEVs-in normalization (fig43): MPG x (wt/wt_2024)^e_w x (HP/HP_2024)^e_h with the final CER's pooled elasticities, each class at its own 2024 design. Ex-BEV (fig45, fig46): the BEV share s is backed out first, harmonically for MPG and arithmetically for weight and HP, using the Tesla series as the BEV proxy: MPG_ice = (1 - s) / (1/MPG - s/MPGe_bev); wt_ice = (wt - s x wt_bev) / (1 - s); same for HP; then normalized with the combustion-only CER's elasticities (Alternatives spec A). Trend = LINEST of ln(normalized) on year; growth = exp(slope) - 1; 2045 = exp(intercept + slope x 2045).
A4: pooled e_w (final CER) | B4: =ABS(CER!C8) -> 0.45270912 | D4: combustion e_w (spec A) | E4: =ABS(Alternatives!F7) -> 0.30375764
A5: pooled e_h (final CER) | B5: =ABS(CER!C9) -> 0.36894371 | D5: combustion e_h (spec A) | E5: =ABS(Alternatives!F8) -> 0.48301416
A7: Scope | B7: BEVs in: growth per year | C7: BEVs in: R-squared | D7: BEVs in: 2045 at trend | E7: Ex-BEV: growth per year | F7: Ex-BEV: R-squared | G7: Ex-BEV: 2045 at trend | H7: Ex-BEV: 2024 normalized | I7: BEVs in: growth 2005 to 2024 | J7: Ex-BEV: growth 2005 to 2024 | K7: Ex-BEV: 2045 at 2005 to 2024 rate
A8: Fleet (all vehicles) | B8: =EXP(INDEX(LINEST(K20:K69,B20:B69,TRUE,TRUE),1,1))-1 -> 0.017897142 | C8: =INDEX(LINEST(K20:K69,B20:B69,TRUE,TRUE),3,1) -> 0.97954874 | D8: =EXP(INDEX(LINEST(K20:K69,B20:B69,TRUE,TRUE),1,2)+INDEX(LINEST(K20:K69,B20:B69,TRUE,TRUE),1,1)*2045) -> 38.130569 | E8: =EXP(INDEX(LINEST(P20:P69,B20:B69,TRUE,TRUE),1,1))-1 -> 0.018621508 | F8: =INDEX(LINEST(P20:P69,B20:B69,TRUE,TRUE),3,1) -> 0.9840344 | G8: =EXP(INDEX(LINEST(P20:P69,B20:B69,TRUE,TRUE),1,2)+INDEX(LINEST(P20:P69,B20:B69,TRUE,TRUE),1,1)*2045) -> 39.057285 | H8: =O69 -> 25.714162 | I8: =EXP(INDEX(LINEST(K50:K69,B50:B69,TRUE,TRUE),1,1))-1 -> 0.02189893 | J8: =EXP(INDEX(LINEST(P50:P69,B50:B69,TRUE,TRUE),1,1))-1 -> 0.018664063 | K8: =EXP(INDEX(LINEST(P50:P69,B50:B69,TRUE,TRUE),1,2)+INDEX(LINEST(P50:P69,B50:B69,TRUE,TRUE),1,1)*2045) -> 39.152457
A9: Sedan/Wagon | B9: =EXP(INDEX(LINEST(K70:K119,B70:B119,TRUE,TRUE),1,1))-1 -> 0.018643913 | C9: =INDEX(LINEST(K70:K119,B70:B119,TRUE,TRUE),3,1) -> 0.97782438 | D9: =EXP(INDEX(LINEST(K70:K119,B70:B119,TRUE,TRUE),1,2)+INDEX(LINEST(K70:K119,B70:B119,TRUE,TRUE),1,1)*2045) -> 48.96437 | E9: =EXP(INDEX(LINEST(P70:P119,B70:B119,TRUE,TRUE),1,1))-1 -> 0.018750132 | F9: =INDEX(LINEST(P70:P119,B70:B119,TRUE,TRUE),3,1) -> 0.98238691 | G9: =EXP(INDEX(LINEST(P70:P119,B70:B119,TRUE,TRUE),1,2)+INDEX(LINEST(P70:P119,B70:B119,TRUE,TRUE),1,1)*2045) -> 49.35122 | H9: =O119 -> 31.754245
A10: Car SUV | B10: =EXP(INDEX(LINEST(K120:K169,B120:B169,TRUE,TRUE),1,1))-1 -> 0.024110537 | C10: =INDEX(LINEST(K120:K169,B120:B169,TRUE,TRUE),3,1) -> 0.91822635 | D10: =EXP(INDEX(LINEST(K120:K169,B120:B169,TRUE,TRUE),1,2)+INDEX(LINEST(K120:K169,B120:B169,TRUE,TRUE),1,1)*2045) -> 50.200411 | E10: =EXP(INDEX(LINEST(P120:P169,B120:B169,TRUE,TRUE),1,1))-1 -> 0.022422856 | F10: =INDEX(LINEST(P120:P169,B120:B169,TRUE,TRUE),3,1) -> 0.94440925 | G10: =EXP(INDEX(LINEST(P120:P169,B120:B169,TRUE,TRUE),1,2)+INDEX(LINEST(P120:P169,B120:B169,TRUE,TRUE),1,1)*2045) -> 53.092259 | H10: =O169 -> 30.331207
A11: Truck SUV | B11: =EXP(INDEX(LINEST(K170:K219,B170:B219,TRUE,TRUE),1,1))-1 -> 0.020780184 | C11: =INDEX(LINEST(K170:K219,B170:B219,TRUE,TRUE),3,1) -> 0.98100688 | D11: =EXP(INDEX(LINEST(K170:K219,B170:B219,TRUE,TRUE),1,2)+INDEX(LINEST(K170:K219,B170:B219,TRUE,TRUE),1,1)*2045) -> 39.12867 | E11: =EXP(INDEX(LINEST(P170:P219,B170:B219,TRUE,TRUE),1,1))-1 -> 0.022235554 | F11: =INDEX(LINEST(P170:P219,B170:B219,TRUE,TRUE),3,1) -> 0.98388637 | G11: =EXP(INDEX(LINEST(P170:P219,B170:B219,TRUE,TRUE),1,2)+INDEX(LINEST(P170:P219,B170:B219,TRUE,TRUE),1,1)*2045) -> 40.957285 | H11: =O219 -> 24.873698
A12: Pickup | B12: =EXP(INDEX(LINEST(K220:K269,B220:B269,TRUE,TRUE),1,1))-1 -> 0.018354212 | C12: =INDEX(LINEST(K220:K269,B220:B269,TRUE,TRUE),3,1) -> 0.97310385 | D12: =EXP(INDEX(LINEST(K220:K269,B220:B269,TRUE,TRUE),1,2)+INDEX(LINEST(K220:K269,B220:B269,TRUE,TRUE),1,1)*2045) -> 30.340521 | E12: =EXP(INDEX(LINEST(P220:P269,B220:B269,TRUE,TRUE),1,1))-1 -> 0.019911905 | F12: =INDEX(LINEST(P220:P269,B220:B269,TRUE,TRUE),3,1) -> 0.97775769 | G12: =EXP(INDEX(LINEST(P220:P269,B220:B269,TRUE,TRUE),1,2)+INDEX(LINEST(P220:P269,B220:B269,TRUE,TRUE),1,1)*2045) -> 31.501331 | H12: =O269 -> 20.225972
A13: Minivan/Van | B13: =EXP(INDEX(LINEST(K270:K319,B270:B319,TRUE,TRUE),1,1))-1 -> 0.020637318 | C13: =INDEX(LINEST(K270:K319,B270:B319,TRUE,TRUE),3,1) -> 0.9806421 | D13: =EXP(INDEX(LINEST(K270:K319,B270:B319,TRUE,TRUE),1,2)+INDEX(LINEST(K270:K319,B270:B319,TRUE,TRUE),1,1)*2045) -> 39.412317 | E13: =EXP(INDEX(LINEST(P270:P319,B270:B319,TRUE,TRUE),1,1))-1 -> 0.022231614 | F13: =INDEX(LINEST(P270:P319,B270:B319,TRUE,TRUE),3,1) -> 0.98496931 | G13: =EXP(INDEX(LINEST(P270:P319,B270:B319,TRUE,TRUE),1,2)+INDEX(LINEST(P270:P319,B270:B319,TRUE,TRUE),1,1)*2045) -> 41.299927 | H13: =O319 -> 26.0971
A15: Reading: with BEVs in, Car SUV is the fastest class because the Model Y entered it (in-class BEV share 35.7% in 2023, column F); back the BEVs out and its rate falls into line with the others while every class still compounds near 2% a year. The fleet row with BEVs in reproduces the Normalization sheet.
A19: scope | B19: model year | C19: MPG (raw) | D19: weight (lbs) | E19: HP | F19: in-class BEV share s | G19: Tesla MPGe (proxy) | H19: Tesla weight | I19: Tesla HP | J19: normalized, BEVs in | K19: ln | L19: MPG ex-BEV | M19: weight ex-BEV | N19: HP ex-BEV | O19: normalized, ex-BEV | P19: ln
A20: Fleet (all vehicles) | B20: 1975 | C20: 13.0597 | D20: 4060.399 | E20: 137.3346 | F20: 0 | G20: =IFERROR(INDEX('EV Productivity'!$B$9:$B$21,MATCH(B20,'EV Productivity'!$A$9:$A$21,0)),"") | H20: =IFERROR(INDEX('EV Productivity'!$C$9:$C$21,MATCH(B20,'EV Productivity'!$A$9:$A$21,0)),"") | I20: =IFERROR(INDEX('EV Productivity'!$D$9:$D$21,MATCH(B20,'EV Productivity'!$A$9:$A$21,0)),"") | J20: =C20*(D20/$D$69)^$B$4*(E20/$E$69)^$B$5 -> 10.027208 | K20: =LN(J20) -> 2.3053022 | L20: =IF(AND(F20>0,ISNUMBER(G20)),(1-F20)/(1/C20-F20/G20),C20) -> 13.0597 | M20: =IF(AND(F20>0,ISNUMBER(G20)),(D20-F20*H20)/(1-F20),D20) -> 4060.399 | N20: =IF(AND(F20>0,ISNUMBER(G20)),(E20-F20*I20)/(1-F20),E20) -> 137.3346 | O20: =L20*(M20/$M$69)^$E$4*(N20/$N$69)^$E$5 -> 9.6625266 | P20: =LN(O20) -> 2.2682552
A21: Fleet (all vehicles) | B21: 1976 | C21: 14.22136 | D21: 4079.198 | E21: 135.0839 | F21: 0 | G21: =IFERROR(INDEX('EV Productivity'!$B$9:$B$21,MATCH(B21,'EV Productivity'!$A$9:$A$21,0)),"") | H21: =IFERROR(INDEX('EV Productivity'!$C$9:$C$21,MATCH(B21,'EV Productivity'!$A$9:$A$21,0)),"") | I21: =IFERROR(INDEX('EV Productivity'!$D$9:$D$21,MATCH(B21,'EV Productivity'!$A$9:$A$21,0)),"") | J21: =C21*(D21/$D$69)^$B$4*(E21/$E$69)^$B$5 -> 10.875481 | K21: =LN(J21) -> 2.3865108 | L21: =IF(AND(F21>0,ISNUMBER(G21)),(1-F21)/(1/C21-F21/G21),C21) -> 14.22136 | M21: =IF(AND(F21>0,ISNUMBER(G21)),(D21-F21*H21)/(1-F21),D21) -> 4079.198 | N21: =IF(AND(F21>0,ISNUMBER(G21)),(E21-F21*I21)/(1-F21),E21) -> 135.0839 | O21: =L21*(M21/$M$69)^$E$4*(N21/$N$69)^$E$5 -> 10.453018 | P21: =LN(O21) -> 2.3468908
A22: Fleet (all vehicles) | B22: 1977 | C22: 15.06743 | D22: 3981.818 | E22: 135.9847 | F22: 0 | G22: =IFERROR(INDEX('EV Productivity'!$B$9:$B$21,MATCH(B22,'EV Productivity'!$A$9:$A$21,0)),"") | H22: =IFERROR(INDEX('EV Productivity'!$C$9:$C$21,MATCH(B22,'EV Productivity'!$A$9:$A$21,0)),"") | I22: =IFERROR(INDEX('EV Productivity'!$D$9:$D$21,MATCH(B22,'EV Productivity'!$A$9:$A$21,0)),"") | J22: =C22*(D22/$D$69)^$B$4*(E22/$E$69)^$B$5 -> 11.425126 | K22: =LN(J22) -> 2.435815 | L22: =IF(AND(F22>0,ISNUMBER(G22)),(1-F22)/(1/C22-F22/G22),C22) -> 15.06743 | M22: =IF(AND(F22>0,ISNUMBER(G22)),(D22-F22*H22)/(1-F22),D22) -> 3981.818 | N22: =IF(AND(F22>0,ISNUMBER(G22)),(E22-F22*I22)/(1-F22),E22) -> 135.9847 | O22: =L22*(M22/$M$69)^$E$4*(N22/$N$69)^$E$5 -> 11.029263 | P22: =LN(O22) -> 2.4005521
A23: Fleet (all vehicles) | B23: 1978 | C23: 15.83777 | D23: 3715.238 | E23: 129.0248 | F23: 0 | G23: =IFERROR(INDEX('EV Productivity'!$B$9:$B$21,MATCH(B23,'EV Productivity'!$A$9:$A$21,0)),"") | H23: =IFERROR(INDEX('EV Productivity'!$C$9:$C$21,MATCH(B23,'EV Productivity'!$A$9:$A$21,0)),"") | I23: =IFERROR(INDEX('EV Productivity'!$D$9:$D$21,MATCH(B23,'EV Productivity'!$A$9:$A$21,0)),"") | J23: =C23*(D23/$D$69)^$B$4*(E23/$E$69)^$B$5 -> 11.414938 | K23: =LN(J23) -> 2.4349228 | L23: =IF(AND(F23>0,ISNUMBER(G23)),(1-F23)/(1/C23-F23/G23),C23) -> 15.83777 | M23: =IF(AND(F23>0,ISNUMBER(G23)),(D23-F23*H23)/(1-F23),D23) -> 3715.238 | N23: =IF(AND(F23>0,ISNUMBER(G23)),(E23-F23*I23)/(1-F23),E23) -> 129.0248 | O23: =L23*(M23/$M$69)^$E$4*(N23/$N$69)^$E$5 -> 11.067231 | P23: =LN(O23) -> 2.4039886
A24: Fleet (all vehicles) | B24: 1979 | C24: 15.91271 | D24: 3655.465 | E24: 123.5922 | F24: 0 | G24: =IFERROR(INDEX('EV Productivity'!$B$9:$B$21,MATCH(B24,'EV Productivity'!$A$9:$A$21,0)),"") | H24: =IFERROR(INDEX('EV Productivity'!$C$9:$C$21,MATCH(B24,'EV Productivity'!$A$9:$A$21,0)),"") | I24: =IFERROR(INDEX('EV Productivity'!$D$9:$D$21,MATCH(B24,'EV Productivity'!$A$9:$A$21,0)),"") | J24: =C24*(D24/$D$69)^$B$4*(E24/$E$69)^$B$5 -> 11.205781 | K24: =LN(J24) -> 2.4164298 | L24: =IF(AND(F24>0,ISNUMBER(G24)),(1-F24)/(1/C24-F24/G24),C24) -> 15.91271 | M24: =IF(AND(F24>0,ISNUMBER(G24)),(D24-F24*H24)/(1-F24),D24) -> 3655.465 | N24: =IF(AND(F24>0,ISNUMBER(G24)),(E24-F24*I24)/(1-F24),E24) -> 123.5922 | O24: =L24*(M24/$M$69)^$E$4*(N24/$N$69)^$E$5 -> 10.837415 | P24: =LN(O24) -> 2.3830045
A25: Fleet (all vehicles) | B25: 1980 | C25: 19.16493 | D25: 3227.876 | E25: 103.8276 | F25: 0 | G25: =IFERROR(INDEX('EV Productivity'!$B$9:$B$21,MATCH(B25,'EV Productivity'!$A$9:$A$21,0)),"") | H25: =IFERROR(INDEX('EV Productivity'!$C$9:$C$21,MATCH(B25,'EV Productivity'!$A$9:$A$21,0)),"") | I25: =IFERROR(INDEX('EV Productivity'!$D$9:$D$21,MATCH(B25,'EV Productivity'!$A$9:$A$21,0)),"") | J25: =C25*(D25/$D$69)^$B$4*(E25/$E$69)^$B$5 -> 11.962618 | K25: =LN(J25) -> 2.4817866 | L25: =IF(AND(F25>0,ISNUMBER(G25)),(1-F25)/(1/C25-F25/G25),C25) -> 19.16493 | M25: =IF(AND(F25>0,ISNUMBER(G25)),(D25-F25*H25)/(1-F25),D25) -> 3227.876 | N25: =IF(AND(F25>0,ISNUMBER(G25)),(E25-F25*I25)/(1-F25),E25) -> 103.8276 | O25: =L25*(M25/$M$69)^$E$4*(N25/$N$69)^$E$5 -> 11.553787 | P25: =LN(O25) -> 2.4470133
A26: Fleet (all vehicles) | B26: 1981 | C26: 20.52057 | D26: 3201.759 | E26: 102.1236 | F26: 0 | G26: =IFERROR(INDEX('EV Productivity'!$B$9:$B$21,MATCH(B26,'EV Productivity'!$A$9:$A$21,0)),"") | H26: =IFERROR(INDEX('EV Productivity'!$C$9:$C$21,MATCH(B26,'EV Productivity'!$A$9:$A$21,0)),"") | I26: =IFERROR(INDEX('EV Productivity'!$D$9:$D$21,MATCH(B26,'EV Productivity'!$A$9:$A$21,0)),"") | J26: =C26*(D26/$D$69)^$B$4*(E26/$E$69)^$B$5 -> 12.6841 | K26: =LN(J26) -> 2.5403493 | L26: =IF(AND(F26>0,ISNUMBER(G26)),(1-F26)/(1/C26-F26/G26),C26) -> 20.52057 | M26: =IF(AND(F26>0,ISNUMBER(G26)),(D26-F26*H26)/(1-F26),D26) -> 3201.759 | N26: =IF(AND(F26>0,ISNUMBER(G26)),(E26-F26*I26)/(1-F26),E26) -> 102.1236 | O26: =L26*(M26/$M$69)^$E$4*(N26/$N$69)^$E$5 -> 12.242315 | P26: =LN(O26) -> 2.5048984
A27: Fleet (all vehicles) | B27: 1982 | C27: 21.07205 | D27: 3201.843 | E27: 102.9528 | F27: 0 | G27: =IFERROR(INDEX('EV Productivity'!$B$9:$B$21,MATCH(B27,'EV Productivity'!$A$9:$A$21,0)),"") | H27: =IFERROR(INDEX('EV Productivity'!$C$9:$C$21,MATCH(B27,'EV Productivity'!$A$9:$A$21,0)),"") | I27: =IFERROR(INDEX('EV Productivity'!$D$9:$D$21,MATCH(B27,'EV Productivity'!$A$9:$A$21,0)),"") | J27: =C27*(D27/$D$69)^$B$4*(E27/$E$69)^$B$5 -> 13.064053 | K27: =LN(J27) -> 2.5698644 | L27: =IF(AND(F27>0,ISNUMBER(G27)),(1-F27)/(1/C27-F27/G27),C27) -> 21.07205 | M27: =IF(AND(F27>0,ISNUMBER(G27)),(D27-F27*H27)/(1-F27),D27) -> 3201.843 | N27: =IF(AND(F27>0,ISNUMBER(G27)),(E27-F27*I27)/(1-F27),E27) -> 102.9528 | O27: =L27*(M27/$M$69)^$E$4*(N27/$N$69)^$E$5 -> 12.620622 | P27: =LN(O27) -> 2.5353321
A28: Fleet (all vehicles) | B28: 1983 | C28: 20.95239 | D28: 3257.34 | E28: 106.9483 | F28: 0 | G28: =IFERROR(INDEX('EV Productivity'!$B$9:$B$21,MATCH(B28,'EV Productivity'!$A$9:$A$21,0)),"") | H28: =IFERROR(INDEX('EV Productivity'!$C$9:$C$21,MATCH(B28,'EV Productivity'!$A$9:$A$21,0)),"") | I28: =IFERROR(INDEX('EV Productivity'!$D$9:$D$21,MATCH(B28,'EV Productivity'!$A$9:$A$21,0)),"") | J28: =C28*(D28/$D$69)^$B$4*(E28/$E$69)^$B$5 -> 13.276514 | K28: =LN(J28) -> 2.5859966 | L28: =IF(AND(F28>0,ISNUMBER(G28)),(1-F28)/(1/C28-F28/G28),C28) -> 20.95239 | M28: =IF(AND(F28>0,ISNUMBER(G28)),(D28-F28*H28)/(1-F28),D28) -> 3257.34 | N28: =IF(AND(F28>0,ISNUMBER(G28)),(E28-F28*I28)/(1-F28),E28) -> 106.9483 | O28: =L28*(M28/$M$69)^$E$4*(N28/$N$69)^$E$5 -> 12.848768 | P28: =LN(O28) -> 2.5532479
A29: Fleet (all vehicles) | B29: 1984 | C29: 21.00023 | D29: 3261.576 | E29: 108.5963 | F29: 0 | G29: =IFERROR(INDEX('EV Productivity'!$B$9:$B$21,MATCH(B29,'EV Productivity'!$A$9:$A$21,0)),"") | H29: =IFERROR(INDEX('EV Productivity'!$C$9:$C$21,MATCH(B29,'EV Productivity'!$A$9:$A$21,0)),"") | I29: =IFERROR(INDEX('EV Productivity'!$D$9:$D$21,MATCH(B29,'EV Productivity'!$A$9:$A$21,0)),"") | J29: =C29*(D29/$D$69)^$B$4*(E29/$E$69)^$B$5 -> 13.389991 | K29: =LN(J29) -> 2.5945075 | L29: =IF(AND(F29>0,ISNUMBER(G29)),(1-F29)/(1/C29-F29/G29),C29) -> 21.00023 | M29: =IF(AND(F29>0,ISNUMBER(G29)),(D29-F29*H29)/(1-F29),D29) -> 3261.576 | N29: =IF(AND(F29>0,ISNUMBER(G29)),(E29-F29*I29)/(1-F29),E29) -> 108.5963 | O29: =L29*(M29/$M$69)^$E$4*(N29/$N$69)^$E$5 -> 12.9787 | P29: =LN(O29) -> 2.5633095
A30: Fleet (all vehicles) | B30: 1985 | C30: 21.31942 | D30: 3271.127 | E30: 114.1306 | F30: 0 | G30: =IFERROR(INDEX('EV Productivity'!$B$9:$B$21,MATCH(B30,'EV Productivity'!$A$9:$A$21,0)),"") | H30: =IFERROR(INDEX('EV Productivity'!$C$9:$C$21,MATCH(B30,'EV Productivity'!$A$9:$A$21,0)),"") | I30: =IFERROR(INDEX('EV Productivity'!$D$9:$D$21,MATCH(B30,'EV Productivity'!$A$9:$A$21,0)),"") | J30: =C30*(D30/$D$69)^$B$4*(E30/$E$69)^$B$5 -> 13.863437 | K30: =LN(J30) -> 2.629255 | L30: =IF(AND(F30>0,ISNUMBER(G30)),(1-F30)/(1/C30-F30/G30),C30) -> 21.31942 | M30: =IF(AND(F30>0,ISNUMBER(G30)),(D30-F30*H30)/(1-F30),D30) -> 3271.127 | N30: =IF(AND(F30>0,ISNUMBER(G30)),(E30-F30*I30)/(1-F30),E30) -> 114.1306 | O30: =L30*(M30/$M$69)^$E$4*(N30/$N$69)^$E$5 -> 13.508126 | P30: =LN(O30) -> 2.6032915
A31: Fleet (all vehicles) | B31: 1986 | C31: 21.84433 | D31: 3237.974 | E31: 114.3758 | F31: 0 | G31: =IFERROR(INDEX('EV Productivity'!$B$9:$B$21,MATCH(B31,'EV Productivity'!$A$9:$A$21,0)),"") | H31: =IFERROR(INDEX('EV Productivity'!$C$9:$C$21,MATCH(B31,'EV Productivity'!$A$9:$A$21,0)),"") | I31: =IFERROR(INDEX('EV Productivity'!$D$9:$D$21,MATCH(B31,'EV Productivity'!$A$9:$A$21,0)),"") | J31: =C31*(D31/$D$69)^$B$4*(E31/$E$69)^$B$5 -> 14.150615 | K31: =LN(J31) -> 2.6497581 | L31: =IF(AND(F31>0,ISNUMBER(G31)),(1-F31)/(1/C31-F31/G31),C31) -> 21.84433 | M31: =IF(AND(F31>0,ISNUMBER(G31)),(D31-F31*H31)/(1-F31),D31) -> 3237.974 | N31: =IF(AND(F31>0,ISNUMBER(G31)),(E31-F31*I31)/(1-F31),E31) -> 114.3758 | O31: =L31*(M31/$M$69)^$E$4*(N31/$N$69)^$E$5 -> 13.812262 | P31: =LN(O31) -> 2.6255568
... A69: Fleet (all vehicles) | B69: 2024 | C69: 27.24521 | D69: 4353.748 | E69: 258.0114 | F69: 0.072 | G69: =IFERROR(INDEX('EV Productivity'!$B$9:$B$21,MATCH(B69,'EV Productivity'!$A$9:$A$21,0)),"") -> 117.14232 | H69: =IFERROR(INDEX('EV Productivity'!$C$9:$C$21,MATCH(B69,'EV Productivity'!$A$9:$A$21,0)),"") -> 4409.726 | I69: =IFERROR(INDEX('EV Productivity'!$D$9:$D$21,MATCH(B69,'EV Productivity'!$A$9:$A$21,0)),"") -> 420.4574 | J69: =C69*(D69/$D$69)^$B$4*(E69/$E$69)^$B$5 -> 27.24521 | K69: =LN(J69) -> 3.3048777 | L69: =IF(AND(F69>0,ISNUMBER(G69)),(1-F69)/(1/C69-F69/G69),C69) -> 25.714162 | M69: =IF(AND(F69>0,ISNUMBER(G69)),(D69-F69*H69)/(1-F69),D69) -> 4349.4049 | N69: =IF(AND(F69>0,ISNUMBER(G69)),(E69-F69*I69)/(1-F69),E69) -> 245.40783 | O69: =L69*(M69/$M$69)^$E$4*(N69/$N$69)^$E$5 -> 25.714162 | P69: =LN(O69) -> 3.2470419
A70: Sedan/Wagon | B70: 1975 | C70: 13.45833 | D70: 4057.565 | E70: 136.2256 | F70: 0 | G70: =IFERROR(INDEX('EV Productivity'!$B$9:$B$21,MATCH(B70,'EV Productivity'!$A$9:$A$21,0)),"") | H70: =IFERROR(INDEX('EV Productivity'!$C$9:$C$21,MATCH(B70,'EV Productivity'!$A$9:$A$21,0)),"") | I70: =IFERROR(INDEX('EV Productivity'!$D$9:$D$21,MATCH(B70,'EV Productivity'!$A$9:$A$21,0)),"") | J70: =C70*(D70/$D$119)^$B$4*(E70/$E$119)^$B$5 -> 12.193641 | K70: =LN(J70) -> 2.5009146 | L70: =IF(AND(F70>0,ISNUMBER(G70)),(1-F70)/(1/C70-F70/G70),C70) -> 13.45833 | M70: =IF(AND(F70>0,ISNUMBER(G70)),(D70-F70*H70)/(1-F70),D70) -> 4057.565 | N70: =IF(AND(F70>0,ISNUMBER(G70)),(E70-F70*I70)/(1-F70),E70) -> 136.2256 | O70: =L70*(M70/$M$119)^$E$4*(N70/$N$119)^$E$5 -> 11.888044 | P70: =LN(O70) -> 2.4755332
A71: Sedan/Wagon | B71: 1976 | C71: 14.86845 | D71: 4058.944 | E71: 133.571 | F71: 0 | G71: =IFERROR(INDEX('EV Productivity'!$B$9:$B$21,MATCH(B71,'EV Productivity'!$A$9:$A$21,0)),"") | H71: =IFERROR(INDEX('EV Productivity'!$C$9:$C$21,MATCH(B71,'EV Productivity'!$A$9:$A$21,0)),"") | I71: =IFERROR(INDEX('EV Productivity'!$D$9:$D$21,MATCH(B71,'EV Productivity'!$A$9:$A$21,0)),"") | J71: =C71*(D71/$D$119)^$B$4*(E71/$E$119)^$B$5 -> 13.375855 | K71: =LN(J71) -> 2.5934512 | L71: =IF(AND(F71>0,ISNUMBER(G71)),(1-F71)/(1/C71-F71/G71),C71) -> 14.86845 | M71: =IF(AND(F71>0,ISNUMBER(G71)),(D71-F71*H71)/(1-F71),D71) -> 4058.944 | N71: =IF(AND(F71>0,ISNUMBER(G71)),(E71-F71*I71)/(1-F71),E71) -> 133.571 | O71: =L71*(M71/$M$119)^$E$4*(N71/$N$119)^$E$5 -> 13.010729 | P71: =LN(O71) -> 2.5657743
A72: Sedan/Wagon | B72: 1977 | C72: 15.59297 | D72: 3943.519 | E72: 133.1881 | F72: 0 | G72: =IFERROR(INDEX('EV Productivity'!$B$9:$B$21,MATCH(B72,'EV Productivity'!$A$9:$A$21,0)),"") | H72: =IFERROR(INDEX('EV Productivity'!$C$9:$C$21,MATCH(B72,'EV Productivity'!$A$9:$A$21,0)),"") | I72: =IFERROR(INDEX('EV Productivity'!$D$9:$D$21,MATCH(B72,'EV Productivity'!$A$9:$A$21,0)),"") | J72: =C72*(D72/$D$119)^$B$4*(E72/$E$119)^$B$5 -> 13.830971 | K72: =LN(J72) -> 2.6269103 | L72: =IF(AND(F72>0,ISNUMBER(G72)),(1-F72)/(1/C72-F72/G72),C72) -> 15.59297 | M72: =IF(AND(F72>0,ISNUMBER(G72)),(D72-F72*H72)/(1-F72),D72) -> 3943.519 | N72: =IF(AND(F72>0,ISNUMBER(G72)),(E72-F72*I72)/(1-F72),E72) -> 133.1881 | O72: =L72*(M72/$M$119)^$E$4*(N72/$N$119)^$E$5 -> 13.506934 | P72: =LN(O72) -> 2.6032032
A73: Sedan/Wagon | B73: 1978 | C73: 16.94899 | D73: 3587.514 | E73: 124.1623 | F73: 0 | G73: =IFERROR(INDEX('EV Productivity'!$B$9:$B$21,MATCH(B73,'EV Productivity'!$A$9:$A$21,0)),"") | H73: =IFERROR(INDEX('EV Productivity'!$C$9:$C$21,MATCH(B73,'EV Productivity'!$A$9:$A$21,0)),"") | I73: =IFERROR(INDEX('EV Productivity'!$D$9:$D$21,MATCH(B73,'EV Productivity'!$A$9:$A$21,0)),"") | J73: =C73*(D73/$D$119)^$B$4*(E73/$E$119)^$B$5 -> 14.035305 | K73: =LN(J73) -> 2.641576 | L73: =IF(AND(F73>0,ISNUMBER(G73)),(1-F73)/(1/C73-F73/G73),C73) -> 16.94899 | M73: =IF(AND(F73>0,ISNUMBER(G73)),(D73-F73*H73)/(1-F73),D73) -> 3587.514 | N73: =IF(AND(F73>0,ISNUMBER(G73)),(E73-F73*I73)/(1-F73),E73) -> 124.1623 | O73: =L73*(M73/$M$119)^$E$4*(N73/$N$119)^$E$5 -> 13.790184 | P73: =LN(O73) -> 2.623957
A74: Sedan/Wagon | B74: 1979 | C74: 17.24547 | D74: 3484.872 | E74: 119.4639 | F74: 0 | G74: =IFERROR(INDEX('EV Productivity'!$B$9:$B$21,MATCH(B74,'EV Productivity'!$A$9:$A$21,0)),"") | H74: =IFERROR(INDEX('EV Productivity'!$C$9:$C$21,MATCH(B74,'EV Productivity'!$A$9:$A$21,0)),"") | I74: =IFERROR(INDEX('EV Productivity'!$D$9:$D$21,MATCH(B74,'EV Productivity'!$A$9:$A$21,0)),"") | J74: =C74*(D74/$D$119)^$B$4*(E74/$E$119)^$B$5 -> 13.895205 | K74: =LN(J74) -> 2.6315438 | L74: =IF(AND(F74>0,ISNUMBER(G74)),(1-F74)/(1/C74-F74/G74),C74) -> 17.24547 | M74: =IF(AND(F74>0,ISNUMBER(G74)),(D74-F74*H74)/(1-F74),D74) -> 3484.872 | N74: =IF(AND(F74>0,ISNUMBER(G74)),(E74-F74*I74)/(1-F74),E74) -> 119.4639 | O74: =L74*(M74/$M$119)^$E$4*(N74/$N$119)^$E$5 -> 13.651485 | P74: =LN(O74) -> 2.6138483
A75: Sedan/Wagon | B75: 1980 | C75: 20.0121 | D75: 3101.464 | E75: 100.4585 | F75: 0 | G75: =IFERROR(INDEX('EV Productivity'!$B$9:$B$21,MATCH(B75,'EV Productivity'!$A$9:$A$21,0)),"") | H75: =IFERROR(INDEX('EV Productivity'!$C$9:$C$21,MATCH(B75,'EV Productivity'!$A$9:$A$21,0)),"") | I75: =IFERROR(INDEX('EV Productivity'!$D$9:$D$21,MATCH(B75,'EV Productivity'!$A$9:$A$21,0)),"") | J75: =C75*(D75/$D$119)^$B$4*(E75/$E$119)^$B$5 -> 14.348397 | K75: =LN(J75) -> 2.6636382 | L75: =IF(AND(F75>0,ISNUMBER(G75)),(1-F75)/(1/C75-F75/G75),C75) -> 20.0121 | M75: =IF(AND(F75>0,ISNUMBER(G75)),(D75-F75*H75)/(1-F75),D75) -> 3101.464 | N75: =IF(AND(F75>0,ISNUMBER(G75)),(E75-F75*I75)/(1-F75),E75) -> 100.4585 | O75: =L75*(M75/$M$119)^$E$4*(N75/$N$119)^$E$5 -> 14.062887 | P75: =LN(O75) -> 2.6435392
A76: Sedan/Wagon | B76: 1981 | C76: 21.41631 | D76: 3075.865 | E76: 98.7082 | F76: 0 | G76: =IFERROR(INDEX('EV Productivity'!$B$9:$B$21,MATCH(B76,'EV Productivity'!$A$9:$A$21,0)),"") | H76: =IFERROR(INDEX('EV Productivity'!$C$9:$C$21,MATCH(B76,'EV Productivity'!$A$9:$A$21,0)),"") | I76: =IFERROR(INDEX('EV Productivity'!$D$9:$D$21,MATCH(B76,'EV Productivity'!$A$9:$A$21,0)),"") | J76: =C76*(D76/$D$119)^$B$4*(E76/$E$119)^$B$5 -> 15.198808 | K76: =LN(J76) -> 2.721217 | L76: =IF(AND(F76>0,ISNUMBER(G76)),(1-F76)/(1/C76-F76/G76),C76) -> 21.41631 | M76: =IF(AND(F76>0,ISNUMBER(G76)),(D76-F76*H76)/(1-F76),D76) -> 3075.865 | N76: =IF(AND(F76>0,ISNUMBER(G76)),(E76-F76*I76)/(1-F76),E76) -> 98.7082 | O76: =L76*(M76/$M$119)^$E$4*(N76/$N$119)^$E$5 -> 14.884904 | P76: =LN(O76) -> 2.7003475
A77: Sedan/Wagon | B77: 1982 | C77: 22.21184 | D77: 3054.073 | E77: 98.7342 | F77: 0 | G77: =IFERROR(INDEX('EV Productivity'!$B$9:$B$21,MATCH(B77,'EV Productivity'!$A$9:$A$21,0)),"") | H77: =IFERROR(INDEX('EV Productivity'!$C$9:$C$21,MATCH(B77,'EV Productivity'!$A$9:$A$21,0)),"") | I77: =IFERROR(INDEX('EV Productivity'!$D$9:$D$21,MATCH(B77,'EV Productivity'!$A$9:$A$21,0)),"") | J77: =C77*(D77/$D$119)^$B$4*(E77/$E$119)^$B$5 -> 15.714252 | K77: =LN(J77) -> 2.7545681 | L77: =IF(AND(F77>0,ISNUMBER(G77)),(1-F77)/(1/C77-F77/G77),C77) -> 22.21184 | M77: =IF(AND(F77>0,ISNUMBER(G77)),(D77-F77*H77)/(1-F77),D77) -> 3054.073 | N77: =IF(AND(F77>0,ISNUMBER(G77)),(E77-F77*I77)/(1-F77),E77) -> 98.7342 | O77: =L77*(M77/$M$119)^$E$4*(N77/$N$119)^$E$5 -> 15.406472 | P77: =LN(O77) -> 2.7347877
A78: Sedan/Wagon | B78: 1983 | C78: 22.09123 | D78: 3111.96 | E78: 103.8318 | F78: 0 | G78: =IFERROR(INDEX('EV Productivity'!$B$9:$B$21,MATCH(B78,'EV Productivity'!$A$9:$A$21,0)),"") | H78: =IFERROR(INDEX('EV Productivity'!$C$9:$C$21,MATCH(B78,'EV Productivity'!$A$9:$A$21,0)),"") | I78: =IFERROR(INDEX('EV Productivity'!$D$9:$D$21,MATCH(B78,'EV Productivity'!$A$9:$A$21,0)),"") | J78: =C78*(D78/$D$119)^$B$4*(E78/$E$119)^$B$5 -> 16.057831 | K78: =LN(J78) -> 2.7761966 | L78: =IF(AND(F78>0,ISNUMBER(G78)),(1-F78)/(1/C78-F78/G78),C78) -> 22.09123 | M78: =IF(AND(F78>0,ISNUMBER(G78)),(D78-F78*H78)/(1-F78),D78) -> 3111.96 | N78: =IF(AND(F78>0,ISNUMBER(G78)),(E78-F78*I78)/(1-F78),E78) -> 103.8318 | O78: =L78*(M78/$M$119)^$E$4*(N78/$N$119)^$E$5 -> 15.789763 | P78: =LN(O78) -> 2.7593618
A79: Sedan/Wagon | B79: 1984 | C79: 22.4419 | D79: 3098.504 | E79: 105.76 | F79: 0 | G79: =IFERROR(INDEX('EV Productivity'!$B$9:$B$21,MATCH(B79,'EV Productivity'!$A$9:$A$21,0)),"") | H79: =IFERROR(INDEX('EV Productivity'!$C$9:$C$21,MATCH(B79,'EV Productivity'!$A$9:$A$21,0)),"") | I79: =IFERROR(INDEX('EV Productivity'!$D$9:$D$21,MATCH(B79,'EV Productivity'!$A$9:$A$21,0)),"") | J79: =C79*(D79/$D$119)^$B$4*(E79/$E$119)^$B$5 -> 16.391658 | K79: =LN(J79) -> 2.7967725 | L79: =IF(AND(F79>0,ISNUMBER(G79)),(1-F79)/(1/C79-F79/G79),C79) -> 22.4419 | M79: =IF(AND(F79>0,ISNUMBER(G79)),(D79-F79*H79)/(1-F79),D79) -> 3098.504 | N79: =IF(AND(F79>0,ISNUMBER(G79)),(E79-F79*I79)/(1-F79),E79) -> 105.76 | O79: =L79*(M79/$M$119)^$E$4*(N79/$N$119)^$E$5 -> 16.162312 | P79: =LN(O79) -> 2.7826821
A80: Sedan/Wagon | B80: 1985 | C80: 23.01593 | D80: 3092.936 | E80: 110.752 | F80: 0 | G80: =IFERROR(INDEX('EV Productivity'!$B$9:$B$21,MATCH(B80,'EV Productivity'!$A$9:$A$21,0)),"") | H80: =IFERROR(INDEX('EV Productivity'!$C$9:$C$21,MATCH(B80,'EV Productivity'!$A$9:$A$21,0)),"") | I80: =IFERROR(INDEX('EV Productivity'!$D$9:$D$21,MATCH(B80,'EV Productivity'!$A$9:$A$21,0)),"") | J80: =C80*(D80/$D$119)^$B$4*(E80/$E$119)^$B$5 -> 17.085518 | K80: =LN(J80) -> 2.8382312 | L80: =IF(AND(F80>0,ISNUMBER(G80)),(1-F80)/(1/C80-F80/G80),C80) -> 23.01593 | M80: =IF(AND(F80>0,ISNUMBER(G80)),(D80-F80*H80)/(1-F80),D80) -> 3092.936 | N80: =IF(AND(F80>0,ISNUMBER(G80)),(E80-F80*I80)/(1-F80),E80) -> 110.752 | O80: =L80*(M80/$M$119)^$E$4*(N80/$N$119)^$E$5 -> 16.939865 | P80: =LN(O80) -> 2.8296697
A81: Sedan/Wagon | B81: 1986 | C81: 23.72402 | D81: 3040.673 | E81: 110.8588 | F81: 0 | G81: =IFERROR(INDEX('EV Productivity'!$B$9:$B$21,MATCH(B81,'EV Productivity'!$A$9:$A$21,0)),"") | H81: =IFERROR(INDEX('EV Productivity'!$C$9:$C$21,MATCH(B81,'EV Productivity'!$A$9:$A$21,0)),"") | I81: =IFERROR(INDEX('EV Productivity'!$D$9:$D$21,MATCH(B81,'EV Productivity'!$A$9:$A$21,0)),"") | J81: =C81*(D81/$D$119)^$B$4*(E81/$E$119)^$B$5 -> 17.482025 | K81: =LN(J81) -> 2.8611732 | L81: =IF(AND(F81>0,ISNUMBER(G81)),(1-F81)/(1/C81-F81/G81),C81) -> 23.72402 | M81: =IF(AND(F81>0,ISNUMBER(G81)),(D81-F81*H81)/(1-F81),D81) -> 3040.673 | N81: =IF(AND(F81>0,ISNUMBER(G81)),(E81-F81*I81)/(1-F81),E81) -> 110.8588 | O81: =L81*(M81/$M$119)^$E$4*(N81/$N$119)^$E$5 -> 17.378957 | P81: =LN(O81) -> 2.8552601
... A119: Sedan/Wagon | B119: 2024 | C119: 33.48734 | D119: 3544.729 | E119: 210.1009 | F119: 0.071 | G119: =IFERROR(INDEX('EV Productivity'!$B$9:$B$21,MATCH(B119,'EV Productivity'!$A$9:$A$21,0)),"") -> 117.14232 | H119: =IFERROR(INDEX('EV Productivity'!$C$9:$C$21,MATCH(B119,'EV Productivity'!$A$9:$A$21,0)),"") -> 4409.726 | I119: =IFERROR(INDEX('EV Productivity'!$D$9:$D$21,MATCH(B119,'EV Productivity'!$A$9:$A$21,0)),"") -> 420.4574 | J119: =C119*(D119/$D$119)^$B$4*(E119/$E$119)^$B$5 -> 33.48734 | K119: =LN(J119) -> 3.5111675 | L119: =IF(AND(F119>0,ISNUMBER(G119)),(1-F119)/(1/C119-F119/G119),C119) -> 31.754245 | M119: =IF(AND(F119>0,ISNUMBER(G119)),(D119-F119*H119)/(1-F119),D119) -> 3478.6205 | N119: =IF(AND(F119>0,ISNUMBER(G119)),(E119-F119*I119)/(1-F119),E119) -> 194.02414 | O119: =L119*(M119/$M$119)^$E$4*(N119/$N$119)^$E$5 -> 31.754245 | P119: =LN(O119) -> 3.4580264
A120: Car SUV | B120: 1975 | C120: 11.12929 | D120: 4000 | E120: 112.7733 | F120: 0 | G120: =IFERROR(INDEX('EV Productivity'!$B$9:$B$21,MATCH(B120,'EV Productivity'!$A$9:$A$21,0)),"") | H120: =IFERROR(INDEX('EV Productivity'!$C$9:$C$21,MATCH(B120,'EV Productivity'!$A$9:$A$21,0)),"") | I120: =IFERROR(INDEX('EV Productivity'!$D$9:$D$21,MATCH(B120,'EV Productivity'!$A$9:$A$21,0)),"") | J120: =C120*(D120/$D$169)^$B$4*(E120/$E$169)^$B$5 -> 8.362482 | K120: =LN(J120) -> 2.1237553 | L120: =IF(AND(F120>0,ISNUMBER(G120)),(1-F120)/(1/C120-F120/G120),C120) -> 11.12929 | M120: =IF(AND(F120>0,ISNUMBER(G120)),(D120-F120*H120)/(1-F120),D120) -> 4000 | N120: =IF(AND(F120>0,ISNUMBER(G120)),(E120-F120*I120)/(1-F120),E120) -> 112.7733 | O120: =L120*(M120/$M$169)^$E$4*(N120/$N$169)^$E$5 -> 9.304488 | P120: =LN(O120) -> 2.2304969
A121: Car SUV | B121: 1976 | C121: 10.58091 | D121: 3986.237 | E121: 123.1064 | F121: 0 | G121: =IFERROR(INDEX('EV Productivity'!$B$9:$B$21,MATCH(B121,'EV Productivity'!$A$9:$A$21,0)),"") | H121: =IFERROR(INDEX('EV Productivity'!$C$9:$C$21,MATCH(B121,'EV Productivity'!$A$9:$A$21,0)),"") | I121: =IFERROR(INDEX('EV Productivity'!$D$9:$D$21,MATCH(B121,'EV Productivity'!$A$9:$A$21,0)),"") | J121: =C121*(D121/$D$169)^$B$4*(E121/$E$169)^$B$5 -> 8.1989907 | K121: =LN(J121) -> 2.1040111 | L121: =IF(AND(F121>0,ISNUMBER(G121)),(1-F121)/(1/C121-F121/G121),C121) -> 10.58091 | M121: =IF(AND(F121>0,ISNUMBER(G121)),(D121-F121*H121)/(1-F121),D121) -> 3986.237 | N121: =IF(AND(F121>0,ISNUMBER(G121)),(E121-F121*I121)/(1-F121),E121) -> 123.1064 | O121: =L121*(M121/$M$169)^$E$4*(N121/$N$169)^$E$5 -> 9.2189996 | P121: =LN(O121) -> 2.2212665
A122: Car SUV | B122: 1977 | C122: 12.16264 | D122: 4000 | E122: 124.4603 | F122: 0 | G122: =IFERROR(INDEX('EV Productivity'!$B$9:$B$21,MATCH(B122,'EV Productivity'!$A$9:$A$21,0)),"") | H122: =IFERROR(INDEX('EV Productivity'!$C$9:$C$21,MATCH(B122,'EV Productivity'!$A$9:$A$21,0)),"") | I122: =IFERROR(INDEX('EV Productivity'!$D$9:$D$21,MATCH(B122,'EV Productivity'!$A$9:$A$21,0)),"") | J122: =C122*(D122/$D$169)^$B$4*(E122/$E$169)^$B$5 -> 9.4775359 | K122: =LN(J122) -> 2.2489244 | L122: =IF(AND(F122>0,ISNUMBER(G122)),(1-F122)/(1/C122-F122/G122),C122) -> 12.16264 | M122: =IF(AND(F122>0,ISNUMBER(G122)),(D122-F122*H122)/(1-F122),D122) -> 4000 | N122: =IF(AND(F122>0,ISNUMBER(G122)),(E122-F122*I122)/(1-F122),E122) -> 124.4603 | O122: =L122*(M122/$M$169)^$E$4*(N122/$N$169)^$E$5 -> 10.664432 | P122: =LN(O122) -> 2.3669141
A123: Car SUV | B123: 1978 | C123: 11.57282 | D123: 4000 | E123: 126.0851 | F123: 0 | G123: =IFERROR(INDEX('EV Productivity'!$B$9:$B$21,MATCH(B123,'EV Productivity'!$A$9:$A$21,0)),"") | H123: =IFERROR(INDEX('EV Productivity'!$C$9:$C$21,MATCH(B123,'EV Productivity'!$A$9:$A$21,0)),"") | I123: =IFERROR(INDEX('EV Productivity'!$D$9:$D$21,MATCH(B123,'EV Productivity'!$A$9:$A$21,0)),"") | J123: =C123*(D123/$D$169)^$B$4*(E123/$E$169)^$B$5 -> 9.0611854 | K123: =LN(J123) -> 2.2039999 | L123: =IF(AND(F123>0,ISNUMBER(G123)),(1-F123)/(1/C123-F123/G123),C123) -> 11.57282 | M123: =IF(AND(F123>0,ISNUMBER(G123)),(D123-F123*H123)/(1-F123),D123) -> 4000 | N123: =IF(AND(F123>0,ISNUMBER(G123)),(E123-F123*I123)/(1-F123),E123) -> 126.0851 | O123: =L123*(M123/$M$169)^$E$4*(N123/$N$169)^$E$5 -> 10.211037 | P123: =LN(O123) -> 2.3234692
A124: Car SUV | B124: 1979 | C124: 14.26603 | D124: 3270.859 | E124: 98.7179 | F124: 0 | G124: =IFERROR(INDEX('EV Productivity'!$B$9:$B$21,MATCH(B124,'EV Productivity'!$A$9:$A$21,0)),"") | H124: =IFERROR(INDEX('EV Productivity'!$C$9:$C$21,MATCH(B124,'EV Productivity'!$A$9:$A$21,0)),"") | I124: =IFERROR(INDEX('EV Productivity'!$D$9:$D$21,MATCH(B124,'EV Productivity'!$A$9:$A$21,0)),"") | J124: =C124*(D124/$D$169)^$B$4*(E124/$E$169)^$B$5 -> 9.317001 | K124: =LN(J124) -> 2.2318408 | L124: =IF(AND(F124>0,ISNUMBER(G124)),(1-F124)/(1/C124-F124/G124),C124) -> 14.26603 | M124: =IF(AND(F124>0,ISNUMBER(G124)),(D124-F124*H124)/(1-F124),D124) -> 3270.859 | N124: =IF(AND(F124>0,ISNUMBER(G124)),(E124-F124*I124)/(1-F124),E124) -> 98.7179 | O124: =L124*(M124/$M$169)^$E$4*(N124/$N$169)^$E$5 -> 10.521001 | P124: =LN(O124) -> 2.3533733
A125: Car SUV | B125: 1980 | C125: 14.57638 | D125: 4000 | E125: 122.1928 | F125: 0 | G125: =IFERROR(INDEX('EV Productivity'!$B$9:$B$21,MATCH(B125,'EV Productivity'!$A$9:$A$21,0)),"") | H125: =IFERROR(INDEX('EV Productivity'!$C$9:$C$21,MATCH(B125,'EV Productivity'!$A$9:$A$21,0)),"") | I125: =IFERROR(INDEX('EV Productivity'!$D$9:$D$21,MATCH(B125,'EV Productivity'!$A$9:$A$21,0)),"") | J125: =C125*(D125/$D$169)^$B$4*(E125/$E$169)^$B$5 -> 11.281612 | K125: =LN(J125) -> 2.4231742 | L125: =IF(AND(F125>0,ISNUMBER(G125)),(1-F125)/(1/C125-F125/G125),C125) -> 14.57638 | M125: =IF(AND(F125>0,ISNUMBER(G125)),(D125-F125*H125)/(1-F125),D125) -> 4000 | N125: =IF(AND(F125>0,ISNUMBER(G125)),(E125-F125*I125)/(1-F125),E125) -> 122.1928 | O125: =L125*(M125/$M$169)^$E$4*(N125/$N$169)^$E$5 -> 12.667841 | P125: =LN(O125) -> 2.5390665
A126: Car SUV | B126: 1981 | C126: 14.68025 | D126: 4000 | E126: 140 | F126: 0 | G126: =IFERROR(INDEX('EV Productivity'!$B$9:$B$21,MATCH(B126,'EV Productivity'!$A$9:$A$21,0)),"") | H126: =IFERROR(INDEX('EV Productivity'!$C$9:$C$21,MATCH(B126,'EV Productivity'!$A$9:$A$21,0)),"") | I126: =IFERROR(INDEX('EV Productivity'!$D$9:$D$21,MATCH(B126,'EV Productivity'!$A$9:$A$21,0)),"") | J126: =C126*(D126/$D$169)^$B$4*(E126/$E$169)^$B$5 -> 11.946839 | K126: =LN(J126) -> 2.4804668 | L126: =IF(AND(F126>0,ISNUMBER(G126)),(1-F126)/(1/C126-F126/G126),C126) -> 14.68025 | M126: =IF(AND(F126>0,ISNUMBER(G126)),(D126-F126*H126)/(1-F126),D126) -> 4000 | N126: =IF(AND(F126>0,ISNUMBER(G126)),(E126-F126*I126)/(1-F126),E126) -> 140 | O126: =L126*(M126/$M$169)^$E$4*(N126/$N$169)^$E$5 -> 13.624608 | P126: =LN(O126) -> 2.6118775
A127: Car SUV | B127: 1982 | C127: 19.76697 | D127: 2629.999 | E127: 87.8139 | F127: 0 | G127: =IFERROR(INDEX('EV Productivity'!$B$9:$B$21,MATCH(B127,'EV Productivity'!$A$9:$A$21,0)),"") | H127: =IFERROR(INDEX('EV Productivity'!$C$9:$C$21,MATCH(B127,'EV Productivity'!$A$9:$A$21,0)),"") | I127: =IFERROR(INDEX('EV Productivity'!$D$9:$D$21,MATCH(B127,'EV Productivity'!$A$9:$A$21,0)),"") | J127: =C127*(D127/$D$169)^$B$4*(E127/$E$169)^$B$5 -> 11.201711 | K127: =LN(J127) -> 2.4160665 | L127: =IF(AND(F127>0,ISNUMBER(G127)),(1-F127)/(1/C127-F127/G127),C127) -> 19.76697 | M127: =IF(AND(F127>0,ISNUMBER(G127)),(D127-F127*H127)/(1-F127),D127) -> 2629.999 | N127: =IF(AND(F127>0,ISNUMBER(G127)),(E127-F127*I127)/(1-F127),E127) -> 87.8139 | O127: =L127*(M127/$M$169)^$E$4*(N127/$N$169)^$E$5 -> 12.893576 | P127: =LN(O127) -> 2.5567292
A128: Car SUV | B128: 1983 | C128: 20.6873 | D128: 3124.431 | E128: 100.7415 | F128: 0 | G128: =IFERROR(INDEX('EV Productivity'!$B$9:$B$21,MATCH(B128,'EV Productivity'!$A$9:$A$21,0)),"") | H128: =IFERROR(INDEX('EV Productivity'!$C$9:$C$21,MATCH(B128,'EV Productivity'!$A$9:$A$21,0)),"") | I128: =IFERROR(INDEX('EV Productivity'!$D$9:$D$21,MATCH(B128,'EV Productivity'!$A$9:$A$21,0)),"") | J128: =C128*(D128/$D$169)^$B$4*(E128/$E$169)^$B$5 -> 13.332861 | K128: =LN(J128) -> 2.5902318 | L128: =IF(AND(F128>0,ISNUMBER(G128)),(1-F128)/(1/C128-F128/G128),C128) -> 20.6873 | M128: =IF(AND(F128>0,ISNUMBER(G128)),(D128-F128*H128)/(1-F128),D128) -> 3124.431 | N128: =IF(AND(F128>0,ISNUMBER(G128)),(E128-F128*I128)/(1-F128),E128) -> 100.7415 | O128: =L128*(M128/$M$169)^$E$4*(N128/$N$169)^$E$5 -> 15.194006 | P128: =LN(O128) -> 2.720901
A129: Car SUV | B129: 1984 | C129: 19.28953 | D129: 3486.502 | E129: 108.7714 | F129: 0 | G129: =IFERROR(INDEX('EV Productivity'!$B$9:$B$21,MATCH(B129,'EV Productivity'!$A$9:$A$21,0)),"") | H129: =IFERROR(INDEX('EV Productivity'!$C$9:$C$21,MATCH(B129,'EV Productivity'!$A$9:$A$21,0)),"") | I129: =IFERROR(INDEX('EV Productivity'!$D$9:$D$21,MATCH(B129,'EV Productivity'!$A$9:$A$21,0)),"") | J129: =C129*(D129/$D$169)^$B$4*(E129/$E$169)^$B$5 -> 13.439617 | K129: =LN(J129) -> 2.5982068 | L129: =IF(AND(F129>0,ISNUMBER(G129)),(1-F129)/(1/C129-F129/G129),C129) -> 19.28953 | M129: =IF(AND(F129>0,ISNUMBER(G129)),(D129-F129*H129)/(1-F129),D129) -> 3486.502 | N129: =IF(AND(F129>0,ISNUMBER(G129)),(E129-F129*I129)/(1-F129),E129) -> 108.7714 | O129: =L129*(M129/$M$169)^$E$4*(N129/$N$169)^$E$5 -> 15.199951 | P129: =LN(O129) -> 2.7212922
A130: Car SUV | B130: 1985 | C130: 20.08032 | D130: 3469.242 | E130: 108.8355 | F130: 0 | G130: =IFERROR(INDEX('EV Productivity'!$B$9:$B$21,MATCH(B130,'EV Productivity'!$A$9:$A$21,0)),"") | H130: =IFERROR(INDEX('EV Productivity'!$C$9:$C$21,MATCH(B130,'EV Productivity'!$A$9:$A$21,0)),"") | I130: =IFERROR(INDEX('EV Productivity'!$D$9:$D$21,MATCH(B130,'EV Productivity'!$A$9:$A$21,0)),"") | J130: =C130*(D130/$D$169)^$B$4*(E130/$E$169)^$B$5 -> 13.962222 | K130: =LN(J130) -> 2.6363552 | L130: =IF(AND(F130>0,ISNUMBER(G130)),(1-F130)/(1/C130-F130/G130),C130) -> 20.08032 | M130: =IF(AND(F130>0,ISNUMBER(G130)),(D130-F130*H130)/(1-F130),D130) -> 3469.242 | N130: =IF(AND(F130>0,ISNUMBER(G130)),(E130-F130*I130)/(1-F130),E130) -> 108.8355 | O130: =L130*(M130/$M$169)^$E$4*(N130/$N$169)^$E$5 -> 15.803746 | P130: =LN(O130) -> 2.760247
A131: Car SUV | B131: 1986 | C131: 18.92466 | D131: 3479.487 | E131: 121.0844 | F131: 0 | G131: =IFERROR(INDEX('EV Productivity'!$B$9:$B$21,MATCH(B131,'EV Productivity'!$A$9:$A$21,0)),"") | H131: =IFERROR(INDEX('EV Productivity'!$C$9:$C$21,MATCH(B131,'EV Productivity'!$A$9:$A$21,0)),"") | I131: =IFERROR(INDEX('EV Productivity'!$D$9:$D$21,MATCH(B131,'EV Productivity'!$A$9:$A$21,0)),"") | J131: =C131*(D131/$D$169)^$B$4*(E131/$E$169)^$B$5 -> 13.705041 | K131: =LN(J131) -> 2.6177637 | L131: =IF(AND(F131>0,ISNUMBER(G131)),(1-F131)/(1/C131-F131/G131),C131) -> 18.92466 | M131: =IF(AND(F131>0,ISNUMBER(G131)),(D131-F131*H131)/(1-F131),D131) -> 3479.487 | N131: =IF(AND(F131>0,ISNUMBER(G131)),(E131-F131*I131)/(1-F131),E131) -> 121.0844 | O131: =L131*(M131/$M$169)^$E$4*(N131/$N$169)^$E$5 -> 15.695623 | P131: =LN(O131) -> 2.7533819
... A169: Car SUV | B169: 2024 | C169: 39.189 | D169: 3991.283 | E169: 245.3703 | F169: 0.305 | G169: =IFERROR(INDEX('EV Productivity'!$B$9:$B$21,MATCH(B169,'EV Productivity'!$A$9:$A$21,0)),"") -> 117.14232 | H169: =IFERROR(INDEX('EV Productivity'!$C$9:$C$21,MATCH(B169,'EV Productivity'!$A$9:$A$21,0)),"") -> 4409.726 | I169: =IFERROR(INDEX('EV Productivity'!$D$9:$D$21,MATCH(B169,'EV Productivity'!$A$9:$A$21,0)),"") -> 420.4574 | J169: =C169*(D169/$D$169)^$B$4*(E169/$E$169)^$B$5 -> 39.189 | K169: =LN(J169) -> 3.6683961 | L169: =IF(AND(F169>0,ISNUMBER(G169)),(1-F169)/(1/C169-F169/G169),C169) -> 30.331207 | M169: =IF(AND(F169>0,ISNUMBER(G169)),(D169-F169*H169)/(1-F169),D169) -> 3807.6497 | N169: =IF(AND(F169>0,ISNUMBER(G169)),(E169-F169*I169)/(1-F169),E169) -> 168.53352 | O169: =L169*(M169/$M$169)^$E$4*(N169/$N$169)^$E$5 -> 30.331207 | P169: =LN(O169) -> 3.4121771
A170: Truck SUV | B170: 1975 | C170: 11.02071 | D170: 4213.574 | E170: 147.8221 | F170: 0 | G170: =IFERROR(INDEX('EV Productivity'!$B$9:$B$21,MATCH(B170,'EV Productivity'!$A$9:$A$21,0)),"") | H170: =IFERROR(INDEX('EV Productivity'!$C$9:$C$21,MATCH(B170,'EV Productivity'!$A$9:$A$21,0)),"") | I170: =IFERROR(INDEX('EV Productivity'!$D$9:$D$21,MATCH(B170,'EV Productivity'!$A$9:$A$21,0)),"") | J170: =C170*(D170/$D$219)^$B$4*(E170/$E$219)^$B$5 -> 8.6238411 | K170: =LN(J170) -> 2.1545306 | L170: =IF(AND(F170>0,ISNUMBER(G170)),(1-F170)/(1/C170-F170/G170),C170) -> 11.02071 | M170: =IF(AND(F170>0,ISNUMBER(G170)),(D170-F170*H170)/(1-F170),D170) -> 4213.574 | N170: =IF(AND(F170>0,ISNUMBER(G170)),(E170-F170*I170)/(1-F170),E170) -> 147.8221 | O170: =L170*(M170/$M$219)^$E$4*(N170/$N$219)^$E$5 -> 8.2734888 | P170: =LN(O170) -> 2.1130563
A171: Truck SUV | B171: 1976 | C171: 11.76894 | D171: 4328.199 | E171: 141.5282 | F171: 0 | G171: =IFERROR(INDEX('EV Productivity'!$B$9:$B$21,MATCH(B171,'EV Productivity'!$A$9:$A$21,0)),"") | H171: =IFERROR(INDEX('EV Productivity'!$C$9:$C$21,MATCH(B171,'EV Productivity'!$A$9:$A$21,0)),"") | I171: =IFERROR(INDEX('EV Productivity'!$D$9:$D$21,MATCH(B171,'EV Productivity'!$A$9:$A$21,0)),"") | J171: =C171*(D171/$D$219)^$B$4*(E171/$E$219)^$B$5 -> 9.1734746 | K171: =LN(J171) -> 2.2163161 | L171: =IF(AND(F171>0,ISNUMBER(G171)),(1-F171)/(1/C171-F171/G171),C171) -> 11.76894 | M171: =IF(AND(F171>0,ISNUMBER(G171)),(D171-F171*H171)/(1-F171),D171) -> 4328.199 | N171: =IF(AND(F171>0,ISNUMBER(G171)),(E171-F171*I171)/(1-F171),E171) -> 141.5282 | O171: =L171*(M171/$M$219)^$E$4*(N171/$N$219)^$E$5 -> 8.7222798 | P171: =LN(O171) -> 2.1658807
A172: Truck SUV | B172: 1977 | C172: 12.84559 | D172: 4248.173 | E172: 144.9224 | F172: 0 | G172: =IFERROR(INDEX('EV Productivity'!$B$9:$B$21,MATCH(B172,'EV Productivity'!$A$9:$A$21,0)),"") | H172: =IFERROR(INDEX('EV Productivity'!$C$9:$C$21,MATCH(B172,'EV Productivity'!$A$9:$A$21,0)),"") | I172: =IFERROR(INDEX('EV Productivity'!$D$9:$D$21,MATCH(B172,'EV Productivity'!$A$9:$A$21,0)),"") | J172: =C172*(D172/$D$219)^$B$4*(E172/$E$219)^$B$5 -> 10.01564 | K172: =LN(J172) -> 2.3041479 | L172: =IF(AND(F172>0,ISNUMBER(G172)),(1-F172)/(1/C172-F172/G172),C172) -> 12.84559 | M172: =IF(AND(F172>0,ISNUMBER(G172)),(D172-F172*H172)/(1-F172),D172) -> 4248.173 | N172: =IF(AND(F172>0,ISNUMBER(G172)),(E172-F172*I172)/(1-F172),E172) -> 144.9224 | O172: =L172*(M172/$M$219)^$E$4*(N172/$N$219)^$E$5 -> 9.575384 | P172: =LN(O172) -> 2.2591956
A173: Truck SUV | B173: 1978 | C173: 12.2864 | D173: 4281.723 | E173: 149.658 | F173: 0 | G173: =IFERROR(INDEX('EV Productivity'!$B$9:$B$21,MATCH(B173,'EV Productivity'!$A$9:$A$21,0)),"") | H173: =IFERROR(INDEX('EV Productivity'!$C$9:$C$21,MATCH(B173,'EV Productivity'!$A$9:$A$21,0)),"") | I173: =IFERROR(INDEX('EV Productivity'!$D$9:$D$21,MATCH(B173,'EV Productivity'!$A$9:$A$21,0)),"") | J173: =C173*(D173/$D$219)^$B$4*(E173/$E$219)^$B$5 -> 9.7285478 | K173: =LN(J173) -> 2.2750646 | L173: =IF(AND(F173>0,ISNUMBER(G173)),(1-F173)/(1/C173-F173/G173),C173) -> 12.2864 | M173: =IF(AND(F173>0,ISNUMBER(G173)),(D173-F173*H173)/(1-F173),D173) -> 4281.723 | N173: =IF(AND(F173>0,ISNUMBER(G173)),(E173-F173*I173)/(1-F173),E173) -> 149.658 | O173: =L173*(M173/$M$219)^$E$4*(N173/$N$219)^$E$5 -> 9.3241565 | P173: =LN(O173) -> 2.2326085
A174: Truck SUV | B174: 1979 | C174: 10.53097 | D174: 4560.526 | E174: 145.2456 | F174: 0 | G174: =IFERROR(INDEX('EV Productivity'!$B$9:$B$21,MATCH(B174,'EV Productivity'!$A$9:$A$21,0)),"") | H174: =IFERROR(INDEX('EV Productivity'!$C$9:$C$21,MATCH(B174,'EV Productivity'!$A$9:$A$21,0)),"") | I174: =IFERROR(INDEX('EV Productivity'!$D$9:$D$21,MATCH(B174,'EV Productivity'!$A$9:$A$21,0)),"") | J174: =C174*(D174/$D$219)^$B$4*(E174/$E$219)^$B$5 -> 8.4859249 | K174: =LN(J174) -> 2.1384089 | L174: =IF(AND(F174>0,ISNUMBER(G174)),(1-F174)/(1/C174-F174/G174),C174) -> 10.53097 | M174: =IF(AND(F174>0,ISNUMBER(G174)),(D174-F174*H174)/(1-F174),D174) -> 4560.526 | N174: =IF(AND(F174>0,ISNUMBER(G174)),(E174-F174*I174)/(1-F174),E174) -> 145.2456 | O174: =L174*(M174/$M$219)^$E$4*(N174/$N$219)^$E$5 -> 8.029665 | P174: =LN(O174) -> 2.0831428
A175: Truck SUV | B175: 1980 | C175: 13.18631 | D175: 4236.831 | E175: 130.7478 | F175: 0 | G175: =IFERROR(INDEX('EV Productivity'!$B$9:$B$21,MATCH(B175,'EV Productivity'!$A$9:$A$21,0)),"") | H175: =IFERROR(INDEX('EV Productivity'!$C$9:$C$21,MATCH(B175,'EV Productivity'!$A$9:$A$21,0)),"") | I175: =IFERROR(INDEX('EV Productivity'!$D$9:$D$21,MATCH(B175,'EV Productivity'!$A$9:$A$21,0)),"") | J175: =C175*(D175/$D$219)^$B$4*(E175/$E$219)^$B$5 -> 9.8862166 | K175: =LN(J175) -> 2.2911415 | L175: =IF(AND(F175>0,ISNUMBER(G175)),(1-F175)/(1/C175-F175/G175),C175) -> 13.18631 | M175: =IF(AND(F175>0,ISNUMBER(G175)),(D175-F175*H175)/(1-F175),D175) -> 4236.831 | N175: =IF(AND(F175>0,ISNUMBER(G175)),(E175-F175*I175)/(1-F175),E175) -> 130.7478 | O175: =L175*(M175/$M$219)^$E$4*(N175/$N$219)^$E$5 -> 9.3450465 | P175: =LN(O175) -> 2.2348464
A176: Truck SUV | B176: 1981 | C176: 14.30158 | D176: 4208.028 | E176: 131.5149 | F176: 0 | G176: =IFERROR(INDEX('EV Productivity'!$B$9:$B$21,MATCH(B176,'EV Productivity'!$A$9:$A$21,0)),"") | H176: =IFERROR(INDEX('EV Productivity'!$C$9:$C$21,MATCH(B176,'EV Productivity'!$A$9:$A$21,0)),"") | I176: =IFERROR(INDEX('EV Productivity'!$D$9:$D$21,MATCH(B176,'EV Productivity'!$A$9:$A$21,0)),"") | J176: =C176*(D176/$D$219)^$B$4*(E176/$E$219)^$B$5 -> 10.712406 | K176: =LN(J176) -> 2.3714025 | L176: =IF(AND(F176>0,ISNUMBER(G176)),(1-F176)/(1/C176-F176/G176),C176) -> 14.30158 | M176: =IF(AND(F176>0,ISNUMBER(G176)),(D176-F176*H176)/(1-F176),D176) -> 4208.028 | N176: =IF(AND(F176>0,ISNUMBER(G176)),(E176-F176*I176)/(1-F176),E176) -> 131.5149 | O176: =L176*(M176/$M$219)^$E$4*(N176/$N$219)^$E$5 -> 10.143071 | P176: =LN(O176) -> 2.3167908
A177: Truck SUV | B177: 1982 | C177: 14.69788 | D177: 4494.407 | E177: 132.9675 | F177: 0 | G177: =IFERROR(INDEX('EV Productivity'!$B$9:$B$21,MATCH(B177,'EV Productivity'!$A$9:$A$21,0)),"") | H177: =IFERROR(INDEX('EV Productivity'!$C$9:$C$21,MATCH(B177,'EV Productivity'!$A$9:$A$21,0)),"") | I177: =IFERROR(INDEX('EV Productivity'!$D$9:$D$21,MATCH(B177,'EV Productivity'!$A$9:$A$21,0)),"") | J177: =C177*(D177/$D$219)^$B$4*(E177/$E$219)^$B$5 -> 11.388393 | K177: =LN(J177) -> 2.4325946 | L177: =IF(AND(F177>0,ISNUMBER(G177)),(1-F177)/(1/C177-F177/G177),C177) -> 14.69788 | M177: =IF(AND(F177>0,ISNUMBER(G177)),(D177-F177*H177)/(1-F177),D177) -> 4494.407 | N177: =IF(AND(F177>0,ISNUMBER(G177)),(E177-F177*I177)/(1-F177),E177) -> 132.9675 | O177: =L177*(M177/$M$219)^$E$4*(N177/$N$219)^$E$5 -> 10.691286 | P177: =LN(O177) -> 2.369429
A178: Truck SUV | B178: 1983 | C178: 15.79468 | D178: 4269.657 | E178: 126.9095 | F178: 0 | G178: =IFERROR(INDEX('EV Productivity'!$B$9:$B$21,MATCH(B178,'EV Productivity'!$A$9:$A$21,0)),"") | H178: =IFERROR(INDEX('EV Productivity'!$C$9:$C$21,MATCH(B178,'EV Productivity'!$A$9:$A$21,0)),"") | I178: =IFERROR(INDEX('EV Productivity'!$D$9:$D$21,MATCH(B178,'EV Productivity'!$A$9:$A$21,0)),"") | J178: =C178*(D178/$D$219)^$B$4*(E178/$E$219)^$B$5 -> 11.753328 | K178: =LN(J178) -> 2.4641364 | L178: =IF(AND(F178>0,ISNUMBER(G178)),(1-F178)/(1/C178-F178/G178),C178) -> 15.79468 | M178: =IF(AND(F178>0,ISNUMBER(G178)),(D178-F178*H178)/(1-F178),D178) -> 4269.657 | N178: =IF(AND(F178>0,ISNUMBER(G178)),(E178-F178*I178)/(1-F178),E178) -> 126.9095 | O178: =L178*(M178/$M$219)^$E$4*(N178/$N$219)^$E$5 -> 11.059534 | P178: =LN(O178) -> 2.4032929
A179: Truck SUV | B179: 1984 | C179: 16.19242 | D179: 4048.509 | E179: 121.6039 | F179: 0 | G179: =IFERROR(INDEX('EV Productivity'!$B$9:$B$21,MATCH(B179,'EV Productivity'!$A$9:$A$21,0)),"") | H179: =IFERROR(INDEX('EV Productivity'!$C$9:$C$21,MATCH(B179,'EV Productivity'!$A$9:$A$21,0)),"") | I179: =IFERROR(INDEX('EV Productivity'!$D$9:$D$21,MATCH(B179,'EV Productivity'!$A$9:$A$21,0)),"") | J179: =C179*(D179/$D$219)^$B$4*(E179/$E$219)^$B$5 -> 11.578772 | K179: =LN(J179) -> 2.4491734 | L179: =IF(AND(F179>0,ISNUMBER(G179)),(1-F179)/(1/C179-F179/G179),C179) -> 16.19242 | M179: =IF(AND(F179>0,ISNUMBER(G179)),(D179-F179*H179)/(1-F179),D179) -> 4048.509 | N179: =IF(AND(F179>0,ISNUMBER(G179)),(E179-F179*I179)/(1-F179),E179) -> 121.6039 | O179: =L179*(M179/$M$219)^$E$4*(N179/$N$219)^$E$5 -> 10.92857 | P179: =LN(O179) -> 2.3913804
A180: Truck SUV | B180: 1985 | C180: 16.53857 | D180: 4092.154 | E180: 123.3431 | F180: 0 | G180: =IFERROR(INDEX('EV Productivity'!$B$9:$B$21,MATCH(B180,'EV Productivity'!$A$9:$A$21,0)),"") | H180: =IFERROR(INDEX('EV Productivity'!$C$9:$C$21,MATCH(B180,'EV Productivity'!$A$9:$A$21,0)),"") | I180: =IFERROR(INDEX('EV Productivity'!$D$9:$D$21,MATCH(B180,'EV Productivity'!$A$9:$A$21,0)),"") | J180: =C180*(D180/$D$219)^$B$4*(E180/$E$219)^$B$5 -> 11.94627 | K180: =LN(J180) -> 2.4804191 | L180: =IF(AND(F180>0,ISNUMBER(G180)),(1-F180)/(1/C180-F180/G180),C180) -> 16.53857 | M180: =IF(AND(F180>0,ISNUMBER(G180)),(D180-F180*H180)/(1-F180),D180) -> 4092.154 | N180: =IF(AND(F180>0,ISNUMBER(G180)),(E180-F180*I180)/(1-F180),E180) -> 123.3431 | O180: =L180*(M180/$M$219)^$E$4*(N180/$N$219)^$E$5 -> 11.275687 | P180: =LN(O180) -> 2.4226488
A181: Truck SUV | B181: 1986 | C181: 17.03397 | D181: 3957.881 | E181: 127.7072 | F181: 0 | G181: =IFERROR(INDEX('EV Productivity'!$B$9:$B$21,MATCH(B181,'EV Productivity'!$A$9:$A$21,0)),"") | H181: =IFERROR(INDEX('EV Productivity'!$C$9:$C$21,MATCH(B181,'EV Productivity'!$A$9:$A$21,0)),"") | I181: =IFERROR(INDEX('EV Productivity'!$D$9:$D$21,MATCH(B181,'EV Productivity'!$A$9:$A$21,0)),"") | J181: =C181*(D181/$D$219)^$B$4*(E181/$E$219)^$B$5 -> 12.276147 | K181: =LN(J181) -> 2.5076581 | L181: =IF(AND(F181>0,ISNUMBER(G181)),(1-F181)/(1/C181-F181/G181),C181) -> 17.03397 | M181: =IF(AND(F181>0,ISNUMBER(G181)),(D181-F181*H181)/(1-F181),D181) -> 3957.881 | N181: =IF(AND(F181>0,ISNUMBER(G181)),(E181-F181*I181)/(1-F181),E181) -> 127.7072 | O181: =L181*(M181/$M$219)^$E$4*(N181/$N$219)^$E$5 -> 11.691049 | P181: =LN(O181) -> 2.4588235
... A219: Truck SUV | B219: 2024 | C219: 25.70378 | D219: 4547.716 | E219: 261.6723 | F219: 0.041 | G219: =IFERROR(INDEX('EV Productivity'!$B$9:$B$21,MATCH(B219,'EV Productivity'!$A$9:$A$21,0)),"") -> 117.14232 | H219: =IFERROR(INDEX('EV Productivity'!$C$9:$C$21,MATCH(B219,'EV Productivity'!$A$9:$A$21,0)),"") -> 4409.726 | I219: =IFERROR(INDEX('EV Productivity'!$D$9:$D$21,MATCH(B219,'EV Productivity'!$A$9:$A$21,0)),"") -> 420.4574 | J219: =C219*(D219/$D$219)^$B$4*(E219/$E$219)^$B$5 -> 25.70378 | K219: =LN(J219) -> 3.2466381 | L219: =IF(AND(F219>0,ISNUMBER(G219)),(1-F219)/(1/C219-F219/G219),C219) -> 24.873698 | M219: =IF(AND(F219>0,ISNUMBER(G219)),(D219-F219*H219)/(1-F219),D219) -> 4553.6155 | N219: =IF(AND(F219>0,ISNUMBER(G219)),(E219-F219*I219)/(1-F219),E219) -> 254.88378 | O219: =L219*(M219/$M$219)^$E$4*(N219/$N$219)^$E$5 -> 24.873698 | P219: =LN(O219) -> 3.2138109
A220: Pickup | B220: 1975 | C220: 11.91476 | D220: 4011.977 | E220: 140.9365 | F220: 0 | G220: =IFERROR(INDEX('EV Productivity'!$B$9:$B$21,MATCH(B220,'EV Productivity'!$A$9:$A$21,0)),"") | H220: =IFERROR(INDEX('EV Productivity'!$C$9:$C$21,MATCH(B220,'EV Productivity'!$A$9:$A$21,0)),"") | I220: =IFERROR(INDEX('EV Productivity'!$D$9:$D$21,MATCH(B220,'EV Productivity'!$A$9:$A$21,0)),"") | J220: =C220*(D220/$D$269)^$B$4*(E220/$E$269)^$B$5 -> 7.6684529 | K220: =LN(J220) -> 2.0371149 | L220: =IF(AND(F220>0,ISNUMBER(G220)),(1-F220)/(1/C220-F220/G220),C220) -> 11.91476 | M220: =IF(AND(F220>0,ISNUMBER(G220)),(D220-F220*H220)/(1-F220),D220) -> 4011.977 | N220: =IF(AND(F220>0,ISNUMBER(G220)),(E220-F220*I220)/(1-F220),E220) -> 140.9365 | O220: =L220*(M220/$M$269)^$E$4*(N220/$N$269)^$E$5 -> 7.2408013 | P220: =LN(O220) -> 1.9797319
A221: Pickup | B221: 1976 | C221: 12.44161 | D221: 4121.843 | E221: 139.4 | F221: 0 | G221: =IFERROR(INDEX('EV Productivity'!$B$9:$B$21,MATCH(B221,'EV Productivity'!$A$9:$A$21,0)),"") | H221: =IFERROR(INDEX('EV Productivity'!$C$9:$C$21,MATCH(B221,'EV Productivity'!$A$9:$A$21,0)),"") | I221: =IFERROR(INDEX('EV Productivity'!$D$9:$D$21,MATCH(B221,'EV Productivity'!$A$9:$A$21,0)),"") | J221: =C221*(D221/$D$269)^$B$4*(E221/$E$269)^$B$5 -> 8.0733586 | K221: =LN(J221) -> 2.0885696 | L221: =IF(AND(F221>0,ISNUMBER(G221)),(1-F221)/(1/C221-F221/G221),C221) -> 12.44161 | M221: =IF(AND(F221>0,ISNUMBER(G221)),(D221-F221*H221)/(1-F221),D221) -> 4121.843 | N221: =IF(AND(F221>0,ISNUMBER(G221)),(E221-F221*I221)/(1-F221),E221) -> 139.4 | O221: =L221*(M221/$M$269)^$E$4*(N221/$N$269)^$E$5 -> 7.5830237 | P221: =LN(O221) -> 2.025912
A222: Pickup | B222: 1977 | C222: 13.55757 | D222: 4091.847 | E222: 146.3648 | F222: 0 | G222: =IFERROR(INDEX('EV Productivity'!$B$9:$B$21,MATCH(B222,'EV Productivity'!$A$9:$A$21,0)),"") | H222: =IFERROR(INDEX('EV Productivity'!$C$9:$C$21,MATCH(B222,'EV Productivity'!$A$9:$A$21,0)),"") | I222: =IFERROR(INDEX('EV Productivity'!$D$9:$D$21,MATCH(B222,'EV Productivity'!$A$9:$A$21,0)),"") | J222: =C222*(D222/$D$269)^$B$4*(E222/$E$269)^$B$5 -> 8.9276152 | K222: =LN(J222) -> 2.1891493 | L222: =IF(AND(F222>0,ISNUMBER(G222)),(1-F222)/(1/C222-F222/G222),C222) -> 13.55757 | M222: =IF(AND(F222>0,ISNUMBER(G222)),(D222-F222*H222)/(1-F222),D222) -> 4091.847 | N222: =IF(AND(F222>0,ISNUMBER(G222)),(E222-F222*I222)/(1-F222),E222) -> 146.3648 | O222: =L222*(M222/$M$269)^$E$4*(N222/$N$269)^$E$5 -> 8.4413407 | P222: =LN(O222) -> 2.1331411
A223: Pickup | B223: 1978 | C223: 13.32817 | D223: 4104.366 | E223: 144.152 | F223: 0 | G223: =IFERROR(INDEX('EV Productivity'!$B$9:$B$21,MATCH(B223,'EV Productivity'!$A$9:$A$21,0)),"") | H223: =IFERROR(INDEX('EV Productivity'!$C$9:$C$21,MATCH(B223,'EV Productivity'!$A$9:$A$21,0)),"") | I223: =IFERROR(INDEX('EV Productivity'!$D$9:$D$21,MATCH(B223,'EV Productivity'!$A$9:$A$21,0)),"") | J223: =C223*(D223/$D$269)^$B$4*(E223/$E$269)^$B$5 -> 8.7394442 | K223: =LN(J223) -> 2.1678466 | L223: =IF(AND(F223>0,ISNUMBER(G223)),(1-F223)/(1/C223-F223/G223),C223) -> 13.32817 | M223: =IF(AND(F223>0,ISNUMBER(G223)),(D223-F223*H223)/(1-F223),D223) -> 4104.366 | N223: =IF(AND(F223>0,ISNUMBER(G223)),(E223-F223*I223)/(1-F223),E223) -> 144.152 | O223: =L223*(M223/$M$269)^$E$4*(N223/$N$269)^$E$5 -> 8.2453194 | P223: =LN(O223) -> 2.1096457
A224: Pickup | B224: 1979 | C224: 13.21499 | D224: 4142.085 | E224: 135.6823 | F224: 0 | G224: =IFERROR(INDEX('EV Productivity'!$B$9:$B$21,MATCH(B224,'EV Productivity'!$A$9:$A$21,0)),"") | H224: =IFERROR(INDEX('EV Productivity'!$C$9:$C$21,MATCH(B224,'EV Productivity'!$A$9:$A$21,0)),"") | I224: =IFERROR(INDEX('EV Productivity'!$D$9:$D$21,MATCH(B224,'EV Productivity'!$A$9:$A$21,0)),"") | J224: =C224*(D224/$D$269)^$B$4*(E224/$E$269)^$B$5 -> 8.5089588 | K224: =LN(J224) -> 2.1411196 | L224: =IF(AND(F224>0,ISNUMBER(G224)),(1-F224)/(1/C224-F224/G224),C224) -> 13.21499 | M224: =IF(AND(F224>0,ISNUMBER(G224)),(D224-F224*H224)/(1-F224),D224) -> 4142.085 | N224: =IF(AND(F224>0,ISNUMBER(G224)),(E224-F224*I224)/(1-F224),E224) -> 135.6823 | O224: =L224*(M224/$M$269)^$E$4*(N224/$N$269)^$E$5 -> 7.9617503 | P224: =LN(O224) -> 2.0746489
A225: Pickup | B225: 1980 | C225: 16.51884 | D225: 3739.957 | E225: 118.0136 | F225: 0 | G225: =IFERROR(INDEX('EV Productivity'!$B$9:$B$21,MATCH(B225,'EV Productivity'!$A$9:$A$21,0)),"") | H225: =IFERROR(INDEX('EV Productivity'!$C$9:$C$21,MATCH(B225,'EV Productivity'!$A$9:$A$21,0)),"") | I225: =IFERROR(INDEX('EV Productivity'!$D$9:$D$21,MATCH(B225,'EV Productivity'!$A$9:$A$21,0)),"") | J225: =C225*(D225/$D$269)^$B$4*(E225/$E$269)^$B$5 -> 9.646187 | K225: =LN(J225) -> 2.2665627 | L225: =IF(AND(F225>0,ISNUMBER(G225)),(1-F225)/(1/C225-F225/G225),C225) -> 16.51884 | M225: =IF(AND(F225>0,ISNUMBER(G225)),(D225-F225*H225)/(1-F225),D225) -> 3739.957 | N225: =IF(AND(F225>0,ISNUMBER(G225)),(E225-F225*I225)/(1-F225),E225) -> 118.0136 | O225: =L225*(M225/$M$269)^$E$4*(N225/$N$269)^$E$5 -> 9.0195008 | P225: =LN(O225) -> 2.199389
A226: Pickup | B226: 1981 | C226: 17.88228 | D226: 3679.45 | E226: 115.4839 | F226: 0 | G226: =IFERROR(INDEX('EV Productivity'!$B$9:$B$21,MATCH(B226,'EV Productivity'!$A$9:$A$21,0)),"") | H226: =IFERROR(INDEX('EV Productivity'!$C$9:$C$21,MATCH(B226,'EV Productivity'!$A$9:$A$21,0)),"") | I226: =IFERROR(INDEX('EV Productivity'!$D$9:$D$21,MATCH(B226,'EV Productivity'!$A$9:$A$21,0)),"") | J226: =C226*(D226/$D$269)^$B$4*(E226/$E$269)^$B$5 -> 10.283008 | K226: =LN(J226) -> 2.3304928 | L226: =IF(AND(F226>0,ISNUMBER(G226)),(1-F226)/(1/C226-F226/G226),C226) -> 17.88228 | M226: =IF(AND(F226>0,ISNUMBER(G226)),(D226-F226*H226)/(1-F226),D226) -> 3679.45 | N226: =IF(AND(F226>0,ISNUMBER(G226)),(E226-F226*I226)/(1-F226),E226) -> 115.4839 | O226: =L226*(M226/$M$269)^$E$4*(N226/$N$269)^$E$5 -> 9.6145432 | P226: =LN(O226) -> 2.2632769
A227: Pickup | B227: 1982 | C227: 18.48502 | D227: 3628.863 | E227: 116.5468 | F227: 0 | G227: =IFERROR(INDEX('EV Productivity'!$B$9:$B$21,MATCH(B227,'EV Productivity'!$A$9:$A$21,0)),"") | H227: =IFERROR(INDEX('EV Productivity'!$C$9:$C$21,MATCH(B227,'EV Productivity'!$A$9:$A$21,0)),"") | I227: =IFERROR(INDEX('EV Productivity'!$D$9:$D$21,MATCH(B227,'EV Productivity'!$A$9:$A$21,0)),"") | J227: =C227*(D227/$D$269)^$B$4*(E227/$E$269)^$B$5 -> 10.598963 | K227: =LN(J227) -> 2.3607561 | L227: =IF(AND(F227>0,ISNUMBER(G227)),(1-F227)/(1/C227-F227/G227),C227) -> 18.48502 | M227: =IF(AND(F227>0,ISNUMBER(G227)),(D227-F227*H227)/(1-F227),D227) -> 3628.863 | N227: =IF(AND(F227>0,ISNUMBER(G227)),(E227-F227*I227)/(1-F227),E227) -> 116.5468 | O227: =L227*(M227/$M$269)^$E$4*(N227/$N$269)^$E$5 -> 9.9407985 | P227: =LN(O227) -> 2.2966473
A228: Pickup | B228: 1983 | C228: 18.87651 | D228: 3543.619 | E228: 112.3953 | F228: 0 | G228: =IFERROR(INDEX('EV Productivity'!$B$9:$B$21,MATCH(B228,'EV Productivity'!$A$9:$A$21,0)),"") | H228: =IFERROR(INDEX('EV Productivity'!$C$9:$C$21,MATCH(B228,'EV Productivity'!$A$9:$A$21,0)),"") | I228: =IFERROR(INDEX('EV Productivity'!$D$9:$D$21,MATCH(B228,'EV Productivity'!$A$9:$A$21,0)),"") | J228: =C228*(D228/$D$269)^$B$4*(E228/$E$269)^$B$5 -> 10.565253 | K228: =LN(J228) -> 2.3575706 | L228: =IF(AND(F228>0,ISNUMBER(G228)),(1-F228)/(1/C228-F228/G228),C228) -> 18.87651 | M228: =IF(AND(F228>0,ISNUMBER(G228)),(D228-F228*H228)/(1-F228),D228) -> 3543.619 | N228: =IF(AND(F228>0,ISNUMBER(G228)),(E228-F228*I228)/(1-F228),E228) -> 112.3953 | O228: =L228*(M228/$M$269)^$E$4*(N228/$N$269)^$E$5 -> 9.9032708 | P228: =LN(O228) -> 2.2928651
A229: Pickup | B229: 1984 | C229: 18.25999 | D229: 3618.901 | E229: 114.0118 | F229: 0 | G229: =IFERROR(INDEX('EV Productivity'!$B$9:$B$21,MATCH(B229,'EV Productivity'!$A$9:$A$21,0)),"") | H229: =IFERROR(INDEX('EV Productivity'!$C$9:$C$21,MATCH(B229,'EV Productivity'!$A$9:$A$21,0)),"") | I229: =IFERROR(INDEX('EV Productivity'!$D$9:$D$21,MATCH(B229,'EV Productivity'!$A$9:$A$21,0)),"") | J229: =C229*(D229/$D$269)^$B$4*(E229/$E$269)^$B$5 -> 10.372415 | K229: =LN(J229) -> 2.3391499 | L229: =IF(AND(F229>0,ISNUMBER(G229)),(1-F229)/(1/C229-F229/G229),C229) -> 18.25999 | M229: =IF(AND(F229>0,ISNUMBER(G229)),(D229-F229*H229)/(1-F229),D229) -> 3618.901 | N229: =IF(AND(F229>0,ISNUMBER(G229)),(E229-F229*I229)/(1-F229),E229) -> 114.0118 | O229: =L229*(M229/$M$269)^$E$4*(N229/$N$269)^$E$5 -> 9.7079198 | P229: =LN(O229) -> 2.272942
A230: Pickup | B230: 1985 | C230: 18.20137 | D230: 3642.38 | E230: 122.8821 | F230: 0 | G230: =IFERROR(INDEX('EV Productivity'!$B$9:$B$21,MATCH(B230,'EV Productivity'!$A$9:$A$21,0)),"") | H230: =IFERROR(INDEX('EV Productivity'!$C$9:$C$21,MATCH(B230,'EV Productivity'!$A$9:$A$21,0)),"") | I230: =IFERROR(INDEX('EV Productivity'!$D$9:$D$21,MATCH(B230,'EV Productivity'!$A$9:$A$21,0)),"") | J230: =C230*(D230/$D$269)^$B$4*(E230/$E$269)^$B$5 -> 10.660066 | K230: =LN(J230) -> 2.3665046 | L230: =IF(AND(F230>0,ISNUMBER(G230)),(1-F230)/(1/C230-F230/G230),C230) -> 18.20137 | M230: =IF(AND(F230>0,ISNUMBER(G230)),(D230-F230*H230)/(1-F230),D230) -> 3642.38 | N230: =IF(AND(F230>0,ISNUMBER(G230)),(E230-F230*I230)/(1-F230),E230) -> 122.8821 | O230: =L230*(M230/$M$269)^$E$4*(N230/$N$269)^$E$5 -> 10.05309 | P230: =LN(O230) -> 2.30788
A231: Pickup | B231: 1986 | C231: 18.8625 | D231: 3574.005 | E231: 120.347 | F231: 0 | G231: =IFERROR(INDEX('EV Productivity'!$B$9:$B$21,MATCH(B231,'EV Productivity'!$A$9:$A$21,0)),"") | H231: =IFERROR(INDEX('EV Productivity'!$C$9:$C$21,MATCH(B231,'EV Productivity'!$A$9:$A$21,0)),"") | I231: =IFERROR(INDEX('EV Productivity'!$D$9:$D$21,MATCH(B231,'EV Productivity'!$A$9:$A$21,0)),"") | J231: =C231*(D231/$D$269)^$B$4*(E231/$E$269)^$B$5 -> 10.868986 | K231: =LN(J231) -> 2.3859134 | L231: =IF(AND(F231>0,ISNUMBER(G231)),(1-F231)/(1/C231-F231/G231),C231) -> 18.8625 | M231: =IF(AND(F231>0,ISNUMBER(G231)),(D231-F231*H231)/(1-F231),D231) -> 3574.005 | N231: =IF(AND(F231>0,ISNUMBER(G231)),(E231-F231*I231)/(1-F231),E231) -> 120.347 | O231: =L231*(M231/$M$269)^$E$4*(N231/$N$269)^$E$5 -> 10.254674 | P231: =LN(O231) -> 2.3277336
... A269: Pickup | B269: 2024 | C269: 20.54899 | D269: 5244.535 | E269: 334.9473 | F269: 0.019 | G269: =IFERROR(INDEX('EV Productivity'!$B$9:$B$21,MATCH(B269,'EV Productivity'!$A$9:$A$21,0)),"") -> 117.14232 | H269: =IFERROR(INDEX('EV Productivity'!$C$9:$C$21,MATCH(B269,'EV Productivity'!$A$9:$A$21,0)),"") -> 4409.726 | I269: =IFERROR(INDEX('EV Productivity'!$D$9:$D$21,MATCH(B269,'EV Productivity'!$A$9:$A$21,0)),"") -> 420.4574 | J269: =C269*(D269/$D$269)^$B$4*(E269/$E$269)^$B$5 -> 20.54899 | K269: =LN(J269) -> 3.0228118 | L269: =IF(AND(F269>0,ISNUMBER(G269)),(1-F269)/(1/C269-F269/G269),C269) -> 20.225972 | M269: =IF(AND(F269>0,ISNUMBER(G269)),(D269-F269*H269)/(1-F269),D269) -> 5260.7036 | N269: =IF(AND(F269>0,ISNUMBER(G269)),(E269-F269*I269)/(1-F269),E269) -> 333.29114 | O269: =L269*(M269/$M$269)^$E$4*(N269/$N$269)^$E$5 -> 20.225972 | P269: =LN(O269) -> 3.0069675
A270: Minivan/Van | B270: 1975 | C270: 11.10606 | D270: 4195.69 | E270: 143.2245 | F270: 0 | G270: =IFERROR(INDEX('EV Productivity'!$B$9:$B$21,MATCH(B270,'EV Productivity'!$A$9:$A$21,0)),"") | H270: =IFERROR(INDEX('EV Productivity'!$C$9:$C$21,MATCH(B270,'EV Productivity'!$A$9:$A$21,0)),"") | I270: =IFERROR(INDEX('EV Productivity'!$D$9:$D$21,MATCH(B270,'EV Productivity'!$A$9:$A$21,0)),"") | J270: =C270*(D270/$D$319)^$B$4*(E270/$E$319)^$B$5 -> 8.4074154 | K270: =LN(J270) -> 2.1291141 | L270: =IF(AND(F270>0,ISNUMBER(G270)),(1-F270)/(1/C270-F270/G270),C270) -> 11.10606 | M270: =IF(AND(F270>0,ISNUMBER(G270)),(D270-F270*H270)/(1-F270),D270) -> 4195.69 | N270: =IF(AND(F270>0,ISNUMBER(G270)),(E270-F270*I270)/(1-F270),E270) -> 143.2245 | O270: =L270*(M270/$M$319)^$E$4*(N270/$N$319)^$E$5 -> 8.0066439 | P270: =LN(O270) -> 2.0802717
A271: Minivan/Van | B271: 1976 | C271: 11.78392 | D271: 4199.864 | E271: 145.6272 | F271: 0 | G271: =IFERROR(INDEX('EV Productivity'!$B$9:$B$21,MATCH(B271,'EV Productivity'!$A$9:$A$21,0)),"") | H271: =IFERROR(INDEX('EV Productivity'!$C$9:$C$21,MATCH(B271,'EV Productivity'!$A$9:$A$21,0)),"") | I271: =IFERROR(INDEX('EV Productivity'!$D$9:$D$21,MATCH(B271,'EV Productivity'!$A$9:$A$21,0)),"") | J271: =C271*(D271/$D$319)^$B$4*(E271/$E$319)^$B$5 -> 8.9795269 | K271: =LN(J271) -> 2.1949472 | L271: =IF(AND(F271>0,ISNUMBER(G271)),(1-F271)/(1/C271-F271/G271),C271) -> 11.78392 | M271: =IF(AND(F271>0,ISNUMBER(G271)),(D271-F271*H271)/(1-F271),D271) -> 4199.864 | N271: =IF(AND(F271>0,ISNUMBER(G271)),(E271-F271*I271)/(1-F271),E271) -> 145.6272 | O271: =L271*(M271/$M$319)^$E$4*(N271/$N$319)^$E$5 -> 8.5664586 | P271: =LN(O271) -> 2.1478544
A272: Minivan/Van | B272: 1977 | C272: 12.51297 | D272: 4252.284 | E272: 152.3661 | F272: 0 | G272: =IFERROR(INDEX('EV Productivity'!$B$9:$B$21,MATCH(B272,'EV Productivity'!$A$9:$A$21,0)),"") | H272: =IFERROR(INDEX('EV Productivity'!$C$9:$C$21,MATCH(B272,'EV Productivity'!$A$9:$A$21,0)),"") | I272: =IFERROR(INDEX('EV Productivity'!$D$9:$D$21,MATCH(B272,'EV Productivity'!$A$9:$A$21,0)),"") | J272: =C272*(D272/$D$319)^$B$4*(E272/$E$319)^$B$5 -> 9.7501444 | K272: =LN(J272) -> 2.2772821 | L272: =IF(AND(F272>0,ISNUMBER(G272)),(1-F272)/(1/C272-F272/G272),C272) -> 12.51297 | M272: =IF(AND(F272>0,ISNUMBER(G272)),(D272-F272*H272)/(1-F272),D272) -> 4252.284 | N272: =IF(AND(F272>0,ISNUMBER(G272)),(E272-F272*I272)/(1-F272),E272) -> 152.3661 | O272: =L272*(M272/$M$319)^$E$4*(N272/$N$319)^$E$5 -> 9.3324896 | P272: =LN(O272) -> 2.2335018
A273: Minivan/Van | B273: 1978 | C273: 12.08009 | D273: 4249.551 | E273: 149.1321 | F273: 0 | G273: =IFERROR(INDEX('EV Productivity'!$B$9:$B$21,MATCH(B273,'EV Productivity'!$A$9:$A$21,0)),"") | H273: =IFERROR(INDEX('EV Productivity'!$C$9:$C$21,MATCH(B273,'EV Productivity'!$A$9:$A$21,0)),"") | I273: =IFERROR(INDEX('EV Productivity'!$D$9:$D$21,MATCH(B273,'EV Productivity'!$A$9:$A$21,0)),"") | J273: =C273*(D273/$D$319)^$B$4*(E273/$E$319)^$B$5 -> 9.3359148 | K273: =LN(J273) -> 2.2338688 | L273: =IF(AND(F273>0,ISNUMBER(G273)),(1-F273)/(1/C273-F273/G273),C273) -> 12.08009 | M273: =IF(AND(F273>0,ISNUMBER(G273)),(D273-F273*H273)/(1-F273),D273) -> 4249.551 | N273: =IF(AND(F273>0,ISNUMBER(G273)),(E273-F273*I273)/(1-F273),E273) -> 149.1321 | O273: =L273*(M273/$M$319)^$E$4*(N273/$N$319)^$E$5 -> 8.9150159 | P273: =LN(O273) -> 2.187737
A274: Minivan/Van | B274: 1979 | C274: 11.48461 | D274: 4540.969 | E274: 144.2939 | F274: 0 | G274: =IFERROR(INDEX('EV Productivity'!$B$9:$B$21,MATCH(B274,'EV Productivity'!$A$9:$A$21,0)),"") | H274: =IFERROR(INDEX('EV Productivity'!$C$9:$C$21,MATCH(B274,'EV Productivity'!$A$9:$A$21,0)),"") | I274: =IFERROR(INDEX('EV Productivity'!$D$9:$D$21,MATCH(B274,'EV Productivity'!$A$9:$A$21,0)),"") | J274: =C274*(D274/$D$319)^$B$4*(E274/$E$319)^$B$5 -> 9.0356423 | K274: =LN(J274) -> 2.201177 | L274: =IF(AND(F274>0,ISNUMBER(G274)),(1-F274)/(1/C274-F274/G274),C274) -> 11.48461 | M274: =IF(AND(F274>0,ISNUMBER(G274)),(D274-F274*H274)/(1-F274),D274) -> 4540.969 | N274: =IF(AND(F274>0,ISNUMBER(G274)),(E274-F274*I274)/(1-F274),E274) -> 144.2939 | O274: =L274*(M274/$M$319)^$E$4*(N274/$N$319)^$E$5 -> 8.5113765 | P274: =LN(O274) -> 2.1414037
A275: Minivan/Van | B275: 1980 | C275: 14.13642 | D275: 4352.742 | E275: 130.5904 | F275: 0 | G275: =IFERROR(INDEX('EV Productivity'!$B$9:$B$21,MATCH(B275,'EV Productivity'!$A$9:$A$21,0)),"") | H275: =IFERROR(INDEX('EV Productivity'!$C$9:$C$21,MATCH(B275,'EV Productivity'!$A$9:$A$21,0)),"") | I275: =IFERROR(INDEX('EV Productivity'!$D$9:$D$21,MATCH(B275,'EV Productivity'!$A$9:$A$21,0)),"") | J275: =C275*(D275/$D$319)^$B$4*(E275/$E$319)^$B$5 -> 10.516472 | K275: =LN(J275) -> 2.3529428 | L275: =IF(AND(F275>0,ISNUMBER(G275)),(1-F275)/(1/C275-F275/G275),C275) -> 14.13642 | M275: =IF(AND(F275>0,ISNUMBER(G275)),(D275-F275*H275)/(1-F275),D275) -> 4352.742 | N275: =IF(AND(F275>0,ISNUMBER(G275)),(E275-F275*I275)/(1-F275),E275) -> 130.5904 | O275: =L275*(M275/$M$319)^$E$4*(N275/$N$319)^$E$5 -> 9.8561197 | P275: =LN(O275) -> 2.2880926
A276: Minivan/Van | B276: 1981 | C276: 14.84219 | D276: 4323.985 | E276: 129.0355 | F276: 0 | G276: =IFERROR(INDEX('EV Productivity'!$B$9:$B$21,MATCH(B276,'EV Productivity'!$A$9:$A$21,0)),"") | H276: =IFERROR(INDEX('EV Productivity'!$C$9:$C$21,MATCH(B276,'EV Productivity'!$A$9:$A$21,0)),"") | I276: =IFERROR(INDEX('EV Productivity'!$D$9:$D$21,MATCH(B276,'EV Productivity'!$A$9:$A$21,0)),"") | J276: =C276*(D276/$D$319)^$B$4*(E276/$E$319)^$B$5 -> 10.959888 | K276: =LN(J276) -> 2.3942421 | L276: =IF(AND(F276>0,ISNUMBER(G276)),(1-F276)/(1/C276-F276/G276),C276) -> 14.84219 | M276: =IF(AND(F276>0,ISNUMBER(G276)),(D276-F276*H276)/(1-F276),D276) -> 4323.985 | N276: =IF(AND(F276>0,ISNUMBER(G276)),(E276-F276*I276)/(1-F276),E276) -> 129.0355 | O276: =L276*(M276/$M$319)^$E$4*(N276/$N$319)^$E$5 -> 10.2678 | P276: =LN(O276) -> 2.3290128
A277: Minivan/Van | B277: 1982 | C277: 14.72404 | D277: 4342.08 | E277: 132.2636 | F277: 0 | G277: =IFERROR(INDEX('EV Productivity'!$B$9:$B$21,MATCH(B277,'EV Productivity'!$A$9:$A$21,0)),"") | H277: =IFERROR(INDEX('EV Productivity'!$C$9:$C$21,MATCH(B277,'EV Productivity'!$A$9:$A$21,0)),"") | I277: =IFERROR(INDEX('EV Productivity'!$D$9:$D$21,MATCH(B277,'EV Productivity'!$A$9:$A$21,0)),"") | J277: =C277*(D277/$D$319)^$B$4*(E277/$E$319)^$B$5 -> 10.992978 | K277: =LN(J277) -> 2.3972567 | L277: =IF(AND(F277>0,ISNUMBER(G277)),(1-F277)/(1/C277-F277/G277),C277) -> 14.72404 | M277: =IF(AND(F277>0,ISNUMBER(G277)),(D277-F277*H277)/(1-F277),D277) -> 4342.08 | N277: =IF(AND(F277>0,ISNUMBER(G277)),(E277-F277*I277)/(1-F277),E277) -> 132.2636 | O277: =L277*(M277/$M$319)^$E$4*(N277/$N$319)^$E$5 -> 10.321448 | P277: =LN(O277) -> 2.334224
A278: Minivan/Van | B278: 1983 | C278: 15.06647 | D278: 4414.28 | E278: 136.1429 | F278: 0 | G278: =IFERROR(INDEX('EV Productivity'!$B$9:$B$21,MATCH(B278,'EV Productivity'!$A$9:$A$21,0)),"") | H278: =IFERROR(INDEX('EV Productivity'!$C$9:$C$21,MATCH(B278,'EV Productivity'!$A$9:$A$21,0)),"") | I278: =IFERROR(INDEX('EV Productivity'!$D$9:$D$21,MATCH(B278,'EV Productivity'!$A$9:$A$21,0)),"") | J278: =C278*(D278/$D$319)^$B$4*(E278/$E$319)^$B$5 -> 11.454448 | K278: =LN(J278) -> 2.4383782 | L278: =IF(AND(F278>0,ISNUMBER(G278)),(1-F278)/(1/C278-F278/G278),C278) -> 15.06647 | M278: =IF(AND(F278>0,ISNUMBER(G278)),(D278-F278*H278)/(1-F278),D278) -> 4414.28 | N278: =IF(AND(F278>0,ISNUMBER(G278)),(E278-F278*I278)/(1-F278),E278) -> 136.1429 | O278: =L278*(M278/$M$319)^$E$4*(N278/$N$319)^$E$5 -> 10.763778 | P278: =LN(O278) -> 2.3761866
A279: Minivan/Van | B279: 1984 | C279: 16.11388 | D279: 4074.744 | E279: 126.0343 | F279: 0 | G279: =IFERROR(INDEX('EV Productivity'!$B$9:$B$21,MATCH(B279,'EV Productivity'!$A$9:$A$21,0)),"") | H279: =IFERROR(INDEX('EV Productivity'!$C$9:$C$21,MATCH(B279,'EV Productivity'!$A$9:$A$21,0)),"") | I279: =IFERROR(INDEX('EV Productivity'!$D$9:$D$21,MATCH(B279,'EV Productivity'!$A$9:$A$21,0)),"") | J279: =C279*(D279/$D$319)^$B$4*(E279/$E$319)^$B$5 -> 11.483252 | K279: =LN(J279) -> 2.4408897 | L279: =IF(AND(F279>0,ISNUMBER(G279)),(1-F279)/(1/C279-F279/G279),C279) -> 16.11388 | M279: =IF(AND(F279>0,ISNUMBER(G279)),(D279-F279*H279)/(1-F279),D279) -> 4074.744 | N279: =IF(AND(F279>0,ISNUMBER(G279)),(E279-F279*I279)/(1-F279),E279) -> 126.0343 | O279: =L279*(M279/$M$319)^$E$4*(N279/$N$319)^$E$5 -> 10.824576 | P279: =LN(O279) -> 2.3818191
A280: Minivan/Van | B280: 1985 | C280: 16.54583 | D280: 3975.166 | E280: 129.0611 | F280: 0 | G280: =IFERROR(INDEX('EV Productivity'!$B$9:$B$21,MATCH(B280,'EV Productivity'!$A$9:$A$21,0)),"") | H280: =IFERROR(INDEX('EV Productivity'!$C$9:$C$21,MATCH(B280,'EV Productivity'!$A$9:$A$21,0)),"") | I280: =IFERROR(INDEX('EV Productivity'!$D$9:$D$21,MATCH(B280,'EV Productivity'!$A$9:$A$21,0)),"") | J280: =C280*(D280/$D$319)^$B$4*(E280/$E$319)^$B$5 -> 11.76228 | K280: =LN(J280) -> 2.4648978 | L280: =IF(AND(F280>0,ISNUMBER(G280)),(1-F280)/(1/C280-F280/G280),C280) -> 16.54583 | M280: =IF(AND(F280>0,ISNUMBER(G280)),(D280-F280*H280)/(1-F280),D280) -> 3975.166 | N280: =IF(AND(F280>0,ISNUMBER(G280)),(E280-F280*I280)/(1-F280),E280) -> 129.0611 | O280: =L280*(M280/$M$319)^$E$4*(N280/$N$319)^$E$5 -> 11.158702 | P280: =LN(O280) -> 2.4122196
A281: Minivan/Van | B281: 1986 | C281: 17.46989 | D281: 3997.909 | E281: 127.491 | F281: 0 | G281: =IFERROR(INDEX('EV Productivity'!$B$9:$B$21,MATCH(B281,'EV Productivity'!$A$9:$A$21,0)),"") | H281: =IFERROR(INDEX('EV Productivity'!$C$9:$C$21,MATCH(B281,'EV Productivity'!$A$9:$A$21,0)),"") | I281: =IFERROR(INDEX('EV Productivity'!$D$9:$D$21,MATCH(B281,'EV Productivity'!$A$9:$A$21,0)),"") | J281: =C281*(D281/$D$319)^$B$4*(E281/$E$319)^$B$5 -> 12.3952 | K281: =LN(J281) -> 2.5173093 | L281: =IF(AND(F281>0,ISNUMBER(G281)),(1-F281)/(1/C281-F281/G281),C281) -> 17.46989 | M281: =IF(AND(F281>0,ISNUMBER(G281)),(D281-F281*H281)/(1-F281),D281) -> 3997.909 | N281: =IF(AND(F281>0,ISNUMBER(G281)),(E281-F281*I281)/(1-F281),E281) -> 127.491 | O281: =L281*(M281/$M$319)^$E$4*(N281/$N$319)^$E$5 -> 11.732762 | P281: =LN(O281) -> 2.4623851
... A319: Minivan/Van | B319: 2024 | C319: 26.0971 | D319: 4772.663 | E319: 260.0404 | F319: 0 | G319: =IFERROR(INDEX('EV Productivity'!$B$9:$B$21,MATCH(B319,'EV Productivity'!$A$9:$A$21,0)),"") -> 117.14232 | H319: =IFERROR(INDEX('EV Productivity'!$C$9:$C$21,MATCH(B319,'EV Productivity'!$A$9:$A$21,0)),"") -> 4409.726 | I319: =IFERROR(INDEX('EV Productivity'!$D$9:$D$21,MATCH(B319,'EV Productivity'!$A$9:$A$21,0)),"") -> 420.4574 | J319: =C319*(D319/$D$319)^$B$4*(E319/$E$319)^$B$5 -> 26.0971 | K319: =LN(J319) -> 3.2618242 | L319: =IF(AND(F319>0,ISNUMBER(G319)),(1-F319)/(1/C319-F319/G319),C319) -> 26.0971 | M319: =IF(AND(F319>0,ISNUMBER(G319)),(D319-F319*H319)/(1-F319),D319) -> 4772.663 | N319: =IF(AND(F319>0,ISNUMBER(G319)),(E319-F319*I319)/(1-F319),E319) -> 260.0404 | O319: =L319*(M319/$M$319)^$E$4*(N319/$N$319)^$E$5 -> 26.0971 | P319: =LN(O319) -> 3.2618242

Sheet Reference
A1: Deck numbers next to the cell that produces each one
A3: Deck claim | B3: Deck value | C3: Workbook value (live) | D3: Where
A4: Final CER R-squared | B4: 0.9546 | C4: =CER!C15 -> 0.954622 | D4: CER!C15
A5: Final CER F(4, 1280) | B5: 6731.9 | C5: =CER!C18 -> 6731.8746 | D5: CER!C18
A6: ln(weight) coefficient | B6: -0.4527 | C6: =CER!C8 -> -0.45270912 | D6: CER!C8
A7: ln(horsepower) coefficient | B7: -0.3689 | C7: =CER!C9 -> -0.36894371 | D7: CER!C9
A8: hybrid coefficient | B8: 0.2238 | C8: =CER!C10 -> 0.22375357 | D8: CER!C10
A9: battery-electric coefficient | B9: 1.708 | C9: =CER!C11 -> 1.7079701 | D9: CER!C11
A10: 10% more weight costs (MPG) | B10: -0.045 | C10: =CER!C26 -> -0.045270912 | D10: CER!C26
A11: 10% more horsepower costs (MPG) | B11: -0.037 | C11: =CER!C27 -> -0.036894371 | D11: CER!C27
A12: Hybrid premium | B12: 0.25 | C12: =CER!C28 -> 0.25076276 | D12: CER!C28
A13: Battery-electric premium | B13: 4.52 | C13: =CER!C29 -> 4.5177498 | D13: CER!C29
A14: Share inside the 95% band | B14: 0.94 | C14: =CER!C42 -> 0.9385214 | D14: CER!C42
A15: Combustion-only CER R-squared (spec A) | B15: 0.846 | C15: =Alternatives!C6 -> 0.84603748 | D15: Alternatives!C6
A16: Merged electrified flag R-squared (spec C) | B16: 0.4651 | C16: =Alternatives!C25 -> 0.46508851 | D16: Alternatives!C25
A17: BEV-specific slopes R-squared (spec E) | B17: 0.968 | C17: =Alternatives!C43 -> 0.96804523 | D17: Alternatives!C43
A18: Nested F, merged flag vs two levels | B18: 13798 | C18: =Alternatives!F62 -> 13798.036 | D18: Alternatives!F62
A19: Nested F, footprint | B19: 0.03 | C19: =Alternatives!F61 -> 0.026167688 | D19: Alternatives!F61
A20: Nested F, BEV-specific slopes | B20: 178.66 | C20: =Alternatives!F63 -> 178.65742 | D20: Alternatives!F63
A21: Productivity growth 1975 to 2024 (per year) | B21: 0.0179 | C21: =Normalization!K13 -> 0.017897142 | D21: Normalization!K13
A22: Trend R-squared 1975 to 2024 | B22: 0.98 | C22: =Normalization!K12 -> 0.97954874 | D22: Normalization!K12
A23: 2045 at the 2005 to 2024 rate | B23: 43 | C23: =Normalization!L15 -> 43.019806 | D23: Normalization!L15
A24: 2045 at the 1975 to 2024 rate | B24: 38.1 | C24: =Normalization!K15 -> 38.130569 | D24: Normalization!K15
A25: Normalized 1987 MPG (worked example) | B25: 14.3 | C25: =Normalization!K27 -> 14.346651 | D25: Normalization!K27
A26: S-curve: GDI vs turbo rate ratio (2.1x) | B26: 2.1 | C26: =Diffusion!D6/Diffusion!D5 -> 2.1324042 | D26: Diffusion!D6/D5
A27: S-curve: turbo 10 to 90% years | B27: 15.3 | C27: =Diffusion!H5 -> 15.31167 | D27: Diffusion!H5
A28: S-curve: hybrid 10 to 90% years | B28: 23.9 | C28: =Diffusion!H8 -> 23.882876 | D28: Diffusion!H8
A29: S-curve: BEV 10 to 90% years | B29: 15.1 | C29: =Diffusion!H9 -> 15.1012 | D29: Diffusion!H9
A30: S-curve: hybrid midpoint | B30: 2036 | C30: =Diffusion!F8 -> 2036.2 | D30: Diffusion!F8
A31: S-curve: BEV midpoint | B31: 2032 | C31: =Diffusion!F9 -> 2032.3 | D31: Diffusion!F9
A32: fig43 Sedan/Wagon growth per year (BEVs in) | B32: 0.0186 | C32: ='Class Productivity'!B9 -> 0.018643913 | D32: Class Productivity!B9
A33: fig43 Car SUV growth per year (BEVs in) | B33: 0.0241 | C33: ='Class Productivity'!B10 -> 0.024110537 | D33: Class Productivity!B10
A34: fig43 Truck SUV growth per year (BEVs in) | B34: 0.0208 | C34: ='Class Productivity'!B11 -> 0.020780184 | D34: Class Productivity!B11
A35: fig43 Pickup growth per year (BEVs in) | B35: 0.0184 | C35: ='Class Productivity'!B12 -> 0.018354212 | D35: Class Productivity!B12
A36: fig43 Minivan/Van growth per year (BEVs in) | B36: 0.0206 | C36: ='Class Productivity'!B13 -> 0.020637318 | D36: Class Productivity!B13
A37: fig43 Car SUV R-squared (lowest of the classes) | B37: 0.918 | C37: ='Class Productivity'!C10 -> 0.91822635 | D37: Class Productivity!C10
A38: fig45 fleet ex-BEV growth per year | B38: 0.0186 | C38: ='Class Productivity'!E8 -> 0.018621508 | D38: Class Productivity!E8
A39: fig45 fleet ex-BEV R-squared | B39: 0.984 | C39: ='Class Productivity'!F8 -> 0.9840344 | D39: Class Productivity!F8
A40: fig45 fleet ex-BEV 2045 at trend | B40: 39 | C40: ='Class Productivity'!G8 -> 39.057285 | D40: Class Productivity!G8
A41: fig46 Sedan/Wagon ex-BEV growth per year | B41: 0.0188 | C41: ='Class Productivity'!E9 -> 0.018750132 | D41: Class Productivity!E9
A42: fig46 Car SUV ex-BEV growth per year | B42: 0.0224 | C42: ='Class Productivity'!E10 -> 0.022422856 | D42: Class Productivity!E10
A43: fig46 Truck SUV ex-BEV growth per year | B43: 0.0222 | C43: ='Class Productivity'!E11 -> 0.022235554 | D43: Class Productivity!E11
A44: fig46 Pickup ex-BEV growth per year | B44: 0.0199 | C44: ='Class Productivity'!E12 -> 0.019911905 | D44: Class Productivity!E12
A45: fig46 Minivan/Van ex-BEV growth per year | B45: 0.0222 | C45: ='Class Productivity'!E13 -> 0.022231614 | D45: Class Productivity!E13
A46: fig46 Car SUV ex-BEV R-squared | B46: 0.944 | C46: ='Class Productivity'!F10 -> 0.94440925 | D46: Class Productivity!F10
A47: fig44 Tesla normalized growth per year | B47: 0.0236 | C47: ='EV Productivity'!J12 -> 0.023601099 | D47: EV Productivity!J12
A48: fig44 Tesla trend R-squared | B48: 0.716 | C48: ='EV Productivity'!J11 -> 0.71632056 | D48: EV Productivity!J11
A49: fig44 Tesla 2045 at trend (MPGe-equivalent) | B49: 207 | C49: ='EV Productivity'!J14 -> 207.36049 | D49: EV Productivity!J14
A52: HC1 robust standard errors on the CER sheet (column H) come from 33_pooled_model.py; Excel's LINEST has no robust-error option, so those five numbers are the only typed statistics in the workbook.
